Workbook

Sheet contents
A1: Name | B1: Link to old | C1: Link to new
A2: =RR_v2!A1 -> River Rush | B2: RR | C2: RR_v2
A3: =NS_v2!A1 -> Night Sky (5 Segment) | B3: NS | C3: NS_v2
A4: =J_v2!A1 -> Jigsaw Puzzle | B4: J | C4: J_v2
A5: =TaD_v2!A1 -> Target Day | B5: TaD | C5: TaD_v2
A6: =c_day_v2!A1 -> Daily Rewards - NEW | B6: c_day | C6: c_day_v2
A7: =c_saga_v2!A1 -> Saga Progression - NEW | B7: c_saga | C7: c_saga_v2
A8: =F_v2!A1 -> Flock Flurry | B8: F | C8: F_v2
A9: =Ki_v2!A1 -> Kite Festival | B9: Ki | C9: Ki_v2
A10: =BB_v2!A1 -> Bomb's Ballet | B10: BB | C10: BB_v2
A11: =Ph_v2!A1 -> Photoshoot | B11: Ph | C11: Ph_v2
A12: =Race_v2!A1 -> All LB Challenges | B12: Race | C12: Race_v2
A13: =HH_v2!A1 -> Hatchling Hideaway | B13: HH | C13: HH_v2

Sheet cal_parsed
A1: calendar | B1: event | C1: start | D1: dur
A2: cal_curr | B2: Target Day | C2: 10 | D2: 7
A3: cal_curr | B3: Target Day | C3: 24 | D3: 7
A4: cal_curr | B4: Target Day | C4: 1 | D4: 2
A5: cal_curr | B5: Top Players Leaderboard | C5: 6 | D5: 7
A6: cal_curr | B6: Top Players Leaderboard | C6: 13 | D6: 7
A7: cal_curr | B7: Top Players Leaderboard | C7: 20 | D7: 7
A8: cal_curr | B8: Top Players Leaderboard | C8: 27 | D8: 7
A9: cal_curr | B9: Top Players Leaderboard | C9: 1 | D9: 5
A10: cal_curr | B10: Jigsaw Puzzle | C10: 1 | D10: 3
A11: cal_curr | B11: Jigsaw Puzzle | C11: 14 | D11: 4
A12: cal_curr | B12: Jigsaw Puzzle | C12: 28 | D12: 4
A13: cal_curr | B13: Photoshoot | C13: 7 | D13: 4
... A284: cal_new | B284: Night Sky | C284: 33 | D284: 1

Sheet c_saga
A1: Saga Progression - OLD
B3: 0-9 | D3: 10-19 | F3: 20-39 | H3: 40-99 | J3: 100+ | W3: all segs
A4: Node | B4: Levels Req | C4: HC Reward | D4: Levels Req | E4: HC Reward | F4: Levels Req | G4: HC Reward | H4: Levels Req | I4: HC Reward | J4: Levels Req | K4: HC Reward | M4: 👁 | T4: Original | U4: Old Nerf | W4: SPT | X4: Red | Y4: Chuck | Z4: Bomb | AA4: Slingshot | AB4: Shuffle | AC4: Comet | AD4: Unlimited Lives | AE4: Unlimited Red | AF4: Unlimited Chuck | AG4: Unlimited Bomb | AH4: Coin Val | AJ4: cur | AK4: image
A5: 1 | B5: 10 | C5: 10 | D5: 10 | E5: 10 | F5: 10 | G5: 10 | H5: 10 | I5: 10 | J5: 10 | K5: 10 | M5: =IFERROR(__xludf.DUMMYFUNCTION("LET( names, HSTACK(""Coins"", W$4:AG$4), amounts, HSTACK(C5, W5:AG5), lookupNames, $AJ$5:$AJ$16, lookupImages, $AK$5:$AK$16, imgs, MAP(names, LAMBDA(n, XLOOKUP(n, lookupNames, lookupImages))), keepImgs, FILTER(imgs, amounts<>0), keepAmounts,"&" FILTER(amounts, amounts<>0), MAKEARRAY( 1, COLUMNS(keepAmounts)*2, LAMBDA(r,c, IF( ISODD(c), INDEX(keepImgs, 1, ROUNDUP(c/2)), INDEX(keepAmounts, 1, c/2) ) ) ) )"),"") | N5: =IFERROR(__xludf.DUMMYFUNCTION("""COMPUTED_VALUE"""),10.0) -> 10 | O5: =IFERROR(__xludf.DUMMYFUNCTION("""COMPUTED_VALUE"""),"") | P5: =IFERROR(__xludf.DUMMYFUNCTION("""COMPUTED_VALUE"""),1.0) -> 1 | Q5: =IFERROR(__xludf.DUMMYFUNCTION("""COMPUTED_VALUE"""),"") | R5: =IFERROR(__xludf.DUMMYFUNCTION("""COMPUTED_VALUE"""),15.0) -> 15 | T5: 15 | U5: 10 | W5: 0 | X5: 1 | Y5: 0 | Z5: 0 | AA5: 0 | AB5: 0 | AC5: 0 | AD5: 15 | AE5: 0 | AF5: 0 | AG5: 0 | AH5: =SUMPRODUCT(W5:AG5, {0,33,50,67,167,67,50,4.17,7.56,12.17,16.22}) -> 95.55 | AI5: 100 | AJ5: Coins | AL5: =AH5-AI5 -> -4.45
A6: 2 | B6: 10 | C6: 0 | D6: 10 | E6: 0 | F6: 10 | G6: 0 | H6: 10 | I6: 0 | J6: 10 | K6: 0 | M6: =IFERROR(__xludf.DUMMYFUNCTION("LET( names, HSTACK(""Coins"", W$4:AG$4), amounts, HSTACK(C6, W6:AG6), lookupNames, $AJ$5:$AJ$16, lookupImages, $AK$5:$AK$16, imgs, MAP(names, LAMBDA(n, XLOOKUP(n, lookupNames, lookupImages))), keepImgs, FILTER(imgs, amounts<>0), keepAmounts,"&" FILTER(amounts, amounts<>0), MAKEARRAY( 1, COLUMNS(keepAmounts)*2, LAMBDA(r,c, IF( ISODD(c), INDEX(keepImgs, 1, ROUNDUP(c/2)), INDEX(keepAmounts, 1, c/2) ) ) ) )"),"") | N6: =IFERROR(__xludf.DUMMYFUNCTION("""COMPUTED_VALUE"""),1.0) -> 1 | O6: =IFERROR(__xludf.DUMMYFUNCTION("""COMPUTED_VALUE"""),"") | P6: =IFERROR(__xludf.DUMMYFUNCTION("""COMPUTED_VALUE"""),1.0) -> 1 | Q6: =IFERROR(__xludf.DUMMYFUNCTION("""COMPUTED_VALUE"""),"") | R6: =IFERROR(__xludf.DUMMYFUNCTION("""COMPUTED_VALUE"""),15.0) -> 15 | T6: 15 | U6: 10 | W6: 0 | X6: 1 | Y6: 1 | Z6: 0 | AA6: 0 | AB6: 0 | AC6: 0 | AD6: 15 | AE6: 0 | AF6: 0 | AG6: 0 | AH6: =SUMPRODUCT(W6:AG6, {0,33,50,67,167,67,50,4.17,7.56,12.17,16.22}) -> 145.55 | AI6: 112.55 | AJ6: {=TRANSPOSE(W4:AG4)} -> SPT | AL6: =AH6-AI6 -> 33
A7: 3 | B7: 10 | C7: 10 | D7: 10 | E7: 10 | F7: 10 | G7: 10 | H7: 10 | I7: 10 | J7: 10 | K7: 10 | M7: =IFERROR(__xludf.DUMMYFUNCTION("LET( names, HSTACK(""Coins"", W$4:AG$4), amounts, HSTACK(C7, W7:AG7), lookupNames, $AJ$5:$AJ$16, lookupImages, $AK$5:$AK$16, imgs, MAP(names, LAMBDA(n, XLOOKUP(n, lookupNames, lookupImages))), keepImgs, FILTER(imgs, amounts<>0), keepAmounts,"&" FILTER(amounts, amounts<>0), MAKEARRAY( 1, COLUMNS(keepAmounts)*2, LAMBDA(r,c, IF( ISODD(c), INDEX(keepImgs, 1, ROUNDUP(c/2)), INDEX(keepAmounts, 1, c/2) ) ) ) )"),"") | N7: =IFERROR(__xludf.DUMMYFUNCTION("""COMPUTED_VALUE"""),10.0) -> 10 | O7: =IFERROR(__xludf.DUMMYFUNCTION("""COMPUTED_VALUE"""),"") | P7: =IFERROR(__xludf.DUMMYFUNCTION("""COMPUTED_VALUE"""),1.0) -> 1 | Q7: =IFERROR(__xludf.DUMMYFUNCTION("""COMPUTED_VALUE"""),"") | R7: =IFERROR(__xludf.DUMMYFUNCTION("""COMPUTED_VALUE"""),15.0) -> 15 | T7: 15 | U7: 10 | W7: 0 | X7: 0 | Y7: 0 | Z7: 1 | AA7: 0 | AB7: 0 | AC7: 0 | AD7: 15 | AE7: 0 | AF7: 0 | AG7: 0 | AH7: =SUMPRODUCT(W7:AG7, {0,33,50,67,167,67,50,4.17,7.56,12.17,16.22}) -> 129.55 | AI7: 95.55 | AJ7: Red | AL7: =AH7-AI7 -> 34
A8: 4 | B8: 10 | C8: 0 | D8: 10 | E8: 0 | F8: 10 | G8: 0 | H8: 10 | I8: 0 | J8: 10 | K8: 0 | M8: =IFERROR(__xludf.DUMMYFUNCTION("LET( names, HSTACK(""Coins"", W$4:AG$4), amounts, HSTACK(C8, W8:AG8), lookupNames, $AJ$5:$AJ$16, lookupImages, $AK$5:$AK$16, imgs, MAP(names, LAMBDA(n, XLOOKUP(n, lookupNames, lookupImages))), keepImgs, FILTER(imgs, amounts<>0), keepAmounts,"&" FILTER(amounts, amounts<>0), MAKEARRAY( 1, COLUMNS(keepAmounts)*2, LAMBDA(r,c, IF( ISODD(c), INDEX(keepImgs, 1, ROUNDUP(c/2)), INDEX(keepAmounts, 1, c/2) ) ) ) )"),"") | N8: =IFERROR(__xludf.DUMMYFUNCTION("""COMPUTED_VALUE"""),1.0) -> 1 | O8: =IFERROR(__xludf.DUMMYFUNCTION("""COMPUTED_VALUE"""),"") | P8: =IFERROR(__xludf.DUMMYFUNCTION("""COMPUTED_VALUE"""),1.0) -> 1 | Q8: =IFERROR(__xludf.DUMMYFUNCTION("""COMPUTED_VALUE"""),"") | R8: =IFERROR(__xludf.DUMMYFUNCTION("""COMPUTED_VALUE"""),15.0) -> 15 | T8: 20 | U8: 10 | W8: 0 | X8: 1 | Y8: 0 | Z8: 0 | AA8: 0 | AB8: 1 | AC8: 0 | AD8: 15 | AE8: 0 | AF8: 0 | AG8: 0 | AH8: =SUMPRODUCT(W8:AG8, {0,33,50,67,167,67,50,4.17,7.56,12.17,16.22}) -> 162.55 | AI8: 95.55 | AJ8: Chuck | AL8: =AH8-AI8 -> 67
A9: 5 | B9: 10 | C9: 10 | D9: 10 | E9: 10 | F9: 10 | G9: 10 | H9: 10 | I9: 10 | J9: 10 | K9: 10 | M9: =IFERROR(__xludf.DUMMYFUNCTION("LET( names, HSTACK(""Coins"", W$4:AG$4), amounts, HSTACK(C9, W9:AG9), lookupNames, $AJ$5:$AJ$16, lookupImages, $AK$5:$AK$16, imgs, MAP(names, LAMBDA(n, XLOOKUP(n, lookupNames, lookupImages))), keepImgs, FILTER(imgs, amounts<>0), keepAmounts,"&" FILTER(amounts, amounts<>0), MAKEARRAY( 1, COLUMNS(keepAmounts)*2, LAMBDA(r,c, IF( ISODD(c), INDEX(keepImgs, 1, ROUNDUP(c/2)), INDEX(keepAmounts, 1, c/2) ) ) ) )"),"") | N9: =IFERROR(__xludf.DUMMYFUNCTION("""COMPUTED_VALUE"""),10.0) -> 10 | O9: =IFERROR(__xludf.DUMMYFUNCTION("""COMPUTED_VALUE"""),"") | P9: =IFERROR(__xludf.DUMMYFUNCTION("""COMPUTED_VALUE"""),1.0) -> 1 | Q9: =IFERROR(__xludf.DUMMYFUNCTION("""COMPUTED_VALUE"""),"") | R9: =IFERROR(__xludf.DUMMYFUNCTION("""COMPUTED_VALUE"""),15.0) -> 15 | T9: 20 | U9: 10 | W9: 0 | X9: 0 | Y9: 0 | Z9: 1 | AA9: 0 | AB9: 0 | AC9: 0 | AD9: 15 | AE9: 0 | AF9: 0 | AG9: 0 | AH9: =SUMPRODUCT(W9:AG9, {0,33,50,67,167,67,50,4.17,7.56,12.17,16.22}) -> 129.55 | AI9: 100 | AJ9: Bomb | AL9: =AH9-AI9 -> 29.55
A10: 6 | B10: 10 | C10: 0 | D10: 10 | E10: 0 | F10: 10 | G10: 0 | H10: 10 | I10: 0 | J10: 10 | K10: 0 | M10: =IFERROR(__xludf.DUMMYFUNCTION("LET( names, HSTACK(""Coins"", W$4:AG$4), amounts, HSTACK(C10, W10:AG10), lookupNames, $AJ$5:$AJ$16, lookupImages, $AK$5:$AK$16, imgs, MAP(names, LAMBDA(n, XLOOKUP(n, lookupNames, lookupImages))), keepImgs, FILTER(imgs, amounts<>0), keepAmoun"&"ts, FILTER(amounts, amounts<>0), MAKEARRAY( 1, COLUMNS(keepAmounts)*2, LAMBDA(r,c, IF( ISODD(c), INDEX(keepImgs, 1, ROUNDUP(c/2)), INDEX(keepAmounts, 1, c/2) ) ) ) )"),"") | N10: =IFERROR(__xludf.DUMMYFUNCTION("""COMPUTED_VALUE"""),1.0) -> 1 | O10: =IFERROR(__xludf.DUMMYFUNCTION("""COMPUTED_VALUE"""),"") | P10: =IFERROR(__xludf.DUMMYFUNCTION("""COMPUTED_VALUE"""),1.0) -> 1 | Q10: =IFERROR(__xludf.DUMMYFUNCTION("""COMPUTED_VALUE"""),"") | R10: =IFERROR(__xludf.DUMMYFUNCTION("""COMPUTED_VALUE"""),20.0) -> 20 | T10: 20 | U10: 15 | W10: 0 | X10: 0 | Y10: 1 | Z10: 0 | AA10: 0 | AB10: 0 | AC10: 1 | AD10: 20 | AE10: 0 | AF10: 0 | AG10: 0 | AH10: =SUMPRODUCT(W10:AG10, {0,33,50,67,167,67,50,4.17,7.56,12.17,16.22}) -> 183.4 | AI10: 229.55 | AJ10: Slingshot | AL10: =AH10-AI10 -> -46.15
A11: 7 | B11: 10 | C11: 10 | D11: 10 | E11: 10 | F11: 10 | G11: 10 | H11: 10 | I11: 10 | J11: 10 | K11: 10 | M11: =IFERROR(__xludf.DUMMYFUNCTION("LET( names, HSTACK(""Coins"", W$4:AG$4), amounts, HSTACK(C11, W11:AG11), lookupNames, $AJ$5:$AJ$16, lookupImages, $AK$5:$AK$16, imgs, MAP(names, LAMBDA(n, XLOOKUP(n, lookupNames, lookupImages))), keepImgs, FILTER(imgs, amounts<>0), keepAmoun"&"ts, FILTER(amounts, amounts<>0), MAKEARRAY( 1, COLUMNS(keepAmounts)*2, LAMBDA(r,c, IF( ISODD(c), INDEX(keepImgs, 1, ROUNDUP(c/2)), INDEX(keepAmounts, 1, c/2) ) ) ) )"),"") | N11: =IFERROR(__xludf.DUMMYFUNCTION("""COMPUTED_VALUE"""),10.0) -> 10 | O11: =IFERROR(__xludf.DUMMYFUNCTION("""COMPUTED_VALUE"""),"") | P11: =IFERROR(__xludf.DUMMYFUNCTION("""COMPUTED_VALUE"""),1.0) -> 1 | Q11: =IFERROR(__xludf.DUMMYFUNCTION("""COMPUTED_VALUE"""),"") | R11: =IFERROR(__xludf.DUMMYFUNCTION("""COMPUTED_VALUE"""),20.0) -> 20 | T11: 25 | U11: 15 | W11: 0 | X11: 0 | Y11: 0 | Z11: 1 | AA11: 0 | AB11: 0 | AC11: 0 | AD11: 20 | AE11: 0 | AF11: 0 | AG11: 0 | AH11: =SUMPRODUCT(W11:AG11, {0,33,50,67,167,67,50,4.17,7.56,12.17,16.22}) -> 150.4 | AI11: 192.1 | AJ11: Shuffle | AL11: =AH11-AI11 -> -41.7
A12: 8 | B12: 10 | C12: 0 | D12: 10 | E12: 0 | F12: 10 | G12: 0 | H12: 10 | I12: 0 | J12: 10 | K12: 0 | M12: =IFERROR(__xludf.DUMMYFUNCTION("LET( names, HSTACK(""Coins"", W$4:AG$4), amounts, HSTACK(C12, W12:AG12), lookupNames, $AJ$5:$AJ$16, lookupImages, $AK$5:$AK$16, imgs, MAP(names, LAMBDA(n, XLOOKUP(n, lookupNames, lookupImages))), keepImgs, FILTER(imgs, amounts<>0), keepAmoun"&"ts, FILTER(amounts, amounts<>0), MAKEARRAY( 1, COLUMNS(keepAmounts)*2, LAMBDA(r,c, IF( ISODD(c), INDEX(keepImgs, 1, ROUNDUP(c/2)), INDEX(keepAmounts, 1, c/2) ) ) ) )"),"") | N12: =IFERROR(__xludf.DUMMYFUNCTION("""COMPUTED_VALUE"""),1.0) -> 1 | O12: =IFERROR(__xludf.DUMMYFUNCTION("""COMPUTED_VALUE"""),"") | P12: =IFERROR(__xludf.DUMMYFUNCTION("""COMPUTED_VALUE"""),1.0) -> 1 | Q12: =IFERROR(__xludf.DUMMYFUNCTION("""COMPUTED_VALUE"""),"") | R12: =IFERROR(__xludf.DUMMYFUNCTION("""COMPUTED_VALUE"""),30.0) -> 30 | T12: 25 | U12: 15 | W12: 0 | X12: 0 | Y12: 1 | Z12: 0 | AA12: 1 | AB12: 0 | AC12: 0 | AD12: 30 | AE12: 0 | AF12: 0 | AG12: 0 | AH12: =SUMPRODUCT(W12:AG12, {0,33,50,67,167,67,50,4.17,7.56,12.17,16.22}) -> 342.1 | AI12: 217 | AJ12: Comet | AL12: =AH12-AI12 -> 125.1
A13: 9 | B13: 10 | C13: 10 | D13: 10 | E13: 10 | F13: 10 | G13: 10 | H13: 10 | I13: 10 | J13: 10 | K13: 10 | M13: =IFERROR(__xludf.DUMMYFUNCTION("LET( names, HSTACK(""Coins"", W$4:AG$4), amounts, HSTACK(C13, W13:AG13), lookupNames, $AJ$5:$AJ$16, lookupImages, $AK$5:$AK$16, imgs, MAP(names, LAMBDA(n, XLOOKUP(n, lookupNames, lookupImages))), keepImgs, FILTER(imgs, amounts<>0), keepAmoun"&"ts, FILTER(amounts, amounts<>0), MAKEARRAY( 1, COLUMNS(keepAmounts)*2, LAMBDA(r,c, IF( ISODD(c), INDEX(keepImgs, 1, ROUNDUP(c/2)), INDEX(keepAmounts, 1, c/2) ) ) ) )"),"") | N13: =IFERROR(__xludf.DUMMYFUNCTION("""COMPUTED_VALUE"""),10.0) -> 10 | O13: =IFERROR(__xludf.DUMMYFUNCTION("""COMPUTED_VALUE"""),"") | P13: =IFERROR(__xludf.DUMMYFUNCTION("""COMPUTED_VALUE"""),1.0) -> 1 | Q13: =IFERROR(__xludf.DUMMYFUNCTION("""COMPUTED_VALUE"""),"") | R13: =IFERROR(__xludf.DUMMYFUNCTION("""COMPUTED_VALUE"""),60.0) -> 60 | T13: 25 | U13: 15 | W13: 0 | X13: 0 | Y13: 0 | Z13: 0 | AA13: 0 | AB13: 1 | AC13: 0 | AD13: 60 | AE13: 0 | AF13: 0 | AG13: 0 | AH13: =SUMPRODUCT(W13:AG13, {0,33,50,67,167,67,50,4.17,7.56,12.17,16.22}) -> 317.2 | AI13: 300.2 | AJ13: Unlimited Lives | AL13: =AH13-AI13 -> 17
A14: 10 | B14: 10 | C14: 25 | D14: 10 | E14: 25 | F14: 10 | G14: 25 | H14: 10 | I14: 25 | J14: 10 | K14: 25 | M14: =IFERROR(__xludf.DUMMYFUNCTION("LET( names, HSTACK(""Coins"", W$4:AG$4), amounts, HSTACK(C14, W14:AG14), lookupNames, $AJ$5:$AJ$16, lookupImages, $AK$5:$AK$16, imgs, MAP(names, LAMBDA(n, XLOOKUP(n, lookupNames, lookupImages))), keepImgs, FILTER(imgs, amounts<>0), keepAmoun"&"ts, FILTER(amounts, amounts<>0), MAKEARRAY( 1, COLUMNS(keepAmounts)*2, LAMBDA(r,c, IF( ISODD(c), INDEX(keepImgs, 1, ROUNDUP(c/2)), INDEX(keepAmounts, 1, c/2) ) ) ) )"),"") | N14: =IFERROR(__xludf.DUMMYFUNCTION("""COMPUTED_VALUE"""),25.0) -> 25 | O14: =IFERROR(__xludf.DUMMYFUNCTION("""COMPUTED_VALUE"""),"") | P14: =IFERROR(__xludf.DUMMYFUNCTION("""COMPUTED_VALUE"""),1.0) -> 1 | Q14: =IFERROR(__xludf.DUMMYFUNCTION("""COMPUTED_VALUE"""),"") | R14: =IFERROR(__xludf.DUMMYFUNCTION("""COMPUTED_VALUE"""),60.0) -> 60 | T14: 30 | U14: 20 | W14: 0 | X14: 0 | Y14: 0 | Z14: 0 | AA14: 0 | AB14: 0 | AC14: 1 | AD14: 60 | AE14: 0 | AF14: 0 | AG14: 0 | AH14: =SUMPRODUCT(W14:AG14, {0,33,50,67,167,67,50,4.17,7.56,12.17,16.22}) -> 300.2 | AI14: 117 | AJ14: Unlimited Red | AL14: =AH14-AI14 -> 183.2
AJ15: Unlimited Chuck
A16: Total per cycle | B16: =SUM(B5:B14) -> 100 | C16: =SUM(C5:C14) -> 75 | D16: =SUM(D5:D14) -> 100 | E16: =SUM(E5:E14) -> 75 | F16: =SUM(F5:F14) -> 100 | G16: =SUM(G5:G14) -> 75 | H16: =SUM(H5:H14) -> 100 | I16: =SUM(I5:I14) -> 75 | ... K16: =SUM(K5:K14) -> 75 | T16: =SUM(T5:T14) -> 210 | U16: =SUM(U5:U14) -> 130 | AJ16: Unlimited Bomb
A17: HC per level | C17: =C16/B16 -> 0.75 | E17: =E16/D16 -> 0.75 | G17: =G16/F16 -> 0.75 | I17: =I16/H16 -> 0.75 | K17: =K16/J16 -> 0.75 | T17: =T16/$J$16 -> 2.1 | U17: =U16/$J$16 -> 1.3
T19: =T16/saga_progression_old!$C$15 -> #REF! | U19: =U16/saga_progression_old!$C$15 -> #REF!

Sheet c_saga_v2
A1: Saga Progression - NEW
B3: 0-9 | D3: 10-19 | F3: 20-39 | H3: 40-99 | J3: 100+ | W3: all segs
A4: Node | B4: Levels Req | C4: HC Reward | D4: Levels Req | E4: HC Reward | F4: Levels Req | G4: HC Reward | H4: Levels Req | I4: HC Reward | J4: Levels Req | K4: HC Reward | M4: 👁 | T4: Original | U4: Old Nerf | W4: SPT | X4: Red | Y4: Chuck | Z4: Bomb | AA4: Slingshot | AB4: Shuffle | AC4: Comet | AD4: Unlimited Lives | AE4: Unlimited Red | AF4: Unlimited Chuck | AG4: Unlimited Bomb | AH4: Coin Val | AJ4: cur | AK4: image
A5: 1 | B5: 10 | C5: 10 | D5: 10 | E5: 10 | F5: 10 | G5: 10 | H5: 10 | I5: 10 | J5: 10 | K5: 10 | M5: =IFERROR(__xludf.DUMMYFUNCTION("LET( names, HSTACK(""Coins"", W$4:AG$4), amounts, HSTACK(C5, W5:AG5), lookupNames, $AJ$5:$AJ$16, lookupImages, $AK$5:$AK$16, imgs, MAP(names, LAMBDA(n, XLOOKUP(n, lookupNames, lookupImages))), keepImgs, FILTER(imgs, amounts<>0), keepAmounts,"&" FILTER(amounts, amounts<>0), MAKEARRAY( 1, COLUMNS(keepAmounts)*2, LAMBDA(r,c, IF( ISODD(c), INDEX(keepImgs, 1, ROUNDUP(c/2)), INDEX(keepAmounts, 1, c/2) ) ) ) )"),"") | N5: =IFERROR(__xludf.DUMMYFUNCTION("""COMPUTED_VALUE"""),10.0) -> 10 | O5: =IFERROR(__xludf.DUMMYFUNCTION("""COMPUTED_VALUE"""),"") | P5: =IFERROR(__xludf.DUMMYFUNCTION("""COMPUTED_VALUE"""),15.0) -> 15 | T5: 15 | U5: 10 | W5: 0 | X5: 0 | Y5: 0 | Z5: 0 | AA5: 0 | AB5: 0 | AC5: 0 | AD5: 15 | AE5: 0 | AF5: 0 | AG5: 0 | AH5: =SUMPRODUCT(W5:AG5, {0,33,50,67,167,67,50,4.17,7.56,12.17,16.22}) -> 62.55 | AI5: 100 | AJ5: Coins | AL5: =AH5-AI5 -> -37.45
A6: 2 | B6: 10 | C6: 0 | D6: 10 | E6: 0 | F6: 10 | G6: 0 | H6: 10 | I6: 0 | J6: 10 | K6: 0 | M6: =IFERROR(__xludf.DUMMYFUNCTION("LET( names, HSTACK(""Coins"", W$4:AG$4), amounts, HSTACK(C6, W6:AG6), lookupNames, $AJ$5:$AJ$16, lookupImages, $AK$5:$AK$16, imgs, MAP(names, LAMBDA(n, XLOOKUP(n, lookupNames, lookupImages))), keepImgs, FILTER(imgs, amounts<>0), keepAmounts,"&" FILTER(amounts, amounts<>0), MAKEARRAY( 1, COLUMNS(keepAmounts)*2, LAMBDA(r,c, IF( ISODD(c), INDEX(keepImgs, 1, ROUNDUP(c/2)), INDEX(keepAmounts, 1, c/2) ) ) ) )"),"") | N6: =IFERROR(__xludf.DUMMYFUNCTION("""COMPUTED_VALUE"""),1.0) -> 1 | O6: =IFERROR(__xludf.DUMMYFUNCTION("""COMPUTED_VALUE"""),"") | P6: =IFERROR(__xludf.DUMMYFUNCTION("""COMPUTED_VALUE"""),15.0) -> 15 | T6: 15 | U6: 10 | W6: 0 | X6: 1 | Y6: 0 | Z6: 0 | AA6: 0 | AB6: 0 | AC6: 0 | AD6: 15 | AE6: 0 | AF6: 0 | AG6: 0 | AH6: =SUMPRODUCT(W6:AG6, {0,33,50,67,167,67,50,4.17,7.56,12.17,16.22}) -> 95.55 | AI6: 112.55 | AJ6: {=TRANSPOSE(W4:AG4)} -> SPT | AL6: =AH6-AI6 -> -17
A7: 3 | B7: 10 | C7: 10 | D7: 10 | E7: 10 | F7: 10 | G7: 10 | H7: 10 | I7: 10 | J7: 10 | K7: 10 | M7: =IFERROR(__xludf.DUMMYFUNCTION("LET( names, HSTACK(""Coins"", W$4:AG$4), amounts, HSTACK(C7, W7:AG7), lookupNames, $AJ$5:$AJ$16, lookupImages, $AK$5:$AK$16, imgs, MAP(names, LAMBDA(n, XLOOKUP(n, lookupNames, lookupImages))), keepImgs, FILTER(imgs, amounts<>0), keepAmounts,"&" FILTER(amounts, amounts<>0), MAKEARRAY( 1, COLUMNS(keepAmounts)*2, LAMBDA(r,c, IF( ISODD(c), INDEX(keepImgs, 1, ROUNDUP(c/2)), INDEX(keepAmounts, 1, c/2) ) ) ) )"),"") | N7: =IFERROR(__xludf.DUMMYFUNCTION("""COMPUTED_VALUE"""),10.0) -> 10 | O7: =IFERROR(__xludf.DUMMYFUNCTION("""COMPUTED_VALUE"""),"") | P7: =IFERROR(__xludf.DUMMYFUNCTION("""COMPUTED_VALUE"""),15.0) -> 15 | T7: 15 | U7: 10 | W7: 0 | X7: 0 | Y7: 0 | Z7: 0 | AA7: 0 | AB7: 0 | AC7: 0 | AD7: 15 | AE7: 0 | AF7: 0 | AG7: 0 | AH7: =SUMPRODUCT(W7:AG7, {0,33,50,67,167,67,50,4.17,7.56,12.17,16.22}) -> 62.55 | AI7: 95.55 | AJ7: Red | AL7: =AH7-AI7 -> -33
A8: 4 | B8: 10 | C8: 0 | D8: 10 | E8: 0 | F8: 10 | G8: 0 | H8: 10 | I8: 0 | J8: 10 | K8: 0 | M8: =IFERROR(__xludf.DUMMYFUNCTION("LET( names, HSTACK(""Coins"", W$4:AG$4), amounts, HSTACK(C8, W8:AG8), lookupNames, $AJ$5:$AJ$16, lookupImages, $AK$5:$AK$16, imgs, MAP(names, LAMBDA(n, XLOOKUP(n, lookupNames, lookupImages))), keepImgs, FILTER(imgs, amounts<>0), keepAmounts,"&" FILTER(amounts, amounts<>0), MAKEARRAY( 1, COLUMNS(keepAmounts)*2, LAMBDA(r,c, IF( ISODD(c), INDEX(keepImgs, 1, ROUNDUP(c/2)), INDEX(keepAmounts, 1, c/2) ) ) ) )"),"") | N8: =IFERROR(__xludf.DUMMYFUNCTION("""COMPUTED_VALUE"""),1.0) -> 1 | O8: =IFERROR(__xludf.DUMMYFUNCTION("""COMPUTED_VALUE"""),"") | P8: =IFERROR(__xludf.DUMMYFUNCTION("""COMPUTED_VALUE"""),15.0) -> 15 | T8: 20 | U8: 10 | W8: 0 | X8: 1 | Y8: 0 | Z8: 0 | AA8: 0 | AB8: 0 | AC8: 0 | AD8: 15 | AE8: 0 | AF8: 0 | AG8: 0 | AH8: =SUMPRODUCT(W8:AG8, {0,33,50,67,167,67,50,4.17,7.56,12.17,16.22}) -> 95.55 | AI8: 95.55 | AJ8: Chuck | AL8: =AH8-AI8 -> 0
A9: 5 | B9: 10 | C9: 0 | D9: 10 | E9: 0 | F9: 10 | G9: 0 | H9: 10 | I9: 0 | J9: 10 | K9: 0 | M9: =IFERROR(__xludf.DUMMYFUNCTION("LET( names, HSTACK(""Coins"", W$4:AG$4), amounts, HSTACK(C9, W9:AG9), lookupNames, $AJ$5:$AJ$16, lookupImages, $AK$5:$AK$16, imgs, MAP(names, LAMBDA(n, XLOOKUP(n, lookupNames, lookupImages))), keepImgs, FILTER(imgs, amounts<>0), keepAmounts,"&" FILTER(amounts, amounts<>0), MAKEARRAY( 1, COLUMNS(keepAmounts)*2, LAMBDA(r,c, IF( ISODD(c), INDEX(keepImgs, 1, ROUNDUP(c/2)), INDEX(keepAmounts, 1, c/2) ) ) ) )"),"") | N9: =IFERROR(__xludf.DUMMYFUNCTION("""COMPUTED_VALUE"""),1.0) -> 1 | O9: =IFERROR(__xludf.DUMMYFUNCTION("""COMPUTED_VALUE"""),"") | P9: =IFERROR(__xludf.DUMMYFUNCTION("""COMPUTED_VALUE"""),15.0) -> 15 | T9: 20 | U9: 10 | W9: 0 | X9: 0 | Y9: 1 | Z9: 0 | AA9: 0 | AB9: 0 | AC9: 0 | AD9: 15 | AE9: 0 | AF9: 0 | AG9: 0 | AH9: =SUMPRODUCT(W9:AG9, {0,33,50,67,167,67,50,4.17,7.56,12.17,16.22}) -> 112.55 | AI9: 100 | AJ9: Bomb | AL9: =AH9-AI9 -> 12.55
A10: 6 | B10: 10 | C10: 0 | D10: 10 | E10: 0 | F10: 10 | G10: 0 | H10: 10 | I10: 0 | J10: 10 | K10: 0 | M10: =IFERROR(__xludf.DUMMYFUNCTION("LET( names, HSTACK(""Coins"", W$4:AG$4), amounts, HSTACK(C10, W10:AG10), lookupNames, $AJ$5:$AJ$16, lookupImages, $AK$5:$AK$16, imgs, MAP(names, LAMBDA(n, XLOOKUP(n, lookupNames, lookupImages))), keepImgs, FILTER(imgs, amounts<>0), keepAmoun"&"ts, FILTER(amounts, amounts<>0), MAKEARRAY( 1, COLUMNS(keepAmounts)*2, LAMBDA(r,c, IF( ISODD(c), INDEX(keepImgs, 1, ROUNDUP(c/2)), INDEX(keepAmounts, 1, c/2) ) ) ) )"),"") | N10: =IFERROR(__xludf.DUMMYFUNCTION("""COMPUTED_VALUE"""),1.0) -> 1 | O10: =IFERROR(__xludf.DUMMYFUNCTION("""COMPUTED_VALUE"""),"") | P10: =IFERROR(__xludf.DUMMYFUNCTION("""COMPUTED_VALUE"""),20.0) -> 20 | T10: 20 | U10: 15 | W10: 0 | X10: 0 | Y10: 1 | Z10: 0 | AA10: 0 | AB10: 0 | AC10: 0 | AD10: 20 | AE10: 0 | AF10: 0 | AG10: 0 | AH10: =SUMPRODUCT(W10:AG10, {0,33,50,67,167,67,50,4.17,7.56,12.17,16.22}) -> 133.4 | AI10: 229.55 | AJ10: Slingshot | AL10: =AH10-AI10 -> -96.15
A11: 7 | B11: 10 | C11: 10 | D11: 10 | E11: 10 | F11: 10 | G11: 10 | H11: 10 | I11: 10 | J11: 10 | K11: 10 | M11: =IFERROR(__xludf.DUMMYFUNCTION("LET( names, HSTACK(""Coins"", W$4:AG$4), amounts, HSTACK(C11, W11:AG11), lookupNames, $AJ$5:$AJ$16, lookupImages, $AK$5:$AK$16, imgs, MAP(names, LAMBDA(n, XLOOKUP(n, lookupNames, lookupImages))), keepImgs, FILTER(imgs, amounts<>0), keepAmoun"&"ts, FILTER(amounts, amounts<>0), MAKEARRAY( 1, COLUMNS(keepAmounts)*2, LAMBDA(r,c, IF( ISODD(c), INDEX(keepImgs, 1, ROUNDUP(c/2)), INDEX(keepAmounts, 1, c/2) ) ) ) )"),"") | N11: =IFERROR(__xludf.DUMMYFUNCTION("""COMPUTED_VALUE"""),10.0) -> 10 | O11: =IFERROR(__xludf.DUMMYFUNCTION("""COMPUTED_VALUE"""),"") | P11: =IFERROR(__xludf.DUMMYFUNCTION("""COMPUTED_VALUE"""),20.0) -> 20 | T11: 25 | U11: 15 | W11: 0 | X11: 0 | Y11: 0 | Z11: 0 | AA11: 0 | AB11: 0 | AC11: 0 | AD11: 20 | AE11: 0 | AF11: 0 | AG11: 0 | AH11: =SUMPRODUCT(W11:AG11, {0,33,50,67,167,67,50,4.17,7.56,12.17,16.22}) -> 83.4 | AI11: 192.1 | AJ11: Shuffle | AL11: =AH11-AI11 -> -108.7
A12: 8 | B12: 10 | C12: 0 | D12: 10 | E12: 0 | F12: 10 | G12: 0 | H12: 10 | I12: 0 | J12: 10 | K12: 0 | M12: =IFERROR(__xludf.DUMMYFUNCTION("LET( names, HSTACK(""Coins"", W$4:AG$4), amounts, HSTACK(C12, W12:AG12), lookupNames, $AJ$5:$AJ$16, lookupImages, $AK$5:$AK$16, imgs, MAP(names, LAMBDA(n, XLOOKUP(n, lookupNames, lookupImages))), keepImgs, FILTER(imgs, amounts<>0), keepAmoun"&"ts, FILTER(amounts, amounts<>0), MAKEARRAY( 1, COLUMNS(keepAmounts)*2, LAMBDA(r,c, IF( ISODD(c), INDEX(keepImgs, 1, ROUNDUP(c/2)), INDEX(keepAmounts, 1, c/2) ) ) ) )"),"") | N12: =IFERROR(__xludf.DUMMYFUNCTION("""COMPUTED_VALUE"""),1.0) -> 1 | O12: =IFERROR(__xludf.DUMMYFUNCTION("""COMPUTED_VALUE"""),"") | P12: =IFERROR(__xludf.DUMMYFUNCTION("""COMPUTED_VALUE"""),30.0) -> 30 | T12: 25 | U12: 15 | W12: 0 | X12: 0 | Y12: 0 | Z12: 1 | AA12: 0 | AB12: 0 | AC12: 0 | AD12: 30 | AE12: 0 | AF12: 0 | AG12: 0 | AH12: =SUMPRODUCT(W12:AG12, {0,33,50,67,167,67,50,4.17,7.56,12.17,16.22}) -> 192.1 | AI12: 217 | AJ12: Comet | AL12: =AH12-AI12 -> -24.9
A13: 9 | B13: 10 | C13: 10 | D13: 10 | E13: 10 | F13: 10 | G13: 10 | H13: 10 | I13: 10 | J13: 10 | K13: 10 | M13: =IFERROR(__xludf.DUMMYFUNCTION("LET( names, HSTACK(""Coins"", W$4:AG$4), amounts, HSTACK(C13, W13:AG13), lookupNames, $AJ$5:$AJ$16, lookupImages, $AK$5:$AK$16, imgs, MAP(names, LAMBDA(n, XLOOKUP(n, lookupNames, lookupImages))), keepImgs, FILTER(imgs, amounts<>0), keepAmoun"&"ts, FILTER(amounts, amounts<>0), MAKEARRAY( 1, COLUMNS(keepAmounts)*2, LAMBDA(r,c, IF( ISODD(c), INDEX(keepImgs, 1, ROUNDUP(c/2)), INDEX(keepAmounts, 1, c/2) ) ) ) )"),"") | N13: =IFERROR(__xludf.DUMMYFUNCTION("""COMPUTED_VALUE"""),10.0) -> 10 | O13: =IFERROR(__xludf.DUMMYFUNCTION("""COMPUTED_VALUE"""),"") | P13: =IFERROR(__xludf.DUMMYFUNCTION("""COMPUTED_VALUE"""),60.0) -> 60 | T13: 25 | U13: 15 | W13: 0 | X13: 0 | Y13: 0 | Z13: 0 | AA13: 0 | AB13: 0 | AC13: 0 | AD13: 60 | AE13: 0 | AF13: 0 | AG13: 0 | AH13: =SUMPRODUCT(W13:AG13, {0,33,50,67,167,67,50,4.17,7.56,12.17,16.22}) -> 250.2 | AI13: 300.2 | AJ13: Unlimited Lives | AL13: =AH13-AI13 -> -50
A14: 10 | B14: 10 | C14: 20 | D14: 10 | E14: 20 | F14: 10 | G14: 20 | H14: 10 | I14: 20 | J14: 10 | K14: 20 | M14: =IFERROR(__xludf.DUMMYFUNCTION("LET( names, HSTACK(""Coins"", W$4:AG$4), amounts, HSTACK(C14, W14:AG14), lookupNames, $AJ$5:$AJ$16, lookupImages, $AK$5:$AK$16, imgs, MAP(names, LAMBDA(n, XLOOKUP(n, lookupNames, lookupImages))), keepImgs, FILTER(imgs, amounts<>0), keepAmoun"&"ts, FILTER(amounts, amounts<>0), MAKEARRAY( 1, COLUMNS(keepAmounts)*2, LAMBDA(r,c, IF( ISODD(c), INDEX(keepImgs, 1, ROUNDUP(c/2)), INDEX(keepAmounts, 1, c/2) ) ) ) )"),"") | N14: =IFERROR(__xludf.DUMMYFUNCTION("""COMPUTED_VALUE"""),20.0) -> 20 | O14: =IFERROR(__xludf.DUMMYFUNCTION("""COMPUTED_VALUE"""),"") | P14: =IFERROR(__xludf.DUMMYFUNCTION("""COMPUTED_VALUE"""),60.0) -> 60 | T14: 30 | U14: 20 | W14: 0 | X14: 0 | Y14: 0 | Z14: 0 | AA14: 0 | AB14: 0 | AC14: 0 | AD14: 60 | AE14: 0 | AF14: 0 | AG14: 0 | AH14: =SUMPRODUCT(W14:AG14, {0,33,50,67,167,67,50,4.17,7.56,12.17,16.22}) -> 250.2 | AI14: 117 | AJ14: Unlimited Red | AL14: =AH14-AI14 -> 133.2
AJ15: Unlimited Chuck
A16: Total per cycle | B16: =SUM(B5:B14) -> 100 | C16: =SUM(C5:C14) -> 60 | D16: =SUM(D5:D14) -> 100 | E16: =SUM(E5:E14) -> 60 | F16: =SUM(F5:F14) -> 100 | G16: =SUM(G5:G14) -> 60 | H16: =SUM(H5:H14) -> 100 | I16: =SUM(I5:I14) -> 60 | ... K16: =SUM(K5:K14) -> 60 | T16: =SUM(T5:T14) -> 210 | U16: =SUM(U5:U14) -> 130 | AJ16: Unlimited Bomb
A17: HC per level | C17: =C16/B16 -> 0.6 | E17: =E16/D16 -> 0.6 | G17: =G16/F16 -> 0.6 | I17: =I16/H16 -> 0.6 | K17: =K16/J16 -> 0.6 | T17: =T16/$J$16 -> 2.1 | U17: =U16/$J$16 -> 1.3
T19: =T16/saga_progression_old!$C$15 -> #REF! | U19: =U16/saga_progression_old!$C$15 -> #REF!

Sheet c_day
A1: Daily Rewards - OLD
A3: Day | B3: HC Reward | E3: 👁 | L3: Variant 1 | AB3: cur | AC3: image
A4: 1 | B4: =average(M5,M16,M26,M35,M45) -> 22 | L4: Day | M4: Coin | N4: SPT | O4: Red | P4: Chuck | Q4: Bomb | R4: Slingshot | S4: Shuffle | T4: Comet | U4: Unlimited Lives | V4: Unlimited Red | W4: Unlimited Chuck | X4: Unlimited Bomb | AB4: Coins
A5: 2 | B5: 0 | E5: =IFERROR(__xludf.DUMMYFUNCTION("LET( names, HSTACK(""Coins"", $N$4:$X$4), amounts, HSTACK(M5, N5:X5), lookupNames, $AB$4:$AB$15, lookupImages, $AC$4:$AC$15, imgs, MAP(names, LAMBDA(n, XLOOKUP(n, lookupNames, lookupImages))), keepImgs, FILTER(imgs, amounts<>0), keepAmounts,"&" FILTER(amounts, amounts<>0), MAKEARRAY( 1, COLUMNS(keepAmounts)*2, LAMBDA(r,c, IF( ISODD(c), INDEX(keepImgs, 1, ROUNDUP(c/2)), INDEX(keepAmounts, 1, c/2) ) ) ) )"),"") | F5: =IFERROR(__xludf.DUMMYFUNCTION("""COMPUTED_VALUE"""),20.0) -> 20 | L5: 1 | M5: 20 | N5: 0 | O5: 0 | P5: 0 | Q5: 0 | R5: 0 | S5: 0 | T5: 0 | U5: 0 | V5: 0 | W5: 0 | X5: 0 | AB5: SPT
A6: 3 | B6: 0 | E6: =IFERROR(__xludf.DUMMYFUNCTION("LET( names, HSTACK(""Coins"", $N$4:$X$4), amounts, HSTACK(M6, N6:X6), lookupNames, $AB$4:$AB$15, lookupImages, $AC$4:$AC$15, imgs, MAP(names, LAMBDA(n, XLOOKUP(n, lookupNames, lookupImages))), keepImgs, FILTER(imgs, amounts<>0), keepAmounts,"&" FILTER(amounts, amounts<>0), MAKEARRAY( 1, COLUMNS(keepAmounts)*2, LAMBDA(r,c, IF( ISODD(c), INDEX(keepImgs, 1, ROUNDUP(c/2)), INDEX(keepAmounts, 1, c/2) ) ) ) )"),"") | F6: =IFERROR(__xludf.DUMMYFUNCTION("""COMPUTED_VALUE"""),15.0) -> 15 | L6: 2 | M6: 0 | N6: 0 | O6: 0 | P6: 0 | Q6: 0 | R6: 0 | S6: 0 | T6: 0 | U6: 15 | V6: 0 | W6: 0 | X6: 0 | AB6: Red
A7: 4 | B7: =mround(average(M8,M18,M28), 1) -> 27 | E7: =IFERROR(__xludf.DUMMYFUNCTION("LET( names, HSTACK(""Coins"", $N$4:$X$4), amounts, HSTACK(M7, N7:X7), lookupNames, $AB$4:$AB$15, lookupImages, $AC$4:$AC$15, imgs, MAP(names, LAMBDA(n, XLOOKUP(n, lookupNames, lookupImages))), keepImgs, FILTER(imgs, amounts<>0), keepAmounts,"&" FILTER(amounts, amounts<>0), MAKEARRAY( 1, COLUMNS(keepAmounts)*2, LAMBDA(r,c, IF( ISODD(c), INDEX(keepImgs, 1, ROUNDUP(c/2)), INDEX(keepAmounts, 1, c/2) ) ) ) )"),"") | F7: =IFERROR(__xludf.DUMMYFUNCTION("""COMPUTED_VALUE"""),1.0) -> 1 | L7: 3 | M7: 0 | N7: 0 | O7: 0 | P7: 0 | Q7: 0 | R7: 1 | S7: 0 | T7: 0 | U7: 0 | V7: 0 | W7: 0 | X7: 0 | AB7: Chuck
A8: 5 | B8: 0 | E8: =IFERROR(__xludf.DUMMYFUNCTION("LET( names, HSTACK(""Coins"", $N$4:$X$4), amounts, HSTACK(M8, N8:X8), lookupNames, $AB$4:$AB$15, lookupImages, $AC$4:$AC$15, imgs, MAP(names, LAMBDA(n, XLOOKUP(n, lookupNames, lookupImages))), keepImgs, FILTER(imgs, amounts<>0), keepAmounts,"&" FILTER(amounts, amounts<>0), MAKEARRAY( 1, COLUMNS(keepAmounts)*2, LAMBDA(r,c, IF( ISODD(c), INDEX(keepImgs, 1, ROUNDUP(c/2)), INDEX(keepAmounts, 1, c/2) ) ) ) )"),"") | F8: =IFERROR(__xludf.DUMMYFUNCTION("""COMPUTED_VALUE"""),25.0) -> 25 | L8: 4 | M8: 25 | N8: 0 | O8: 0 | P8: 0 | Q8: 0 | R8: 0 | S8: 0 | T8: 0 | U8: 0 | V8: 0 | W8: 0 | X8: 0 | AB8: Bomb
A9: 6 | B9: =mround(AVERAGE(M10, M20, M30, M50),1) -> 33 | E9: =IFERROR(__xludf.DUMMYFUNCTION("LET( names, HSTACK(""Coins"", $N$4:$X$4), amounts, HSTACK(M9, N9:X9), lookupNames, $AB$4:$AB$15, lookupImages, $AC$4:$AC$15, imgs, MAP(names, LAMBDA(n, XLOOKUP(n, lookupNames, lookupImages))), keepImgs, FILTER(imgs, amounts<>0), keepAmounts,"&" FILTER(amounts, amounts<>0), MAKEARRAY( 1, COLUMNS(keepAmounts)*2, LAMBDA(r,c, IF( ISODD(c), INDEX(keepImgs, 1, ROUNDUP(c/2)), INDEX(keepAmounts, 1, c/2) ) ) ) )"),"") | F9: =IFERROR(__xludf.DUMMYFUNCTION("""COMPUTED_VALUE"""),1.0) -> 1 | L9: 5 | M9: 0 | N9: 0 | O9: 0 | P9: 0 | Q9: 0 | R9: 0 | S9: 1 | T9: 0 | U9: 0 | V9: 0 | W9: 0 | X9: 0 | AB9: Slingshot
A10: 7 | B10: 100 | E10: =IFERROR(__xludf.DUMMYFUNCTION("LET( names, HSTACK(""Coins"", $N$4:$X$4), amounts, HSTACK(M10, N10:X10), lookupNames, $AB$4:$AB$15, lookupImages, $AC$4:$AC$15, imgs, MAP(names, LAMBDA(n, XLOOKUP(n, lookupNames, lookupImages))), keepImgs, FILTER(imgs, amounts<>0), keepAmoun"&"ts, FILTER(amounts, amounts<>0), MAKEARRAY( 1, COLUMNS(keepAmounts)*2, LAMBDA(r,c, IF( ISODD(c), INDEX(keepImgs, 1, ROUNDUP(c/2)), INDEX(keepAmounts, 1, c/2) ) ) ) )"),"") | F10: =IFERROR(__xludf.DUMMYFUNCTION("""COMPUTED_VALUE"""),30.0) -> 30 | L10: 6 | M10: 30 | N10: 0 | O10: 0 | P10: 0 | Q10: 0 | R10: 0 | S10: 0 | T10: 0 | U10: 0 | V10: 0 | W10: 0 | X10: 0 | AB10: Shuffle
E11: =IFERROR(__xludf.DUMMYFUNCTION("LET( names, HSTACK(""Coins"", $N$4:$X$4), amounts, HSTACK(M11, N11:X11), lookupNames, $AB$4:$AB$15, lookupImages, $AC$4:$AC$15, imgs, MAP(names, LAMBDA(n, XLOOKUP(n, lookupNames, lookupImages))), keepImgs, FILTER(imgs, amounts<>0), keepAmoun"&"ts, FILTER(amounts, amounts<>0), MAKEARRAY( 1, COLUMNS(keepAmounts)*2, LAMBDA(r,c, IF( ISODD(c), INDEX(keepImgs, 1, ROUNDUP(c/2)), INDEX(keepAmounts, 1, c/2) ) ) ) )"),"") | F11: =IFERROR(__xludf.DUMMYFUNCTION("""COMPUTED_VALUE"""),100.0) -> 100 | G11: =IFERROR(__xludf.DUMMYFUNCTION("""COMPUTED_VALUE"""),"") | H11: =IFERROR(__xludf.DUMMYFUNCTION("""COMPUTED_VALUE"""),120.0) -> 120 | I11: =IFERROR(__xludf.DUMMYFUNCTION("""COMPUTED_VALUE"""),"") | J11: =IFERROR(__xludf.DUMMYFUNCTION("""COMPUTED_VALUE"""),60.0) -> 60 | L11: 7 | M11: 100 | N11: 0 | O11: 0 | P11: 0 | Q11: 0 | R11: 0 | S11: 0 | T11: 0 | U11: 120 | V11: 60 | W11: 0 | X11: 0 | AB11: Comet
A12: Total per cycle | B12: =SUM(B4:B10) -> 182 | AB12: Unlimited Lives
A13: Avg HC/day (7d) | B13: =B12/7 -> 26 | L13: Variant 2 | AB13: Unlimited Red
L14: Day | M14: Coin | N14: SPT | O14: Red | P14: Chuck | Q14: Bomb | R14: Slingshot | S14: Shuffle | T14: Comet | U14: Unlimited Lives | V14: Unlimited Red | W14: Unlimited Chuck | X14: Unlimited Bomb | AB14: Unlimited Chuck
E15: =IFERROR(__xludf.DUMMYFUNCTION("LET( names, HSTACK(""Coins"", $N$4:$X$4), amounts, HSTACK(M15, N15:X15), lookupNames, $AB$4:$AB$15, lookupImages, $AC$4:$AC$15, imgs, MAP(names, LAMBDA(n, XLOOKUP(n, lookupNames, lookupImages))), keepImgs, FILTER(imgs, amounts<>0), keepAmoun"&"ts, FILTER(amounts, amounts<>0), MAKEARRAY( 1, COLUMNS(keepAmounts)*2, LAMBDA(r,c, IF( ISODD(c), INDEX(keepImgs, 1, ROUNDUP(c/2)), INDEX(keepAmounts, 1, c/2) ) ) ) )"),"") | F15: =IFERROR(__xludf.DUMMYFUNCTION("""COMPUTED_VALUE"""),20.0) -> 20 | L15: 1 | M15: 0 | N15: 0 | O15: 0 | P15: 0 | Q15: 0 | R15: 0 | S15: 0 | T15: 0 | U15: 20 | V15: 0 | W15: 0 | X15: 0 | AB15: Unlimited Bomb
E16: =IFERROR(__xludf.DUMMYFUNCTION("LET( names, HSTACK(""Coins"", $N$4:$X$4), amounts, HSTACK(M16, N16:X16), lookupNames, $AB$4:$AB$15, lookupImages, $AC$4:$AC$15, imgs, MAP(names, LAMBDA(n, XLOOKUP(n, lookupNames, lookupImages))), keepImgs, FILTER(imgs, amounts<>0), keepAmoun"&"ts, FILTER(amounts, amounts<>0), MAKEARRAY( 1, COLUMNS(keepAmounts)*2, LAMBDA(r,c, IF( ISODD(c), INDEX(keepImgs, 1, ROUNDUP(c/2)), INDEX(keepAmounts, 1, c/2) ) ) ) )"),"") | F16: =IFERROR(__xludf.DUMMYFUNCTION("""COMPUTED_VALUE"""),25.0) -> 25 | L16: 2 | M16: 25 | N16: 0 | O16: 0 | P16: 0 | Q16: 0 | R16: 0 | S16: 0 | T16: 0 | U16: 0 | V16: 0 | W16: 0 | X16: 0
E17: =IFERROR(__xludf.DUMMYFUNCTION("LET( names, HSTACK(""Coins"", $N$4:$X$4), amounts, HSTACK(M17, N17:X17), lookupNames, $AB$4:$AB$15, lookupImages, $AC$4:$AC$15, imgs, MAP(names, LAMBDA(n, XLOOKUP(n, lookupNames, lookupImages))), keepImgs, FILTER(imgs, amounts<>0), keepAmoun"&"ts, FILTER(amounts, amounts<>0), MAKEARRAY( 1, COLUMNS(keepAmounts)*2, LAMBDA(r,c, IF( ISODD(c), INDEX(keepImgs, 1, ROUNDUP(c/2)), INDEX(keepAmounts, 1, c/2) ) ) ) )"),"") | F17: =IFERROR(__xludf.DUMMYFUNCTION("""COMPUTED_VALUE"""),1.0) -> 1 | L17: 3 | M17: 0 | N17: 0 | O17: 0 | P17: 0 | Q17: 0 | R17: 1 | S17: 0 | T17: 0 | U17: 0 | V17: 0 | W17: 0 | X17: 0
E18: =IFERROR(__xludf.DUMMYFUNCTION("LET( names, HSTACK(""Coins"", $N$4:$X$4), amounts, HSTACK(M18, N18:X18), lookupNames, $AB$4:$AB$15, lookupImages, $AC$4:$AC$15, imgs, MAP(names, LAMBDA(n, XLOOKUP(n, lookupNames, lookupImages))), keepImgs, FILTER(imgs, amounts<>0), keepAmoun"&"ts, FILTER(amounts, amounts<>0), MAKEARRAY( 1, COLUMNS(keepAmounts)*2, LAMBDA(r,c, IF( ISODD(c), INDEX(keepImgs, 1, ROUNDUP(c/2)), INDEX(keepAmounts, 1, c/2) ) ) ) )"),"") | F18: =IFERROR(__xludf.DUMMYFUNCTION("""COMPUTED_VALUE"""),30.0) -> 30 | L18: 4 | M18: 30 | N18: 0 | O18: 0 | P18: 0 | Q18: 0 | R18: 0 | S18: 0 | T18: 0 | U18: 0 | V18: 0 | W18: 0 | X18: 0
E19: =IFERROR(__xludf.DUMMYFUNCTION("LET( names, HSTACK(""Coins"", $N$4:$X$4), amounts, HSTACK(M19, N19:X19), lookupNames, $AB$4:$AB$15, lookupImages, $AC$4:$AC$15, imgs, MAP(names, LAMBDA(n, XLOOKUP(n, lookupNames, lookupImages))), keepImgs, FILTER(imgs, amounts<>0), keepAmoun"&"ts, FILTER(amounts, amounts<>0), MAKEARRAY( 1, COLUMNS(keepAmounts)*2, LAMBDA(r,c, IF( ISODD(c), INDEX(keepImgs, 1, ROUNDUP(c/2)), INDEX(keepAmounts, 1, c/2) ) ) ) )"),"") | F19: =IFERROR(__xludf.DUMMYFUNCTION("""COMPUTED_VALUE"""),1.0) -> 1 | L19: 5 | M19: 0 | N19: 0 | O19: 0 | P19: 0 | Q19: 0 | R19: 0 | S19: 1 | T19: 0 | U19: 0 | V19: 0 | W19: 0 | X19: 0
E20: =IFERROR(__xludf.DUMMYFUNCTION("LET( names, HSTACK(""Coins"", $N$4:$X$4), amounts, HSTACK(M20, N20:X20), lookupNames, $AB$4:$AB$15, lookupImages, $AC$4:$AC$15, imgs, MAP(names, LAMBDA(n, XLOOKUP(n, lookupNames, lookupImages))), keepImgs, FILTER(imgs, amounts<>0), keepAmoun"&"ts, FILTER(amounts, amounts<>0), MAKEARRAY( 1, COLUMNS(keepAmounts)*2, LAMBDA(r,c, IF( ISODD(c), INDEX(keepImgs, 1, ROUNDUP(c/2)), INDEX(keepAmounts, 1, c/2) ) ) ) )"),"") | F20: =IFERROR(__xludf.DUMMYFUNCTION("""COMPUTED_VALUE"""),35.0) -> 35 | L20: 6 | M20: 35 | N20: 0 | O20: 0 | P20: 0 | Q20: 0 | R20: 0 | S20: 0 | T20: 0 | U20: 0 | V20: 0 | W20: 0 | X20: 0
E21: =IFERROR(__xludf.DUMMYFUNCTION("LET( names, HSTACK(""Coins"", $N$4:$X$4), amounts, HSTACK(M21, N21:X21), lookupNames, $AB$4:$AB$15, lookupImages, $AC$4:$AC$15, imgs, MAP(names, LAMBDA(n, XLOOKUP(n, lookupNames, lookupImages))), keepImgs, FILTER(imgs, amounts<>0), keepAmoun"&"ts, FILTER(amounts, amounts<>0), MAKEARRAY( 1, COLUMNS(keepAmounts)*2, LAMBDA(r,c, IF( ISODD(c), INDEX(keepImgs, 1, ROUNDUP(c/2)), INDEX(keepAmounts, 1, c/2) ) ) ) )"),"") | F21: =IFERROR(__xludf.DUMMYFUNCTION("""COMPUTED_VALUE"""),100.0) -> 100 | G21: =IFERROR(__xludf.DUMMYFUNCTION("""COMPUTED_VALUE"""),"") | H21: =IFERROR(__xludf.DUMMYFUNCTION("""COMPUTED_VALUE"""),120.0) -> 120 | I21: =IFERROR(__xludf.DUMMYFUNCTION("""COMPUTED_VALUE"""),"") | J21: =IFERROR(__xludf.DUMMYFUNCTION("""COMPUTED_VALUE"""),60.0) -> 60 | L21: 7 | M21: 100 | N21: 0 | O21: 0 | P21: 0 | Q21: 0 | R21: 0 | S21: 0 | T21: 0 | U21: 120 | V21: 0 | W21: 60 | X21: 0
L23: Variant 3
L24: Day | M24: Coin | N24: SPT | O24: Red | P24: Chuck | Q24: Bomb | R24: Slingshot | S24: Shuffle | T24: Comet | U24: Unlimited Lives | V24: Unlimited Red | W24: Unlimited Chuck | X24: Unlimited Bomb
E25: =IFERROR(__xludf.DUMMYFUNCTION("LET( names, HSTACK(""Coins"", $N$4:$X$4), amounts, HSTACK(M25, N25:X25), lookupNames, $AB$4:$AB$15, lookupImages, $AC$4:$AC$15, imgs, MAP(names, LAMBDA(n, XLOOKUP(n, lookupNames, lookupImages))), keepImgs, FILTER(imgs, amounts<>0), keepAmoun"&"ts, FILTER(amounts, amounts<>0), MAKEARRAY( 1, COLUMNS(keepAmounts)*2, LAMBDA(r,c, IF( ISODD(c), INDEX(keepImgs, 1, ROUNDUP(c/2)), INDEX(keepAmounts, 1, c/2) ) ) ) )"),"") | F25: =IFERROR(__xludf.DUMMYFUNCTION("""COMPUTED_VALUE"""),15.0) -> 15 | L25: 1 | M25: 0 | N25: 0 | O25: 0 | P25: 0 | Q25: 0 | R25: 0 | S25: 0 | T25: 0 | U25: 15 | V25: 0 | W25: 0 | X25: 0
E26: =IFERROR(__xludf.DUMMYFUNCTION("LET( names, HSTACK(""Coins"", $N$4:$X$4), amounts, HSTACK(M26, N26:X26), lookupNames, $AB$4:$AB$15, lookupImages, $AC$4:$AC$15, imgs, MAP(names, LAMBDA(n, XLOOKUP(n, lookupNames, lookupImages))), keepImgs, FILTER(imgs, amounts<>0), keepAmoun"&"ts, FILTER(amounts, amounts<>0), MAKEARRAY( 1, COLUMNS(keepAmounts)*2, LAMBDA(r,c, IF( ISODD(c), INDEX(keepImgs, 1, ROUNDUP(c/2)), INDEX(keepAmounts, 1, c/2) ) ) ) )"),"") | F26: =IFERROR(__xludf.DUMMYFUNCTION("""COMPUTED_VALUE"""),20.0) -> 20 | L26: 2 | M26: 20 | N26: 0 | O26: 0 | P26: 0 | Q26: 0 | R26: 0 | S26: 0 | T26: 0 | U26: 0 | V26: 0 | W26: 0 | X26: 0
E27: =IFERROR(__xludf.DUMMYFUNCTION("LET( names, HSTACK(""Coins"", $N$4:$X$4), amounts, HSTACK(M27, N27:X27), lookupNames, $AB$4:$AB$15, lookupImages, $AC$4:$AC$15, imgs, MAP(names, LAMBDA(n, XLOOKUP(n, lookupNames, lookupImages))), keepImgs, FILTER(imgs, amounts<>0), keepAmoun"&"ts, FILTER(amounts, amounts<>0), MAKEARRAY( 1, COLUMNS(keepAmounts)*2, LAMBDA(r,c, IF( ISODD(c), INDEX(keepImgs, 1, ROUNDUP(c/2)), INDEX(keepAmounts, 1, c/2) ) ) ) )"),"") | F27: =IFERROR(__xludf.DUMMYFUNCTION("""COMPUTED_VALUE"""),1.0) -> 1 | L27: 3 | M27: 0 | N27: 0 | O27: 0 | P27: 0 | Q27: 0 | R27: 1 | S27: 0 | T27: 0 | U27: 0 | V27: 0 | W27: 0 | X27: 0
E28: =IFERROR(__xludf.DUMMYFUNCTION("LET( names, HSTACK(""Coins"", $N$4:$X$4), amounts, HSTACK(M28, N28:X28), lookupNames, $AB$4:$AB$15, lookupImages, $AC$4:$AC$15, imgs, MAP(names, LAMBDA(n, XLOOKUP(n, lookupNames, lookupImages))), keepImgs, FILTER(imgs, amounts<>0), keepAmoun"&"ts, FILTER(amounts, amounts<>0), MAKEARRAY( 1, COLUMNS(keepAmounts)*2, LAMBDA(r,c, IF( ISODD(c), INDEX(keepImgs, 1, ROUNDUP(c/2)), INDEX(keepAmounts, 1, c/2) ) ) ) )"),"") | F28: =IFERROR(__xludf.DUMMYFUNCTION("""COMPUTED_VALUE"""),25.0) -> 25 | L28: 4 | M28: 25 | N28: 0 | O28: 0 | P28: 0 | Q28: 0 | R28: 0 | S28: 0 | T28: 0 | U28: 0 | V28: 0 | W28: 0 | X28: 0
E29: =IFERROR(__xludf.DUMMYFUNCTION("LET( names, HSTACK(""Coins"", $N$4:$X$4), amounts, HSTACK(M29, N29:X29), lookupNames, $AB$4:$AB$15, lookupImages, $AC$4:$AC$15, imgs, MAP(names, LAMBDA(n, XLOOKUP(n, lookupNames, lookupImages))), keepImgs, FILTER(imgs, amounts<>0), keepAmoun"&"ts, FILTER(amounts, amounts<>0), MAKEARRAY( 1, COLUMNS(keepAmounts)*2, LAMBDA(r,c, IF( ISODD(c), INDEX(keepImgs, 1, ROUNDUP(c/2)), INDEX(keepAmounts, 1, c/2) ) ) ) )"),"") | F29: =IFERROR(__xludf.DUMMYFUNCTION("""COMPUTED_VALUE"""),1.0) -> 1 | L29: 5 | M29: 0 | N29: 0 | O29: 0 | P29: 0 | Q29: 0 | R29: 0 | S29: 1 | T29: 0 | U29: 0 | V29: 0 | W29: 0 | X29: 0
E30: =IFERROR(__xludf.DUMMYFUNCTION("LET( names, HSTACK(""Coins"", $N$4:$X$4), amounts, HSTACK(M30, N30:X30), lookupNames, $AB$4:$AB$15, lookupImages, $AC$4:$AC$15, imgs, MAP(names, LAMBDA(n, XLOOKUP(n, lookupNames, lookupImages))), keepImgs, FILTER(imgs, amounts<>0), keepAmoun"&"ts, FILTER(amounts, amounts<>0), MAKEARRAY( 1, COLUMNS(keepAmounts)*2, LAMBDA(r,c, IF( ISODD(c), INDEX(keepImgs, 1, ROUNDUP(c/2)), INDEX(keepAmounts, 1, c/2) ) ) ) )"),"") | F30: =IFERROR(__xludf.DUMMYFUNCTION("""COMPUTED_VALUE"""),30.0) -> 30 | L30: 6 | M30: 30 | N30: 0 | O30: 0 | P30: 0 | Q30: 0 | R30: 0 | S30: 0 | T30: 0 | U30: 0 | V30: 0 | W30: 0 | X30: 0
E31: =IFERROR(__xludf.DUMMYFUNCTION("LET( names, HSTACK(""Coins"", $N$4:$X$4), amounts, HSTACK(M31, N31:X31), lookupNames, $AB$4:$AB$15, lookupImages, $AC$4:$AC$15, imgs, MAP(names, LAMBDA(n, XLOOKUP(n, lookupNames, lookupImages))), keepImgs, FILTER(imgs, amounts<>0), keepAmoun"&"ts, FILTER(amounts, amounts<>0), MAKEARRAY( 1, COLUMNS(keepAmounts)*2, LAMBDA(r,c, IF( ISODD(c), INDEX(keepImgs, 1, ROUNDUP(c/2)), INDEX(keepAmounts, 1, c/2) ) ) ) )"),"") | F31: =IFERROR(__xludf.DUMMYFUNCTION("""COMPUTED_VALUE"""),100.0) -> 100 | G31: =IFERROR(__xludf.DUMMYFUNCTION("""COMPUTED_VALUE"""),"") | H31: =IFERROR(__xludf.DUMMYFUNCTION("""COMPUTED_VALUE"""),120.0) -> 120 | I31: =IFERROR(__xludf.DUMMYFUNCTION("""COMPUTED_VALUE"""),"") | J31: =IFERROR(__xludf.DUMMYFUNCTION("""COMPUTED_VALUE"""),30.0) -> 30 | L31: 7 | M31: 100 | N31: 0 | O31: 0 | P31: 0 | Q31: 0 | R31: 0 | S31: 0 | T31: 0 | U31: 120 | V31: 0 | W31: 0 | X31: 30
L33: Variant 4
L34: Day | M34: Coin | N34: SPT | O34: Red | P34: Chuck | Q34: Bomb | R34: Slingshot | S34: Shuffle | T34: Comet | U34: Unlimited Lives | V34: Unlimited Red | W34: Unlimited Chuck | X34: Unlimited Bomb
E35: =IFERROR(__xludf.DUMMYFUNCTION("LET( names, HSTACK(""Coins"", $N$4:$X$4), amounts, HSTACK(M35, N35:X35), lookupNames, $AB$4:$AB$15, lookupImages, $AC$4:$AC$15, imgs, MAP(names, LAMBDA(n, XLOOKUP(n, lookupNames, lookupImages))), keepImgs, FILTER(imgs, amounts<>0), keepAmoun"&"ts, FILTER(amounts, amounts<>0), MAKEARRAY( 1, COLUMNS(keepAmounts)*2, LAMBDA(r,c, IF( ISODD(c), INDEX(keepImgs, 1, ROUNDUP(c/2)), INDEX(keepAmounts, 1, c/2) ) ) ) )"),"") | F35: =IFERROR(__xludf.DUMMYFUNCTION("""COMPUTED_VALUE"""),25.0) -> 25 | L35: 1 | M35: 25 | N35: 0 | O35: 0 | P35: 0 | Q35: 0 | R35: 0 | S35: 0 | T35: 0 | U35: 0 | V35: 0 | W35: 0 | X35: 0
E36: =IFERROR(__xludf.DUMMYFUNCTION("LET( names, HSTACK(""Coins"", $N$4:$X$4), amounts, HSTACK(M36, N36:X36), lookupNames, $AB$4:$AB$15, lookupImages, $AC$4:$AC$15, imgs, MAP(names, LAMBDA(n, XLOOKUP(n, lookupNames, lookupImages))), keepImgs, FILTER(imgs, amounts<>0), keepAmoun"&"ts, FILTER(amounts, amounts<>0), MAKEARRAY( 1, COLUMNS(keepAmounts)*2, LAMBDA(r,c, IF( ISODD(c), INDEX(keepImgs, 1, ROUNDUP(c/2)), INDEX(keepAmounts, 1, c/2) ) ) ) )"),"") | F36: =IFERROR(__xludf.DUMMYFUNCTION("""COMPUTED_VALUE"""),30.0) -> 30 | L36: 2 | M36: 0 | N36: 0 | O36: 0 | P36: 0 | Q36: 0 | R36: 0 | S36: 0 | T36: 0 | U36: 30 | V36: 0 | W36: 0 | X36: 0
E37: =IFERROR(__xludf.DUMMYFUNCTION("LET( names, HSTACK(""Coins"", $N$4:$X$4), amounts, HSTACK(M37, N37:X37), lookupNames, $AB$4:$AB$15, lookupImages, $AC$4:$AC$15, imgs, MAP(names, LAMBDA(n, XLOOKUP(n, lookupNames, lookupImages))), keepImgs, FILTER(imgs, amounts<>0), keepAmoun"&"ts, FILTER(amounts, amounts<>0), MAKEARRAY( 1, COLUMNS(keepAmounts)*2, LAMBDA(r,c, IF( ISODD(c), INDEX(keepImgs, 1, ROUNDUP(c/2)), INDEX(keepAmounts, 1, c/2) ) ) ) )"),"") | F37: =IFERROR(__xludf.DUMMYFUNCTION("""COMPUTED_VALUE"""),1.0) -> 1 | L37: 3 | M37: 0 | N37: 0 | O37: 0 | P37: 0 | Q37: 0 | R37: 0 | S37: 1 | T37: 0 | U37: 0 | V37: 0 | W37: 0 | X37: 0
E38: =IFERROR(__xludf.DUMMYFUNCTION("LET( names, HSTACK(""Coins"", $N$4:$X$4), amounts, HSTACK(M38, N38:X38), lookupNames, $AB$4:$AB$15, lookupImages, $AC$4:$AC$15, imgs, MAP(names, LAMBDA(n, XLOOKUP(n, lookupNames, lookupImages))), keepImgs, FILTER(imgs, amounts<>0), keepAmoun"&"ts, FILTER(amounts, amounts<>0), MAKEARRAY( 1, COLUMNS(keepAmounts)*2, LAMBDA(r,c, IF( ISODD(c), INDEX(keepImgs, 1, ROUNDUP(c/2)), INDEX(keepAmounts, 1, c/2) ) ) ) )"),"") | F38: =IFERROR(__xludf.DUMMYFUNCTION("""COMPUTED_VALUE"""),1.0) -> 1 | L38: 4 | M38: 0 | N38: 0 | O38: 0 | P38: 0 | Q38: 0 | R38: 1 | S38: 0 | T38: 0 | U38: 0 | V38: 0 | W38: 0 | X38: 0
E39: =IFERROR(__xludf.DUMMYFUNCTION("LET( names, HSTACK(""Coins"", $N$4:$X$4), amounts, HSTACK(M39, N39:X39), lookupNames, $AB$4:$AB$15, lookupImages, $AC$4:$AC$15, imgs, MAP(names, LAMBDA(n, XLOOKUP(n, lookupNames, lookupImages))), keepImgs, FILTER(imgs, amounts<>0), keepAmoun"&"ts, FILTER(amounts, amounts<>0), MAKEARRAY( 1, COLUMNS(keepAmounts)*2, LAMBDA(r,c, IF( ISODD(c), INDEX(keepImgs, 1, ROUNDUP(c/2)), INDEX(keepAmounts, 1, c/2) ) ) ) )"),"") | F39: =IFERROR(__xludf.DUMMYFUNCTION("""COMPUTED_VALUE"""),30.0) -> 30 | L39: 5 | M39: 30 | N39: 0 | O39: 0 | P39: 0 | Q39: 0 | R39: 0 | S39: 0 | T39: 0 | U39: 0 | V39: 0 | W39: 0 | X39: 0
E40: =IFERROR(__xludf.DUMMYFUNCTION("LET( names, HSTACK(""Coins"", $N$4:$X$4), amounts, HSTACK(M40, N40:X40), lookupNames, $AB$4:$AB$15, lookupImages, $AC$4:$AC$15, imgs, MAP(names, LAMBDA(n, XLOOKUP(n, lookupNames, lookupImages))), keepImgs, FILTER(imgs, amounts<>0), keepAmoun"&"ts, FILTER(amounts, amounts<>0), MAKEARRAY( 1, COLUMNS(keepAmounts)*2, LAMBDA(r,c, IF( ISODD(c), INDEX(keepImgs, 1, ROUNDUP(c/2)), INDEX(keepAmounts, 1, c/2) ) ) ) )"),"") | F40: =IFERROR(__xludf.DUMMYFUNCTION("""COMPUTED_VALUE"""),1.0) -> 1 | L40: 6 | M40: 0 | N40: 0 | O40: 0 | P40: 0 | Q40: 0 | R40: 1 | S40: 0 | T40: 0 | U40: 0 | V40: 0 | W40: 0 | X40: 0
E41: =IFERROR(__xludf.DUMMYFUNCTION("LET( names, HSTACK(""Coins"", $N$4:$X$4), amounts, HSTACK(M41, N41:X41), lookupNames, $AB$4:$AB$15, lookupImages, $AC$4:$AC$15, imgs, MAP(names, LAMBDA(n, XLOOKUP(n, lookupNames, lookupImages))), keepImgs, FILTER(imgs, amounts<>0), keepAmoun"&"ts, FILTER(amounts, amounts<>0), MAKEARRAY( 1, COLUMNS(keepAmounts)*2, LAMBDA(r,c, IF( ISODD(c), INDEX(keepImgs, 1, ROUNDUP(c/2)), INDEX(keepAmounts, 1, c/2) ) ) ) )"),"") | F41: =IFERROR(__xludf.DUMMYFUNCTION("""COMPUTED_VALUE"""),100.0) -> 100 | G41: =IFERROR(__xludf.DUMMYFUNCTION("""COMPUTED_VALUE"""),"") | H41: =IFERROR(__xludf.DUMMYFUNCTION("""COMPUTED_VALUE"""),1.0) -> 1 | I41: =IFERROR(__xludf.DUMMYFUNCTION("""COMPUTED_VALUE"""),"") | J41: =IFERROR(__xludf.DUMMYFUNCTION("""COMPUTED_VALUE"""),120.0) -> 120 | L41: 7 | M41: 100 | N41: 0 | O41: 0 | P41: 0 | Q41: 0 | R41: 0 | S41: 0 | T41: 1 | U41: 120 | V41: 0 | W41: 0 | X41: 0
L43: Variant 5
L44: Day | M44: Coin | N44: SPT | O44: Red | P44: Chuck | Q44: Bomb | R44: Slingshot | S44: Shuffle | T44: Comet | U44: Unlimited Lives | V44: Unlimited Red | W44: Unlimited Chuck | X44: Unlimited Bomb
E45: =IFERROR(__xludf.DUMMYFUNCTION("LET( names, HSTACK(""Coins"", $N$4:$X$4), amounts, HSTACK(M45, N45:X45), lookupNames, $AB$4:$AB$15, lookupImages, $AC$4:$AC$15, imgs, MAP(names, LAMBDA(n, XLOOKUP(n, lookupNames, lookupImages))), keepImgs, FILTER(imgs, amounts<>0), keepAmoun"&"ts, FILTER(amounts, amounts<>0), MAKEARRAY( 1, COLUMNS(keepAmounts)*2, LAMBDA(r,c, IF( ISODD(c), INDEX(keepImgs, 1, ROUNDUP(c/2)), INDEX(keepAmounts, 1, c/2) ) ) ) )"),"") | F45: =IFERROR(__xludf.DUMMYFUNCTION("""COMPUTED_VALUE"""),20.0) -> 20 | L45: 1 | M45: 20 | N45: 0 | O45: 0 | P45: 0 | Q45: 0 | R45: 0 | S45: 0 | T45: 0 | U45: 0 | V45: 0 | W45: 0 | X45: 0
E46: =IFERROR(__xludf.DUMMYFUNCTION("LET( names, HSTACK(""Coins"", $N$4:$X$4), amounts, HSTACK(M46, N46:X46), lookupNames, $AB$4:$AB$15, lookupImages, $AC$4:$AC$15, imgs, MAP(names, LAMBDA(n, XLOOKUP(n, lookupNames, lookupImages))), keepImgs, FILTER(imgs, amounts<>0), keepAmoun"&"ts, FILTER(amounts, amounts<>0), MAKEARRAY( 1, COLUMNS(keepAmounts)*2, LAMBDA(r,c, IF( ISODD(c), INDEX(keepImgs, 1, ROUNDUP(c/2)), INDEX(keepAmounts, 1, c/2) ) ) ) )"),"") | F46: =IFERROR(__xludf.DUMMYFUNCTION("""COMPUTED_VALUE"""),15.0) -> 15 | L46: 2 | M46: 0 | N46: 0 | O46: 0 | P46: 0 | Q46: 0 | R46: 0 | S46: 0 | T46: 0 | U46: 15 | V46: 0 | W46: 0 | X46: 0
E47: =IFERROR(__xludf.DUMMYFUNCTION("LET( names, HSTACK(""Coins"", $N$4:$X$4), amounts, HSTACK(M47, N47:X47), lookupNames, $AB$4:$AB$15, lookupImages, $AC$4:$AC$15, imgs, MAP(names, LAMBDA(n, XLOOKUP(n, lookupNames, lookupImages))), keepImgs, FILTER(imgs, amounts<>0), keepAmoun"&"ts, FILTER(amounts, amounts<>0), MAKEARRAY( 1, COLUMNS(keepAmounts)*2, LAMBDA(r,c, IF( ISODD(c), INDEX(keepImgs, 1, ROUNDUP(c/2)), INDEX(keepAmounts, 1, c/2) ) ) ) )"),"") | F47: =IFERROR(__xludf.DUMMYFUNCTION("""COMPUTED_VALUE"""),1.0) -> 1 | L47: 3 | M47: 0 | N47: 0 | O47: 0 | P47: 0 | Q47: 0 | R47: 1 | S47: 0 | T47: 0 | U47: 0 | V47: 0 | W47: 0 | X47: 0
E48: =IFERROR(__xludf.DUMMYFUNCTION("LET( names, HSTACK(""Coins"", $N$4:$X$4), amounts, HSTACK(M48, N48:X48), lookupNames, $AB$4:$AB$15, lookupImages, $AC$4:$AC$15, imgs, MAP(names, LAMBDA(n, XLOOKUP(n, lookupNames, lookupImages))), keepImgs, FILTER(imgs, amounts<>0), keepAmoun"&"ts, FILTER(amounts, amounts<>0), MAKEARRAY( 1, COLUMNS(keepAmounts)*2, LAMBDA(r,c, IF( ISODD(c), INDEX(keepImgs, 1, ROUNDUP(c/2)), INDEX(keepAmounts, 1, c/2) ) ) ) )"),"") | F48: =IFERROR(__xludf.DUMMYFUNCTION("""COMPUTED_VALUE"""),1.0) -> 1 | L48: 4 | M48: 0 | N48: 0 | O48: 0 | P48: 0 | Q48: 0 | R48: 0 | S48: 1 | T48: 0 | U48: 0 | V48: 0 | W48: 0 | X48: 0
E49: =IFERROR(__xludf.DUMMYFUNCTION("LET( names, HSTACK(""Coins"", $N$4:$X$4), amounts, HSTACK(M49, N49:X49), lookupNames, $AB$4:$AB$15, lookupImages, $AC$4:$AC$15, imgs, MAP(names, LAMBDA(n, XLOOKUP(n, lookupNames, lookupImages))), keepImgs, FILTER(imgs, amounts<>0), keepAmoun"&"ts, FILTER(amounts, amounts<>0), MAKEARRAY( 1, COLUMNS(keepAmounts)*2, LAMBDA(r,c, IF( ISODD(c), INDEX(keepImgs, 1, ROUNDUP(c/2)), INDEX(keepAmounts, 1, c/2) ) ) ) )"),"") | F49: =IFERROR(__xludf.DUMMYFUNCTION("""COMPUTED_VALUE"""),60.0) -> 60 | L49: 5 | M49: 0 | N49: 0 | O49: 0 | P49: 0 | Q49: 0 | R49: 0 | S49: 0 | T49: 0 | U49: 60 | V49: 0 | W49: 0 | X49: 0
E50: =IFERROR(__xludf.DUMMYFUNCTION("LET( names, HSTACK(""Coins"", $N$4:$X$4), amounts, HSTACK(M50, N50:X50), lookupNames, $AB$4:$AB$15, lookupImages, $AC$4:$AC$15, imgs, MAP(names, LAMBDA(n, XLOOKUP(n, lookupNames, lookupImages))), keepImgs, FILTER(imgs, amounts<>0), keepAmoun"&"ts, FILTER(amounts, amounts<>0), MAKEARRAY( 1, COLUMNS(keepAmounts)*2, LAMBDA(r,c, IF( ISODD(c), INDEX(keepImgs, 1, ROUNDUP(c/2)), INDEX(keepAmounts, 1, c/2) ) ) ) )"),"") | F50: =IFERROR(__xludf.DUMMYFUNCTION("""COMPUTED_VALUE"""),35.0) -> 35 | L50: 6 | M50: 35 | N50: 0 | O50: 0 | P50: 0 | Q50: 0 | R50: 0 | S50: 0 | T50: 0 | U50: 0 | V50: 0 | W50: 0 | X50: 0
E51: =IFERROR(__xludf.DUMMYFUNCTION("LET( names, HSTACK(""Coins"", $N$4:$X$4), amounts, HSTACK(M51, N51:X51), lookupNames, $AB$4:$AB$15, lookupImages, $AC$4:$AC$15, imgs, MAP(names, LAMBDA(n, XLOOKUP(n, lookupNames, lookupImages))), keepImgs, FILTER(imgs, amounts<>0), keepAmoun"&"ts, FILTER(amounts, amounts<>0), MAKEARRAY( 1, COLUMNS(keepAmounts)*2, LAMBDA(r,c, IF( ISODD(c), INDEX(keepImgs, 1, ROUNDUP(c/2)), INDEX(keepAmounts, 1, c/2) ) ) ) )"),"") | F51: =IFERROR(__xludf.DUMMYFUNCTION("""COMPUTED_VALUE"""),100.0) -> 100 | G51: =IFERROR(__xludf.DUMMYFUNCTION("""COMPUTED_VALUE"""),"") | H51: =IFERROR(__xludf.DUMMYFUNCTION("""COMPUTED_VALUE"""),1.0) -> 1 | I51: =IFERROR(__xludf.DUMMYFUNCTION("""COMPUTED_VALUE"""),"") | J51: =IFERROR(__xludf.DUMMYFUNCTION("""COMPUTED_VALUE"""),120.0) -> 120 | L51: 7 | M51: 100 | N51: 0 | O51: 0 | P51: 0 | Q51: 0 | R51: 1 | S51: 0 | T51: 0 | U51: 120 | V51: 0 | W51: 0 | X51: 0

Sheet c_day_v2
A1: Daily Rewards - NEW
L2: all segs
A3: Day | B3: HC Reward | E3: 👁 | L3: Variant 1 | AB3: cur | AC3: image
A4: 1 | B4: =average(M5,M16,M26,M35,M45) -> 10 | L4: Day | M4: Coin | N4: SPT | O4: Red | P4: Chuck | Q4: Bomb | R4: Slingshot | S4: Shuffle | T4: Comet | U4: Unlimited Lives | V4: Unlimited Red | W4: Unlimited Chuck | X4: Unlimited Bomb | AB4: Coins
A5: 2 | B5: 0 | E5: =IFERROR(__xludf.DUMMYFUNCTION("LET( names, HSTACK(""Coins"", $N$4:$X$4), amounts, HSTACK(M5, N5:X5), lookupNames, $AB$4:$AB$15, lookupImages, $AC$4:$AC$15, imgs, MAP(names, LAMBDA(n, XLOOKUP(n, lookupNames, lookupImages))), keepImgs, FILTER(imgs, amounts<>0), keepAmounts,"&" FILTER(amounts, amounts<>0), MAKEARRAY( 1, COLUMNS(keepAmounts)*2, LAMBDA(r,c, IF( ISODD(c), INDEX(keepImgs, 1, ROUNDUP(c/2)), INDEX(keepAmounts, 1, c/2) ) ) ) )"),"") | F5: =IFERROR(__xludf.DUMMYFUNCTION("""COMPUTED_VALUE"""),10.0) -> 10 | L5: 1 | M5: 10 | N5: 0 | O5: 0 | P5: 0 | Q5: 0 | R5: 0 | S5: 0 | T5: 0 | U5: 0 | V5: 0 | W5: 0 | X5: 0 | AB5: SPT
A6: 3 | B6: 0 | E6: =IFERROR(__xludf.DUMMYFUNCTION("LET( names, HSTACK(""Coins"", $N$4:$X$4), amounts, HSTACK(M6, N6:X6), lookupNames, $AB$4:$AB$15, lookupImages, $AC$4:$AC$15, imgs, MAP(names, LAMBDA(n, XLOOKUP(n, lookupNames, lookupImages))), keepImgs, FILTER(imgs, amounts<>0), keepAmounts,"&" FILTER(amounts, amounts<>0), MAKEARRAY( 1, COLUMNS(keepAmounts)*2, LAMBDA(r,c, IF( ISODD(c), INDEX(keepImgs, 1, ROUNDUP(c/2)), INDEX(keepAmounts, 1, c/2) ) ) ) )"),"") | F6: =IFERROR(__xludf.DUMMYFUNCTION("""COMPUTED_VALUE"""),15.0) -> 15 | L6: 2 | M6: 0 | N6: 0 | O6: 0 | P6: 0 | Q6: 0 | R6: 0 | S6: 0 | T6: 0 | U6: 15 | V6: 0 | W6: 0 | X6: 0 | AB6: Red
A7: 4 | B7: =mround(average(M8,M18,M28), 1) -> 10 | E7: =IFERROR(__xludf.DUMMYFUNCTION("LET( names, HSTACK(""Coins"", $N$4:$X$4), amounts, HSTACK(M7, N7:X7), lookupNames, $AB$4:$AB$15, lookupImages, $AC$4:$AC$15, imgs, MAP(names, LAMBDA(n, XLOOKUP(n, lookupNames, lookupImages))), keepImgs, FILTER(imgs, amounts<>0), keepAmounts,"&" FILTER(amounts, amounts<>0), MAKEARRAY( 1, COLUMNS(keepAmounts)*2, LAMBDA(r,c, IF( ISODD(c), INDEX(keepImgs, 1, ROUNDUP(c/2)), INDEX(keepAmounts, 1, c/2) ) ) ) )"),"") | F7: =IFERROR(__xludf.DUMMYFUNCTION("""COMPUTED_VALUE"""),1.0) -> 1 | L7: 3 | M7: 0 | N7: 0 | O7: 0 | P7: 0 | Q7: 0 | R7: 1 | S7: 0 | T7: 0 | U7: 0 | V7: 0 | W7: 0 | X7: 0 | AB7: Chuck
A8: 5 | B8: 0 | E8: =IFERROR(__xludf.DUMMYFUNCTION("LET( names, HSTACK(""Coins"", $N$4:$X$4), amounts, HSTACK(M8, N8:X8), lookupNames, $AB$4:$AB$15, lookupImages, $AC$4:$AC$15, imgs, MAP(names, LAMBDA(n, XLOOKUP(n, lookupNames, lookupImages))), keepImgs, FILTER(imgs, amounts<>0), keepAmounts,"&" FILTER(amounts, amounts<>0), MAKEARRAY( 1, COLUMNS(keepAmounts)*2, LAMBDA(r,c, IF( ISODD(c), INDEX(keepImgs, 1, ROUNDUP(c/2)), INDEX(keepAmounts, 1, c/2) ) ) ) )"),"") | F8: =IFERROR(__xludf.DUMMYFUNCTION("""COMPUTED_VALUE"""),10.0) -> 10 | L8: 4 | M8: 10 | N8: 0 | O8: 0 | P8: 0 | Q8: 0 | R8: 0 | S8: 0 | T8: 0 | U8: 0 | V8: 0 | W8: 0 | X8: 0 | AB8: Bomb
A9: 6 | B9: =mround(AVERAGE(M10, M20, M30, M50),1) -> 10 | E9: =IFERROR(__xludf.DUMMYFUNCTION("LET( names, HSTACK(""Coins"", $N$4:$X$4), amounts, HSTACK(M9, N9:X9), lookupNames, $AB$4:$AB$15, lookupImages, $AC$4:$AC$15, imgs, MAP(names, LAMBDA(n, XLOOKUP(n, lookupNames, lookupImages))), keepImgs, FILTER(imgs, amounts<>0), keepAmounts,"&" FILTER(amounts, amounts<>0), MAKEARRAY( 1, COLUMNS(keepAmounts)*2, LAMBDA(r,c, IF( ISODD(c), INDEX(keepImgs, 1, ROUNDUP(c/2)), INDEX(keepAmounts, 1, c/2) ) ) ) )"),"") | F9: =IFERROR(__xludf.DUMMYFUNCTION("""COMPUTED_VALUE"""),1.0) -> 1 | L9: 5 | M9: 0 | N9: 0 | O9: 0 | P9: 0 | Q9: 0 | R9: 0 | S9: 1 | T9: 0 | U9: 0 | V9: 0 | W9: 0 | X9: 0 | AB9: Slingshot
A10: 7 | B10: 100 | E10: =IFERROR(__xludf.DUMMYFUNCTION("LET( names, HSTACK(""Coins"", $N$4:$X$4), amounts, HSTACK(M10, N10:X10), lookupNames, $AB$4:$AB$15, lookupImages, $AC$4:$AC$15, imgs, MAP(names, LAMBDA(n, XLOOKUP(n, lookupNames, lookupImages))), keepImgs, FILTER(imgs, amounts<>0), keepAmoun"&"ts, FILTER(amounts, amounts<>0), MAKEARRAY( 1, COLUMNS(keepAmounts)*2, LAMBDA(r,c, IF( ISODD(c), INDEX(keepImgs, 1, ROUNDUP(c/2)), INDEX(keepAmounts, 1, c/2) ) ) ) )"),"") | F10: =IFERROR(__xludf.DUMMYFUNCTION("""COMPUTED_VALUE"""),10.0) -> 10 | L10: 6 | M10: 10 | N10: 0 | O10: 0 | P10: 0 | Q10: 0 | R10: 0 | S10: 0 | T10: 0 | U10: 0 | V10: 0 | W10: 0 | X10: 0 | AB10: Shuffle
E11: =IFERROR(__xludf.DUMMYFUNCTION("LET( names, HSTACK(""Coins"", $N$4:$X$4), amounts, HSTACK(M11, N11:X11), lookupNames, $AB$4:$AB$15, lookupImages, $AC$4:$AC$15, imgs, MAP(names, LAMBDA(n, XLOOKUP(n, lookupNames, lookupImages))), keepImgs, FILTER(imgs, amounts<>0), keepAmoun"&"ts, FILTER(amounts, amounts<>0), MAKEARRAY( 1, COLUMNS(keepAmounts)*2, LAMBDA(r,c, IF( ISODD(c), INDEX(keepImgs, 1, ROUNDUP(c/2)), INDEX(keepAmounts, 1, c/2) ) ) ) )"),"") | F11: =IFERROR(__xludf.DUMMYFUNCTION("""COMPUTED_VALUE"""),100.0) -> 100 | G11: =IFERROR(__xludf.DUMMYFUNCTION("""COMPUTED_VALUE"""),"") | H11: =IFERROR(__xludf.DUMMYFUNCTION("""COMPUTED_VALUE"""),120.0) -> 120 | I11: =IFERROR(__xludf.DUMMYFUNCTION("""COMPUTED_VALUE"""),"") | J11: =IFERROR(__xludf.DUMMYFUNCTION("""COMPUTED_VALUE"""),60.0) -> 60 | L11: 7 | M11: 100 | N11: 0 | O11: 0 | P11: 0 | Q11: 0 | R11: 0 | S11: 0 | T11: 0 | U11: 120 | V11: 60 | W11: 0 | X11: 0 | AB11: Comet
A12: Total per cycle | B12: =SUM(B4:B10) -> 130 | AB12: Unlimited Lives
A13: Avg HC/day (7d) | B13: =B12/7 -> 18.571429 | L13: Variant 2 | AB13: Unlimited Red
L14: Day | M14: Coin | N14: SPT | O14: Red | P14: Chuck | Q14: Bomb | R14: Slingshot | S14: Shuffle | T14: Comet | U14: Unlimited Lives | V14: Unlimited Red | W14: Unlimited Chuck | X14: Unlimited Bomb | AB14: Unlimited Chuck
A15: % of old | B15: =B12/c_day!B12 -> 0.71428571 | E15: =IFERROR(__xludf.DUMMYFUNCTION("LET( names, HSTACK(""Coins"", $N$4:$X$4), amounts, HSTACK(M15, N15:X15), lookupNames, $AB$4:$AB$15, lookupImages, $AC$4:$AC$15, imgs, MAP(names, LAMBDA(n, XLOOKUP(n, lookupNames, lookupImages))), keepImgs, FILTER(imgs, amounts<>0), keepAmoun"&"ts, FILTER(amounts, amounts<>0), MAKEARRAY( 1, COLUMNS(keepAmounts)*2, LAMBDA(r,c, IF( ISODD(c), INDEX(keepImgs, 1, ROUNDUP(c/2)), INDEX(keepAmounts, 1, c/2) ) ) ) )"),"") | F15: =IFERROR(__xludf.DUMMYFUNCTION("""COMPUTED_VALUE"""),20.0) -> 20 | L15: 1 | M15: 0 | N15: 0 | O15: 0 | P15: 0 | Q15: 0 | R15: 0 | S15: 0 | T15: 0 | U15: 20 | V15: 0 | W15: 0 | X15: 0 | AB15: Unlimited Bomb
E16: =IFERROR(__xludf.DUMMYFUNCTION("LET( names, HSTACK(""Coins"", $N$4:$X$4), amounts, HSTACK(M16, N16:X16), lookupNames, $AB$4:$AB$15, lookupImages, $AC$4:$AC$15, imgs, MAP(names, LAMBDA(n, XLOOKUP(n, lookupNames, lookupImages))), keepImgs, FILTER(imgs, amounts<>0), keepAmoun"&"ts, FILTER(amounts, amounts<>0), MAKEARRAY( 1, COLUMNS(keepAmounts)*2, LAMBDA(r,c, IF( ISODD(c), INDEX(keepImgs, 1, ROUNDUP(c/2)), INDEX(keepAmounts, 1, c/2) ) ) ) )"),"") | F16: =IFERROR(__xludf.DUMMYFUNCTION("""COMPUTED_VALUE"""),10.0) -> 10 | L16: 2 | M16: 10 | N16: 0 | O16: 0 | P16: 0 | Q16: 0 | R16: 0 | S16: 0 | T16: 0 | U16: 0 | V16: 0 | W16: 0 | X16: 0
E17: =IFERROR(__xludf.DUMMYFUNCTION("LET( names, HSTACK(""Coins"", $N$4:$X$4), amounts, HSTACK(M17, N17:X17), lookupNames, $AB$4:$AB$15, lookupImages, $AC$4:$AC$15, imgs, MAP(names, LAMBDA(n, XLOOKUP(n, lookupNames, lookupImages))), keepImgs, FILTER(imgs, amounts<>0), keepAmoun"&"ts, FILTER(amounts, amounts<>0), MAKEARRAY( 1, COLUMNS(keepAmounts)*2, LAMBDA(r,c, IF( ISODD(c), INDEX(keepImgs, 1, ROUNDUP(c/2)), INDEX(keepAmounts, 1, c/2) ) ) ) )"),"") | F17: =IFERROR(__xludf.DUMMYFUNCTION("""COMPUTED_VALUE"""),1.0) -> 1 | L17: 3 | M17: 0 | N17: 0 | O17: 0 | P17: 0 | Q17: 0 | R17: 1 | S17: 0 | T17: 0 | U17: 0 | V17: 0 | W17: 0 | X17: 0
E18: =IFERROR(__xludf.DUMMYFUNCTION("LET( names, HSTACK(""Coins"", $N$4:$X$4), amounts, HSTACK(M18, N18:X18), lookupNames, $AB$4:$AB$15, lookupImages, $AC$4:$AC$15, imgs, MAP(names, LAMBDA(n, XLOOKUP(n, lookupNames, lookupImages))), keepImgs, FILTER(imgs, amounts<>0), keepAmoun"&"ts, FILTER(amounts, amounts<>0), MAKEARRAY( 1, COLUMNS(keepAmounts)*2, LAMBDA(r,c, IF( ISODD(c), INDEX(keepImgs, 1, ROUNDUP(c/2)), INDEX(keepAmounts, 1, c/2) ) ) ) )"),"") | F18: =IFERROR(__xludf.DUMMYFUNCTION("""COMPUTED_VALUE"""),10.0) -> 10 | L18: 4 | M18: 10 | N18: 0 | O18: 0 | P18: 0 | Q18: 0 | R18: 0 | S18: 0 | T18: 0 | U18: 0 | V18: 0 | W18: 0 | X18: 0
E19: =IFERROR(__xludf.DUMMYFUNCTION("LET( names, HSTACK(""Coins"", $N$4:$X$4), amounts, HSTACK(M19, N19:X19), lookupNames, $AB$4:$AB$15, lookupImages, $AC$4:$AC$15, imgs, MAP(names, LAMBDA(n, XLOOKUP(n, lookupNames, lookupImages))), keepImgs, FILTER(imgs, amounts<>0), keepAmoun"&"ts, FILTER(amounts, amounts<>0), MAKEARRAY( 1, COLUMNS(keepAmounts)*2, LAMBDA(r,c, IF( ISODD(c), INDEX(keepImgs, 1, ROUNDUP(c/2)), INDEX(keepAmounts, 1, c/2) ) ) ) )"),"") | F19: =IFERROR(__xludf.DUMMYFUNCTION("""COMPUTED_VALUE"""),1.0) -> 1 | L19: 5 | M19: 0 | N19: 0 | O19: 0 | P19: 0 | Q19: 0 | R19: 0 | S19: 1 | T19: 0 | U19: 0 | V19: 0 | W19: 0 | X19: 0
E20: =IFERROR(__xludf.DUMMYFUNCTION("LET( names, HSTACK(""Coins"", $N$4:$X$4), amounts, HSTACK(M20, N20:X20), lookupNames, $AB$4:$AB$15, lookupImages, $AC$4:$AC$15, imgs, MAP(names, LAMBDA(n, XLOOKUP(n, lookupNames, lookupImages))), keepImgs, FILTER(imgs, amounts<>0), keepAmoun"&"ts, FILTER(amounts, amounts<>0), MAKEARRAY( 1, COLUMNS(keepAmounts)*2, LAMBDA(r,c, IF( ISODD(c), INDEX(keepImgs, 1, ROUNDUP(c/2)), INDEX(keepAmounts, 1, c/2) ) ) ) )"),"") | F20: =IFERROR(__xludf.DUMMYFUNCTION("""COMPUTED_VALUE"""),10.0) -> 10 | L20: 6 | M20: 10 | N20: 0 | O20: 0 | P20: 0 | Q20: 0 | R20: 0 | S20: 0 | T20: 0 | U20: 0 | V20: 0 | W20: 0 | X20: 0
E21: =IFERROR(__xludf.DUMMYFUNCTION("LET( names, HSTACK(""Coins"", $N$4:$X$4), amounts, HSTACK(M21, N21:X21), lookupNames, $AB$4:$AB$15, lookupImages, $AC$4:$AC$15, imgs, MAP(names, LAMBDA(n, XLOOKUP(n, lookupNames, lookupImages))), keepImgs, FILTER(imgs, amounts<>0), keepAmoun"&"ts, FILTER(amounts, amounts<>0), MAKEARRAY( 1, COLUMNS(keepAmounts)*2, LAMBDA(r,c, IF( ISODD(c), INDEX(keepImgs, 1, ROUNDUP(c/2)), INDEX(keepAmounts, 1, c/2) ) ) ) )"),"") | F21: =IFERROR(__xludf.DUMMYFUNCTION("""COMPUTED_VALUE"""),100.0) -> 100 | G21: =IFERROR(__xludf.DUMMYFUNCTION("""COMPUTED_VALUE"""),"") | H21: =IFERROR(__xludf.DUMMYFUNCTION("""COMPUTED_VALUE"""),120.0) -> 120 | I21: =IFERROR(__xludf.DUMMYFUNCTION("""COMPUTED_VALUE"""),"") | J21: =IFERROR(__xludf.DUMMYFUNCTION("""COMPUTED_VALUE"""),60.0) -> 60 | L21: 7 | M21: 100 | N21: 0 | O21: 0 | P21: 0 | Q21: 0 | R21: 0 | S21: 0 | T21: 0 | U21: 120 | V21: 0 | W21: 60 | X21: 0
L23: Variant 3
L24: Day | M24: Coin | N24: SPT | O24: Red | P24: Chuck | Q24: Bomb | R24: Slingshot | S24: Shuffle | T24: Comet | U24: Unlimited Lives | V24: Unlimited Red | W24: Unlimited Chuck | X24: Unlimited Bomb
E25: =IFERROR(__xludf.DUMMYFUNCTION("LET( names, HSTACK(""Coins"", $N$4:$X$4), amounts, HSTACK(M25, N25:X25), lookupNames, $AB$4:$AB$15, lookupImages, $AC$4:$AC$15, imgs, MAP(names, LAMBDA(n, XLOOKUP(n, lookupNames, lookupImages))), keepImgs, FILTER(imgs, amounts<>0), keepAmoun"&"ts, FILTER(amounts, amounts<>0), MAKEARRAY( 1, COLUMNS(keepAmounts)*2, LAMBDA(r,c, IF( ISODD(c), INDEX(keepImgs, 1, ROUNDUP(c/2)), INDEX(keepAmounts, 1, c/2) ) ) ) )"),"") | F25: =IFERROR(__xludf.DUMMYFUNCTION("""COMPUTED_VALUE"""),15.0) -> 15 | L25: 1 | M25: 0 | N25: 0 | O25: 0 | P25: 0 | Q25: 0 | R25: 0 | S25: 0 | T25: 0 | U25: 15 | V25: 0 | W25: 0 | X25: 0
E26: =IFERROR(__xludf.DUMMYFUNCTION("LET( names, HSTACK(""Coins"", $N$4:$X$4), amounts, HSTACK(M26, N26:X26), lookupNames, $AB$4:$AB$15, lookupImages, $AC$4:$AC$15, imgs, MAP(names, LAMBDA(n, XLOOKUP(n, lookupNames, lookupImages))), keepImgs, FILTER(imgs, amounts<>0), keepAmoun"&"ts, FILTER(amounts, amounts<>0), MAKEARRAY( 1, COLUMNS(keepAmounts)*2, LAMBDA(r,c, IF( ISODD(c), INDEX(keepImgs, 1, ROUNDUP(c/2)), INDEX(keepAmounts, 1, c/2) ) ) ) )"),"") | F26: =IFERROR(__xludf.DUMMYFUNCTION("""COMPUTED_VALUE"""),10.0) -> 10 | L26: 2 | M26: 10 | N26: 0 | O26: 0 | P26: 0 | Q26: 0 | R26: 0 | S26: 0 | T26: 0 | U26: 0 | V26: 0 | W26: 0 | X26: 0
E27: =IFERROR(__xludf.DUMMYFUNCTION("LET( names, HSTACK(""Coins"", $N$4:$X$4), amounts, HSTACK(M27, N27:X27), lookupNames, $AB$4:$AB$15, lookupImages, $AC$4:$AC$15, imgs, MAP(names, LAMBDA(n, XLOOKUP(n, lookupNames, lookupImages))), keepImgs, FILTER(imgs, amounts<>0), keepAmoun"&"ts, FILTER(amounts, amounts<>0), MAKEARRAY( 1, COLUMNS(keepAmounts)*2, LAMBDA(r,c, IF( ISODD(c), INDEX(keepImgs, 1, ROUNDUP(c/2)), INDEX(keepAmounts, 1, c/2) ) ) ) )"),"") | F27: =IFERROR(__xludf.DUMMYFUNCTION("""COMPUTED_VALUE"""),1.0) -> 1 | L27: 3 | M27: 0 | N27: 0 | O27: 0 | P27: 0 | Q27: 0 | R27: 1 | S27: 0 | T27: 0 | U27: 0 | V27: 0 | W27: 0 | X27: 0
E28: =IFERROR(__xludf.DUMMYFUNCTION("LET( names, HSTACK(""Coins"", $N$4:$X$4), amounts, HSTACK(M28, N28:X28), lookupNames, $AB$4:$AB$15, lookupImages, $AC$4:$AC$15, imgs, MAP(names, LAMBDA(n, XLOOKUP(n, lookupNames, lookupImages))), keepImgs, FILTER(imgs, amounts<>0), keepAmoun"&"ts, FILTER(amounts, amounts<>0), MAKEARRAY( 1, COLUMNS(keepAmounts)*2, LAMBDA(r,c, IF( ISODD(c), INDEX(keepImgs, 1, ROUNDUP(c/2)), INDEX(keepAmounts, 1, c/2) ) ) ) )"),"") | F28: =IFERROR(__xludf.DUMMYFUNCTION("""COMPUTED_VALUE"""),10.0) -> 10 | L28: 4 | M28: 10 | N28: 0 | O28: 0 | P28: 0 | Q28: 0 | R28: 0 | S28: 0 | T28: 0 | U28: 0 | V28: 0 | W28: 0 | X28: 0
E29: =IFERROR(__xludf.DUMMYFUNCTION("LET( names, HSTACK(""Coins"", $N$4:$X$4), amounts, HSTACK(M29, N29:X29), lookupNames, $AB$4:$AB$15, lookupImages, $AC$4:$AC$15, imgs, MAP(names, LAMBDA(n, XLOOKUP(n, lookupNames, lookupImages))), keepImgs, FILTER(imgs, amounts<>0), keepAmoun"&"ts, FILTER(amounts, amounts<>0), MAKEARRAY( 1, COLUMNS(keepAmounts)*2, LAMBDA(r,c, IF( ISODD(c), INDEX(keepImgs, 1, ROUNDUP(c/2)), INDEX(keepAmounts, 1, c/2) ) ) ) )"),"") | F29: =IFERROR(__xludf.DUMMYFUNCTION("""COMPUTED_VALUE"""),1.0) -> 1 | L29: 5 | M29: 0 | N29: 0 | O29: 0 | P29: 0 | Q29: 0 | R29: 0 | S29: 1 | T29: 0 | U29: 0 | V29: 0 | W29: 0 | X29: 0
E30: =IFERROR(__xludf.DUMMYFUNCTION("LET( names, HSTACK(""Coins"", $N$4:$X$4), amounts, HSTACK(M30, N30:X30), lookupNames, $AB$4:$AB$15, lookupImages, $AC$4:$AC$15, imgs, MAP(names, LAMBDA(n, XLOOKUP(n, lookupNames, lookupImages))), keepImgs, FILTER(imgs, amounts<>0), keepAmoun"&"ts, FILTER(amounts, amounts<>0), MAKEARRAY( 1, COLUMNS(keepAmounts)*2, LAMBDA(r,c, IF( ISODD(c), INDEX(keepImgs, 1, ROUNDUP(c/2)), INDEX(keepAmounts, 1, c/2) ) ) ) )"),"") | F30: =IFERROR(__xludf.DUMMYFUNCTION("""COMPUTED_VALUE"""),10.0) -> 10 | L30: 6 | M30: 10 | N30: 0 | O30: 0 | P30: 0 | Q30: 0 | R30: 0 | S30: 0 | T30: 0 | U30: 0 | V30: 0 | W30: 0 | X30: 0
E31: =IFERROR(__xludf.DUMMYFUNCTION("LET( names, HSTACK(""Coins"", $N$4:$X$4), amounts, HSTACK(M31, N31:X31), lookupNames, $AB$4:$AB$15, lookupImages, $AC$4:$AC$15, imgs, MAP(names, LAMBDA(n, XLOOKUP(n, lookupNames, lookupImages))), keepImgs, FILTER(imgs, amounts<>0), keepAmoun"&"ts, FILTER(amounts, amounts<>0), MAKEARRAY( 1, COLUMNS(keepAmounts)*2, LAMBDA(r,c, IF( ISODD(c), INDEX(keepImgs, 1, ROUNDUP(c/2)), INDEX(keepAmounts, 1, c/2) ) ) ) )"),"") | F31: =IFERROR(__xludf.DUMMYFUNCTION("""COMPUTED_VALUE"""),100.0) -> 100 | G31: =IFERROR(__xludf.DUMMYFUNCTION("""COMPUTED_VALUE"""),"") | H31: =IFERROR(__xludf.DUMMYFUNCTION("""COMPUTED_VALUE"""),120.0) -> 120 | I31: =IFERROR(__xludf.DUMMYFUNCTION("""COMPUTED_VALUE"""),"") | J31: =IFERROR(__xludf.DUMMYFUNCTION("""COMPUTED_VALUE"""),30.0) -> 30 | L31: 7 | M31: 100 | N31: 0 | O31: 0 | P31: 0 | Q31: 0 | R31: 0 | S31: 0 | T31: 0 | U31: 120 | V31: 0 | W31: 0 | X31: 30
L33: Variant 4
L34: Day | M34: Coin | N34: SPT | O34: Red | P34: Chuck | Q34: Bomb | R34: Slingshot | S34: Shuffle | T34: Comet | U34: Unlimited Lives | V34: Unlimited Red | W34: Unlimited Chuck | X34: Unlimited Bomb
E35: =IFERROR(__xludf.DUMMYFUNCTION("LET( names, HSTACK(""Coins"", $N$4:$X$4), amounts, HSTACK(M35, N35:X35), lookupNames, $AB$4:$AB$15, lookupImages, $AC$4:$AC$15, imgs, MAP(names, LAMBDA(n, XLOOKUP(n, lookupNames, lookupImages))), keepImgs, FILTER(imgs, amounts<>0), keepAmoun"&"ts, FILTER(amounts, amounts<>0), MAKEARRAY( 1, COLUMNS(keepAmounts)*2, LAMBDA(r,c, IF( ISODD(c), INDEX(keepImgs, 1, ROUNDUP(c/2)), INDEX(keepAmounts, 1, c/2) ) ) ) )"),"") | F35: =IFERROR(__xludf.DUMMYFUNCTION("""COMPUTED_VALUE"""),10.0) -> 10 | L35: 1 | M35: 10 | N35: 0 | O35: 0 | P35: 0 | Q35: 0 | R35: 0 | S35: 0 | T35: 0 | U35: 0 | V35: 0 | W35: 0 | X35: 0
E36: =IFERROR(__xludf.DUMMYFUNCTION("LET( names, HSTACK(""Coins"", $N$4:$X$4), amounts, HSTACK(M36, N36:X36), lookupNames, $AB$4:$AB$15, lookupImages, $AC$4:$AC$15, imgs, MAP(names, LAMBDA(n, XLOOKUP(n, lookupNames, lookupImages))), keepImgs, FILTER(imgs, amounts<>0), keepAmoun"&"ts, FILTER(amounts, amounts<>0), MAKEARRAY( 1, COLUMNS(keepAmounts)*2, LAMBDA(r,c, IF( ISODD(c), INDEX(keepImgs, 1, ROUNDUP(c/2)), INDEX(keepAmounts, 1, c/2) ) ) ) )"),"") | F36: =IFERROR(__xludf.DUMMYFUNCTION("""COMPUTED_VALUE"""),30.0) -> 30 | L36: 2 | M36: 0 | N36: 0 | O36: 0 | P36: 0 | Q36: 0 | R36: 0 | S36: 0 | T36: 0 | U36: 30 | V36: 0 | W36: 0 | X36: 0
E37: =IFERROR(__xludf.DUMMYFUNCTION("LET( names, HSTACK(""Coins"", $N$4:$X$4), amounts, HSTACK(M37, N37:X37), lookupNames, $AB$4:$AB$15, lookupImages, $AC$4:$AC$15, imgs, MAP(names, LAMBDA(n, XLOOKUP(n, lookupNames, lookupImages))), keepImgs, FILTER(imgs, amounts<>0), keepAmoun"&"ts, FILTER(amounts, amounts<>0), MAKEARRAY( 1, COLUMNS(keepAmounts)*2, LAMBDA(r,c, IF( ISODD(c), INDEX(keepImgs, 1, ROUNDUP(c/2)), INDEX(keepAmounts, 1, c/2) ) ) ) )"),"") | F37: =IFERROR(__xludf.DUMMYFUNCTION("""COMPUTED_VALUE"""),1.0) -> 1 | L37: 3 | M37: 0 | N37: 0 | O37: 0 | P37: 0 | Q37: 0 | R37: 0 | S37: 1 | T37: 0 | U37: 0 | V37: 0 | W37: 0 | X37: 0
E38: =IFERROR(__xludf.DUMMYFUNCTION("LET( names, HSTACK(""Coins"", $N$4:$X$4), amounts, HSTACK(M38, N38:X38), lookupNames, $AB$4:$AB$15, lookupImages, $AC$4:$AC$15, imgs, MAP(names, LAMBDA(n, XLOOKUP(n, lookupNames, lookupImages))), keepImgs, FILTER(imgs, amounts<>0), keepAmoun"&"ts, FILTER(amounts, amounts<>0), MAKEARRAY( 1, COLUMNS(keepAmounts)*2, LAMBDA(r,c, IF( ISODD(c), INDEX(keepImgs, 1, ROUNDUP(c/2)), INDEX(keepAmounts, 1, c/2) ) ) ) )"),"") | F38: =IFERROR(__xludf.DUMMYFUNCTION("""COMPUTED_VALUE"""),1.0) -> 1 | L38: 4 | M38: 0 | N38: 0 | O38: 0 | P38: 0 | Q38: 0 | R38: 1 | S38: 0 | T38: 0 | U38: 0 | V38: 0 | W38: 0 | X38: 0
E39: =IFERROR(__xludf.DUMMYFUNCTION("LET( names, HSTACK(""Coins"", $N$4:$X$4), amounts, HSTACK(M39, N39:X39), lookupNames, $AB$4:$AB$15, lookupImages, $AC$4:$AC$15, imgs, MAP(names, LAMBDA(n, XLOOKUP(n, lookupNames, lookupImages))), keepImgs, FILTER(imgs, amounts<>0), keepAmoun"&"ts, FILTER(amounts, amounts<>0), MAKEARRAY( 1, COLUMNS(keepAmounts)*2, LAMBDA(r,c, IF( ISODD(c), INDEX(keepImgs, 1, ROUNDUP(c/2)), INDEX(keepAmounts, 1, c/2) ) ) ) )"),"") | F39: =IFERROR(__xludf.DUMMYFUNCTION("""COMPUTED_VALUE"""),10.0) -> 10 | L39: 5 | M39: 10 | N39: 0 | O39: 0 | P39: 0 | Q39: 0 | R39: 0 | S39: 0 | T39: 0 | U39: 0 | V39: 0 | W39: 0 | X39: 0
E40: =IFERROR(__xludf.DUMMYFUNCTION("LET( names, HSTACK(""Coins"", $N$4:$X$4), amounts, HSTACK(M40, N40:X40), lookupNames, $AB$4:$AB$15, lookupImages, $AC$4:$AC$15, imgs, MAP(names, LAMBDA(n, XLOOKUP(n, lookupNames, lookupImages))), keepImgs, FILTER(imgs, amounts<>0), keepAmoun"&"ts, FILTER(amounts, amounts<>0), MAKEARRAY( 1, COLUMNS(keepAmounts)*2, LAMBDA(r,c, IF( ISODD(c), INDEX(keepImgs, 1, ROUNDUP(c/2)), INDEX(keepAmounts, 1, c/2) ) ) ) )"),"") | F40: =IFERROR(__xludf.DUMMYFUNCTION("""COMPUTED_VALUE"""),1.0) -> 1 | L40: 6 | M40: 0 | N40: 0 | O40: 0 | P40: 0 | Q40: 0 | R40: 1 | S40: 0 | T40: 0 | U40: 0 | V40: 0 | W40: 0 | X40: 0
E41: =IFERROR(__xludf.DUMMYFUNCTION("LET( names, HSTACK(""Coins"", $N$4:$X$4), amounts, HSTACK(M41, N41:X41), lookupNames, $AB$4:$AB$15, lookupImages, $AC$4:$AC$15, imgs, MAP(names, LAMBDA(n, XLOOKUP(n, lookupNames, lookupImages))), keepImgs, FILTER(imgs, amounts<>0), keepAmoun"&"ts, FILTER(amounts, amounts<>0), MAKEARRAY( 1, COLUMNS(keepAmounts)*2, LAMBDA(r,c, IF( ISODD(c), INDEX(keepImgs, 1, ROUNDUP(c/2)), INDEX(keepAmounts, 1, c/2) ) ) ) )"),"") | F41: =IFERROR(__xludf.DUMMYFUNCTION("""COMPUTED_VALUE"""),100.0) -> 100 | G41: =IFERROR(__xludf.DUMMYFUNCTION("""COMPUTED_VALUE"""),"") | H41: =IFERROR(__xludf.DUMMYFUNCTION("""COMPUTED_VALUE"""),1.0) -> 1 | I41: =IFERROR(__xludf.DUMMYFUNCTION("""COMPUTED_VALUE"""),"") | J41: =IFERROR(__xludf.DUMMYFUNCTION("""COMPUTED_VALUE"""),120.0) -> 120 | L41: 7 | M41: 100 | N41: 0 | O41: 0 | P41: 0 | Q41: 0 | R41: 0 | S41: 0 | T41: 1 | U41: 120 | V41: 0 | W41: 0 | X41: 0
L43: Variant 5
L44: Day | M44: Coin | N44: SPT | O44: Red | P44: Chuck | Q44: Bomb | R44: Slingshot | S44: Shuffle | T44: Comet | U44: Unlimited Lives | V44: Unlimited Red | W44: Unlimited Chuck | X44: Unlimited Bomb
E45: =IFERROR(__xludf.DUMMYFUNCTION("LET( names, HSTACK(""Coins"", $N$4:$X$4), amounts, HSTACK(M45, N45:X45), lookupNames, $AB$4:$AB$15, lookupImages, $AC$4:$AC$15, imgs, MAP(names, LAMBDA(n, XLOOKUP(n, lookupNames, lookupImages))), keepImgs, FILTER(imgs, amounts<>0), keepAmoun"&"ts, FILTER(amounts, amounts<>0), MAKEARRAY( 1, COLUMNS(keepAmounts)*2, LAMBDA(r,c, IF( ISODD(c), INDEX(keepImgs, 1, ROUNDUP(c/2)), INDEX(keepAmounts, 1, c/2) ) ) ) )"),"") | F45: =IFERROR(__xludf.DUMMYFUNCTION("""COMPUTED_VALUE"""),10.0) -> 10 | L45: 1 | M45: 10 | N45: 0 | O45: 0 | P45: 0 | Q45: 0 | R45: 0 | S45: 0 | T45: 0 | U45: 0 | V45: 0 | W45: 0 | X45: 0
E46: =IFERROR(__xludf.DUMMYFUNCTION("LET( names, HSTACK(""Coins"", $N$4:$X$4), amounts, HSTACK(M46, N46:X46), lookupNames, $AB$4:$AB$15, lookupImages, $AC$4:$AC$15, imgs, MAP(names, LAMBDA(n, XLOOKUP(n, lookupNames, lookupImages))), keepImgs, FILTER(imgs, amounts<>0), keepAmoun"&"ts, FILTER(amounts, amounts<>0), MAKEARRAY( 1, COLUMNS(keepAmounts)*2, LAMBDA(r,c, IF( ISODD(c), INDEX(keepImgs, 1, ROUNDUP(c/2)), INDEX(keepAmounts, 1, c/2) ) ) ) )"),"") | F46: =IFERROR(__xludf.DUMMYFUNCTION("""COMPUTED_VALUE"""),15.0) -> 15 | L46: 2 | M46: 0 | N46: 0 | O46: 0 | P46: 0 | Q46: 0 | R46: 0 | S46: 0 | T46: 0 | U46: 15 | V46: 0 | W46: 0 | X46: 0
E47: =IFERROR(__xludf.DUMMYFUNCTION("LET( names, HSTACK(""Coins"", $N$4:$X$4), amounts, HSTACK(M47, N47:X47), lookupNames, $AB$4:$AB$15, lookupImages, $AC$4:$AC$15, imgs, MAP(names, LAMBDA(n, XLOOKUP(n, lookupNames, lookupImages))), keepImgs, FILTER(imgs, amounts<>0), keepAmoun"&"ts, FILTER(amounts, amounts<>0), MAKEARRAY( 1, COLUMNS(keepAmounts)*2, LAMBDA(r,c, IF( ISODD(c), INDEX(keepImgs, 1, ROUNDUP(c/2)), INDEX(keepAmounts, 1, c/2) ) ) ) )"),"") | F47: =IFERROR(__xludf.DUMMYFUNCTION("""COMPUTED_VALUE"""),1.0) -> 1 | L47: 3 | M47: 0 | N47: 0 | O47: 0 | P47: 0 | Q47: 0 | R47: 1 | S47: 0 | T47: 0 | U47: 0 | V47: 0 | W47: 0 | X47: 0
E48: =IFERROR(__xludf.DUMMYFUNCTION("LET( names, HSTACK(""Coins"", $N$4:$X$4), amounts, HSTACK(M48, N48:X48), lookupNames, $AB$4:$AB$15, lookupImages, $AC$4:$AC$15, imgs, MAP(names, LAMBDA(n, XLOOKUP(n, lookupNames, lookupImages))), keepImgs, FILTER(imgs, amounts<>0), keepAmoun"&"ts, FILTER(amounts, amounts<>0), MAKEARRAY( 1, COLUMNS(keepAmounts)*2, LAMBDA(r,c, IF( ISODD(c), INDEX(keepImgs, 1, ROUNDUP(c/2)), INDEX(keepAmounts, 1, c/2) ) ) ) )"),"") | F48: =IFERROR(__xludf.DUMMYFUNCTION("""COMPUTED_VALUE"""),1.0) -> 1 | L48: 4 | M48: 0 | N48: 0 | O48: 0 | P48: 0 | Q48: 0 | R48: 0 | S48: 1 | T48: 0 | U48: 0 | V48: 0 | W48: 0 | X48: 0
E49: =IFERROR(__xludf.DUMMYFUNCTION("LET( names, HSTACK(""Coins"", $N$4:$X$4), amounts, HSTACK(M49, N49:X49), lookupNames, $AB$4:$AB$15, lookupImages, $AC$4:$AC$15, imgs, MAP(names, LAMBDA(n, XLOOKUP(n, lookupNames, lookupImages))), keepImgs, FILTER(imgs, amounts<>0), keepAmoun"&"ts, FILTER(amounts, amounts<>0), MAKEARRAY( 1, COLUMNS(keepAmounts)*2, LAMBDA(r,c, IF( ISODD(c), INDEX(keepImgs, 1, ROUNDUP(c/2)), INDEX(keepAmounts, 1, c/2) ) ) ) )"),"") | F49: =IFERROR(__xludf.DUMMYFUNCTION("""COMPUTED_VALUE"""),60.0) -> 60 | L49: 5 | M49: 0 | N49: 0 | O49: 0 | P49: 0 | Q49: 0 | R49: 0 | S49: 0 | T49: 0 | U49: 60 | V49: 0 | W49: 0 | X49: 0
E50: =IFERROR(__xludf.DUMMYFUNCTION("LET( names, HSTACK(""Coins"", $N$4:$X$4), amounts, HSTACK(M50, N50:X50), lookupNames, $AB$4:$AB$15, lookupImages, $AC$4:$AC$15, imgs, MAP(names, LAMBDA(n, XLOOKUP(n, lookupNames, lookupImages))), keepImgs, FILTER(imgs, amounts<>0), keepAmoun"&"ts, FILTER(amounts, amounts<>0), MAKEARRAY( 1, COLUMNS(keepAmounts)*2, LAMBDA(r,c, IF( ISODD(c), INDEX(keepImgs, 1, ROUNDUP(c/2)), INDEX(keepAmounts, 1, c/2) ) ) ) )"),"") | F50: =IFERROR(__xludf.DUMMYFUNCTION("""COMPUTED_VALUE"""),10.0) -> 10 | L50: 6 | M50: 10 | N50: 0 | O50: 0 | P50: 0 | Q50: 0 | R50: 0 | S50: 0 | T50: 0 | U50: 0 | V50: 0 | W50: 0 | X50: 0
E51: =IFERROR(__xludf.DUMMYFUNCTION("LET( names, HSTACK(""Coins"", $N$4:$X$4), amounts, HSTACK(M51, N51:X51), lookupNames, $AB$4:$AB$15, lookupImages, $AC$4:$AC$15, imgs, MAP(names, LAMBDA(n, XLOOKUP(n, lookupNames, lookupImages))), keepImgs, FILTER(imgs, amounts<>0), keepAmoun"&"ts, FILTER(amounts, amounts<>0), MAKEARRAY( 1, COLUMNS(keepAmounts)*2, LAMBDA(r,c, IF( ISODD(c), INDEX(keepImgs, 1, ROUNDUP(c/2)), INDEX(keepAmounts, 1, c/2) ) ) ) )"),"") | F51: =IFERROR(__xludf.DUMMYFUNCTION("""COMPUTED_VALUE"""),100.0) -> 100 | G51: =IFERROR(__xludf.DUMMYFUNCTION("""COMPUTED_VALUE"""),"") | H51: =IFERROR(__xludf.DUMMYFUNCTION("""COMPUTED_VALUE"""),1.0) -> 1 | I51: =IFERROR(__xludf.DUMMYFUNCTION("""COMPUTED_VALUE"""),"") | J51: =IFERROR(__xludf.DUMMYFUNCTION("""COMPUTED_VALUE"""),120.0) -> 120 | L51: 7 | M51: 100 | N51: 0 | O51: 0 | P51: 0 | Q51: 0 | R51: 1 | S51: 0 | T51: 0 | U51: 120 | V51: 0 | W51: 0 | X51: 0

Sheet SP
A1: Season Pass
A2: Season Pass - Goals and Rewards | D2: Season Pass - Goals and Rewards
A3: Tier | D3: Free Track | X3: Paid Track
A4: Tier | B4: Incr real | C4: Cumul | D4: Coins | E4: SPT | F4: SPT x2 | G4: Red | H4: Chuck | I4: Bomb | J4: Slingshot | K4: Shuffle | L4: Comet | M4: Unlimited Lives | N4: Unlimited Red | O4: Unlimited Chuck | P4: Unlimited Bomb | Q4: Avatar | R4: 1-star Dly | S4: 2-star Dly | T4: 3-star Dly | U4: 4-star Dly | V4: 5-star Dly | W4: 6-star Dly | X4: Coins | Y4: SPT | Z4: SPT x2 | AA4: Red | AB4: Chuck | AC4: Bomb | AD4: Slingshot | AE4: Shuffle | AF4: Comet | AG4: Unlimited Lives | AH4: Unlimited Red | AI4: Unlimited Chuck | AJ4: Unlimited Bomb | AK4: Avatar | AL4: 1-star Dly | AM4: 2-star Dly | AN4: 3-star Dly | AO4: 4-star Dly | AP4: 5-star Dly | AQ4: 6-star Dly
A5: 1 | B5: 10 | C5: =B5 -> 10 | D5: 0 | E5: 0 | F5: 0 | G5: 0 | H5: 1 | I5: 0 | J5: 0 | K5: 0 | L5: 0 | M5: 0 | N5: 10 | O5: 0 | P5: 0 | Q5: 0 | R5: 0 | S5: 0 | T5: 0 | U5: 0 | V5: 0 | W5: 0 | X5: 0 | Y5: 0 | Z5: 0 | AA5: 0 | AB5: 0 | AC5: 0 | AD5: 0 | AE5: 0 | AF5: 0 | AG5: 120 | AH5: 0 | AI5: 15 | AJ5: 0 | AK5: 0 | AL5: 0 | AM5: 0 | AN5: 0 | AO5: 0 | AP5: 0 | AQ5: 0
A6: =A5+1 -> 2 | B6: 14 | C6: =B6+C5 -> 24 | D6: 10 | E6: 0 | F6: 0 | G6: 0 | H6: 0 | I6: 0 | J6: 0 | K6: 0 | L6: 0 | M6: 0 | N6: 0 | O6: 0 | P6: 0 | Q6: 0 | R6: 0 | S6: 0 | T6: 0 | U6: 0 | V6: 0 | W6: 0 | X6: 25 | Y6: 0 | Z6: 0 | AA6: 0 | AB6: 0 | AC6: 0 | AD6: 0 | AE6: 0 | AF6: 0 | AG6: 0 | AH6: 0 | AI6: 0 | AJ6: 0 | AK6: 0 | AL6: 0 | AM6: 0 | AN6: 0 | AO6: 0 | AP6: 0 | AQ6: 0
A7: =A6+1 -> 3 | B7: 20 | C7: =B7+C6 -> 44 | D7: 0 | E7: 0 | F7: 0 | G7: 0 | H7: 0 | I7: 0 | J7: 0 | K7: 0 | L7: 0 | M7: 60 | N7: 0 | O7: 0 | P7: 0 | Q7: 0 | R7: 0 | S7: 0 | T7: 0 | U7: 0 | V7: 0 | W7: 0 | X7: 0 | Y7: 0 | Z7: 0 | AA7: 1 | AB7: 0 | AC7: 0 | AD7: 0 | AE7: 0 | AF7: 0 | AG7: 0 | AH7: 0 | AI7: 0 | AJ7: 0 | AK7: 0 | AL7: 0 | AM7: 0 | AN7: 0 | AO7: 0 | AP7: 0 | AQ7: 0
A8: =A7+1 -> 4 | B8: 28 | C8: =B8+C7 -> 72 | D8: 0 | E8: 0 | F8: 0 | G8: 0 | H8: 0 | I8: 0 | J8: 0 | K8: 0 | L8: 0 | M8: 0 | N8: 0 | O8: 15 | P8: 0 | Q8: 0 | R8: 0 | S8: 0 | T8: 0 | U8: 0 | V8: 0 | W8: 0 | X8: 0 | Y8: 0 | Z8: 0 | AA8: 0 | AB8: 0 | AC8: 0 | AD8: 0 | AE8: 1 | AF8: 0 | AG8: 0 | AH8: 0 | AI8: 0 | AJ8: 0 | AK8: 0 | AL8: 0 | AM8: 0 | AN8: 0 | AO8: 0 | AP8: 0 | AQ8: 0
A9: =A8+1 -> 5 | B9: 35 | C9: =B9+C8 -> 107 | D9: 10 | E9: 0 | F9: 0 | G9: 0 | H9: 0 | I9: 0 | J9: 0 | K9: 0 | L9: 0 | M9: 0 | N9: 0 | O9: 0 | P9: 0 | Q9: 0 | R9: 0 | S9: 0 | T9: 0 | U9: 0 | V9: 0 | W9: 0 | X9: 25 | Y9: 0 | Z9: 0 | AA9: 0 | AB9: 0 | AC9: 0 | AD9: 0 | AE9: 0 | AF9: 0 | AG9: 30 | AH9: 0 | AI9: 0 | AJ9: 0 | AK9: 0 | AL9: 0 | AM9: 0 | AN9: 0 | AO9: 0 | AP9: 0 | AQ9: 0
A10: =A9+1 -> 6 | B10: 70 | C10: =B10+C9 -> 177 | D10: 0 | E10: 0 | F10: 0 | G10: 1 | H10: 0 | I10: 0 | J10: 0 | K10: 0 | L10: 0 | M10: 0 | N10: 0 | O10: 0 | P10: 0 | Q10: 0 | R10: 0 | S10: 0 | T10: 0 | U10: 0 | V10: 0 | W10: 0 | X10: 0 | Y10: 0 | Z10: 0 | AA10: 0 | AB10: 0 | AC10: 1 | AD10: 0 | AE10: 0 | AF10: 0 | AG10: 0 | AH10: 0 | AI10: 0 | AJ10: 0 | AK10: 0 | AL10: 0 | AM10: 0 | AN10: 0 | AO10: 0 | AP10: 0 | AQ10: 0
A11: =A10+1 -> 7 | B11: 70 | C11: =B11+C10 -> 247 | D11: 0 | E11: 0 | F11: 0 | G11: 0 | H11: 1 | I11: 0 | J11: 0 | K11: 0 | L11: 0 | M11: 0 | N11: 0 | O11: 0 | P11: 0 | Q11: 0 | R11: 0 | S11: 0 | T11: 0 | U11: 0 | V11: 0 | W11: 0 | X11: 0 | Y11: 0 | Z11: 0 | AA11: 0 | AB11: 0 | AC11: 0 | AD11: 0 | AE11: 0 | AF11: 0 | AG11: 0 | AH11: 0 | AI11: 0 | AJ11: 10 | AK11: 0 | AL11: 0 | AM11: 0 | AN11: 0 | AO11: 0 | AP11: 0 | AQ11: 0
A12: =A11+1 -> 8 | B12: 70 | C12: =B12+C11 -> 317 | D12: 0 | E12: 0 | F12: 0 | G12: 0 | H12: 0 | I12: 0 | J12: 0 | K12: 0 | L12: 0 | M12: 15 | N12: 0 | O12: 0 | P12: 0 | Q12: 0 | R12: 0 | S12: 0 | T12: 0 | U12: 0 | V12: 0 | W12: 0 | X12: 0 | Y12: 0 | Z12: 0 | AA12: 0 | AB12: 0 | AC12: 0 | AD12: 1 | AE12: 0 | AF12: 0 | AG12: 0 | AH12: 0 | AI12: 0 | AJ12: 0 | AK12: 0 | AL12: 0 | AM12: 0 | AN12: 0 | AO12: 0 | AP12: 0 | AQ12: 0
A13: =A12+1 -> 9 | B13: 70 | C13: =B13+C12 -> 387 | D13: 0 | E13: 0 | F13: 0 | G13: 0 | H13: 0 | I13: 0 | J13: 0 | K13: 0 | L13: 0 | M13: 0 | N13: 10 | O13: 0 | P13: 0 | Q13: 0 | R13: 0 | S13: 0 | T13: 0 | U13: 0 | V13: 0 | W13: 0 | X13: 0 | Y13: 0 | Z13: 0 | AA13: 0 | AB13: 0 | AC13: 0 | AD13: 0 | AE13: 1 | AF13: 0 | AG13: 0 | AH13: 0 | AI13: 0 | AJ13: 0 | AK13: 0 | AL13: 0 | AM13: 0 | AN13: 0 | AO13: 0 | AP13: 0 | AQ13: 0
A14: =A13+1 -> 10 | B14: 100 | C14: =B14+C13 -> 487 | D14: 10 | E14: 0 | F14: 0 | G14: 0 | H14: 0 | I14: 0 | J14: 0 | K14: 0 | L14: 0 | M14: 0 | N14: 0 | O14: 0 | P14: 0 | Q14: 0 | R14: 0 | S14: 0 | T14: 0 | U14: 0 | V14: 0 | W14: 0 | X14: 25 | Y14: 0 | Z14: 0 | AA14: 0 | AB14: 0 | AC14: 0 | AD14: 0 | AE14: 0 | AF14: 0 | AG14: 30 | AH14: 0 | AI14: 0 | AJ14: 0 | AK14: 0 | AL14: 0 | AM14: 0 | AN14: 0 | AO14: 0 | AP14: 0 | AQ14: 0
A15: =A14+1 -> 11 | B15: 100 | C15: =B15+C14 -> 587 | D15: 0 | E15: 0 | F15: 0 | G15: 0 | H15: 0 | I15: 0 | J15: 0 | K15: 0 | L15: 0 | M15: 15 | N15: 0 | O15: 0 | P15: 0 | Q15: 0 | R15: 0 | S15: 0 | T15: 0 | U15: 0 | V15: 0 | W15: 0 | X15: 0 | Y15: 0 | Z15: 0 | AA15: 0 | AB15: 0 | AC15: 0 | AD15: 0 | AE15: 0 | AF15: 1 | AG15: 0 | AH15: 0 | AI15: 0 | AJ15: 0 | AK15: 0 | AL15: 0 | AM15: 0 | AN15: 0 | AO15: 0 | AP15: 0 | AQ15: 0
A16: =A15+1 -> 12 | B16: 100 | C16: =B16+C15 -> 687 | D16: 0 | E16: 0 | F16: 0 | G16: 1 | H16: 0 | I16: 0 | J16: 0 | K16: 0 | L16: 0 | M16: 0 | N16: 0 | O16: 0 | P16: 0 | Q16: 0 | R16: 0 | S16: 0 | T16: 0 | U16: 0 | V16: 0 | W16: 0 | X16: 0 | Y16: 0 | Z16: 0 | AA16: 0 | AB16: 1 | AC16: 0 | AD16: 0 | AE16: 0 | AF16: 0 | AG16: 0 | AH16: 0 | AI16: 0 | AJ16: 0 | AK16: 0 | AL16: 0 | AM16: 0 | AN16: 0 | AO16: 0 | AP16: 0 | AQ16: 0
A17: =A16+1 -> 13 | B17: 100 | C17: =B17+C16 -> 787 | D17: 0 | E17: 0 | F17: 0 | G17: 0 | H17: 0 | I17: 0 | J17: 0 | K17: 1 | L17: 0 | M17: 0 | N17: 0 | O17: 0 | P17: 0 | Q17: 0 | R17: 0 | S17: 0 | T17: 0 | U17: 0 | V17: 0 | W17: 0 | X17: 0 | Y17: 0 | Z17: 0 | AA17: 0 | AB17: 0 | AC17: 0 | AD17: 0 | AE17: 0 | AF17: 0 | AG17: 0 | AH17: 0 | AI17: 15 | AJ17: 0 | AK17: 0 | AL17: 0 | AM17: 0 | AN17: 0 | AO17: 0 | AP17: 0 | AQ17: 0
... A34: =A33+1 -> 30 | B34: 270 | C34: =B34+C33 -> 3557 | D34: 40 | E34: 0 | F34: 0 | G34: 0 | H34: 0 | I34: 0 | J34: 0 | K34: 0 | L34: 0 | M34: 0 | N34: 0 | O34: 0 | P34: 0 | Q34: 0 | R34: 0 | S34: 0 | T34: 0 | U34: 0 | V34: 0 | W34: 0 | X34: 100 | Y34: 0 | Z34: 0 | AA34: 0 | AB34: 0 | AC34: 0 | AD34: 0 | AE34: 0 | AF34: 1 | AG34: 0 | AH34: 0 | AI34: 0 | AJ34: 0 | AK34: 1 | AL34: 0 | AM34: 0 | AN34: 0 | AO34: 0 | AP34: 0 | AQ34: 0
A35: Total | B35: =SUM(B5:B34) -> 3557 | C35: NA | D35: 130 | E35: 0 | F35: 0 | G35: 4 | H35: 5 | I35: 2 | J35: 1 | K35: 2 | L35: 0 | M35: 165 | N35: 35 | O35: 15 | P35: 0 | Q35: 0 | R35: 0 | S35: 0 | T35: 0 | U35: 0 | V35: 0 | W35: 0 | X35: 300 | Y35: 0 | Z35: 0 | AA35: 4 | AB35: 3 | AC35: 5 | AD35: 4 | AE35: 4 | AF35: 4 | AG35: 600 | AH35: 50 | AI35: 65 | AJ35: 35 | AK35: 1 | AL35: 0 | AM35: 0 | AN35: 0 | AO35: 0 | AP35: 0 | AQ35: 0

Sheet SP_lb
A1: Season Pass Challenge
A2: Config Panel
A3: Leaderboard Size | B3: 50
A5: Goals and Rewards
A6: Rank | B6: Coins | C6: SPT | D6: SPT x2 | E6: Red | F6: Chuck | G6: Bomb | H6: Slingshot | I6: Shuffle | J6: Comet | K6: Unlimited Lives | L6: Unlimited Red | M6: Unlimited Chuck | N6: Unlimited Bomb | O6: COOP Token | P6: Avatar | Q6: 1-star Dly | R6: 2-star Dly | S6: 3-star Dly | T6: 4-star Dly | U6: 5-star Dly | V6: 6-star Dly
A7: Rank 1 | B7: 500 | C7: 0 | D7: 0 | E7: 0 | F7: 0 | G7: 1 | H7: 0 | I7: 0 | J7: 0 | K7: 0 | L7: 0 | M7: 0 | N7: 0 | O7: 0 | P7: 1 | Q7: 0 | R7: 0 | S7: 0 | T7: 0 | U7: 0 | V7: 0
A8: Rank 2 | B8: 300 | C8: 0 | D8: 0 | E8: 0 | F8: 0 | G8: 0 | H8: 0 | I8: 1 | J8: 0 | K8: 0 | L8: 0 | M8: 0 | N8: 0 | O8: 0 | P8: 0 | Q8: 0 | R8: 0 | S8: 0 | T8: 0 | U8: 0 | V8: 0
A9: Rank 3 | B9: 200 | C9: 0 | D9: 0 | E9: 0 | F9: 0 | G9: 0 | H9: 0 | I9: 1 | J9: 0 | K9: 0 | L9: 0 | M9: 0 | N9: 0 | O9: 0 | P9: 0 | Q9: 0 | R9: 0 | S9: 0 | T9: 0 | U9: 0 | V9: 0
A10: Rank 4 | B10: 175 | C10: 0 | D10: 0 | E10: 0 | F10: 0 | G10: 0 | H10: 0 | I10: 1 | J10: 0 | K10: 0 | L10: 0 | M10: 0 | N10: 0 | O10: 0 | P10: 0 | Q10: 0 | R10: 0 | S10: 0 | T10: 0 | U10: 0 | V10: 0
A11: Rank 5 | B11: 150 | C11: 0 | D11: 0 | E11: 0 | F11: 0 | G11: 0 | H11: 0 | I11: 1 | J11: 0 | K11: 0 | L11: 0 | M11: 0 | N11: 0 | O11: 0 | P11: 0 | Q11: 0 | R11: 0 | S11: 0 | T11: 0 | U11: 0 | V11: 0
A12: Rank 6 | B12: 125 | C12: 0 | D12: 0 | E12: 0 | F12: 0 | G12: 0 | H12: 0 | I12: 1 | J12: 0 | K12: 0 | L12: 0 | M12: 0 | N12: 0 | O12: 0 | P12: 0 | Q12: 0 | R12: 0 | S12: 0 | T12: 0 | U12: 0 | V12: 0
A13: Rank 7 | B13: 100 | C13: 0 | D13: 0 | E13: 0 | F13: 0 | G13: 0 | H13: 0 | I13: 1 | J13: 0 | K13: 0 | L13: 0 | M13: 0 | N13: 0 | O13: 0 | P13: 0 | Q13: 0 | R13: 0 | S13: 0 | T13: 0 | U13: 0 | V13: 0
A14: Rank 8 | B14: 75 | C14: 0 | D14: 0 | E14: 0 | F14: 0 | G14: 0 | H14: 0 | I14: 1 | J14: 0 | K14: 0 | L14: 0 | M14: 0 | N14: 0 | O14: 0 | P14: 0 | Q14: 0 | R14: 0 | S14: 0 | T14: 0 | U14: 0 | V14: 0
A15: Rank 9 | B15: 50 | C15: 0 | D15: 0 | E15: 0 | F15: 0 | G15: 0 | H15: 0 | I15: 1 | J15: 0 | K15: 0 | L15: 0 | M15: 0 | N15: 0 | O15: 0 | P15: 0 | Q15: 0 | R15: 0 | S15: 0 | T15: 0 | U15: 0 | V15: 0
A16: Rank 10 | B16: 25 | C16: 0 | D16: 0 | E16: 0 | F16: 0 | G16: 0 | H16: 0 | I16: 1 | J16: 0 | K16: 0 | L16: 0 | M16: 0 | N16: 0 | O16: 0 | P16: 0 | Q16: 0 | R16: 0 | S16: 0 | T16: 0 | U16: 0 | V16: 0
A17: Rank 11 | B17: 0 | C17: 0 | D17: 0 | E17: 0 | F17: 0 | G17: 0 | H17: 0 | I17: 0 | J17: 0 | K17: 0 | L17: 0 | M17: 0 | N17: 0 | O17: 0 | P17: 0 | Q17: 0 | R17: 0 | S17: 0 | T17: 0 | U17: 0 | V17: 0
A18: Rank 12 | B18: 0 | C18: 0 | D18: 0 | E18: 0 | F18: 0 | G18: 0 | H18: 1 | I18: 0 | J18: 0 | K18: 0 | L18: 0 | M18: 0 | N18: 0 | O18: 0 | P18: 0 | Q18: 0 | R18: 0 | S18: 0 | T18: 0 | U18: 0 | V18: 0
... A21: Rank 15 | B21: 0 | C21: 0 | D21: 0 | E21: 0 | F21: 0 | G21: 0 | H21: 1 | I21: 0 | J21: 0 | K21: 0 | L21: 0 | M21: 0 | N21: 0 | O21: 0 | P21: 0 | Q21: 0 | R21: 0 | S21: 0 | T21: 0 | U21: 0 | V21: 0

Sheet RR
A1: River Rush
A2: Config Panel
A3: numberOfRounds | B3: 15
A4: groupSize | B4: 5
A5: cycleRounds | B5: =TRUE() -> TRUE
A6: loopbackPoint | B6: 10
A7: firstPeakLastRound | B7: 4
A8: Total levels | B8: =SUMIFS($C$14:$C$88,$B$14:$B$88,"1st") -> 185
A9: Levels during loop | B9: =SUMIFS($C$14:$C$88,$B$14:$B$88,"1st",$A$14:$A$88,">="&$B$6) -> 87
A10: Levels until 1st peak | B10: =SUMIFS($C$14:$C$88,$B$14:$B$88,"1st",$A$14:$A$88,"<="&$B$7) -> 36
A12: Goals and Rewards
A13: Round | B13: Place | C13: Level Req | D13: Level Req Cum | E13: Coins | F13: SPT | G13: SPT x2 | H13: Red | I13: Chuck | J13: Bomb | K13: Slingshot | L13: Shuffle | M13: Comet | N13: Unlimited Lives | O13: Unlimited Red | P13: Unlimited Chuck | Q13: Unlimited Bomb | R13: Avatar | S13: 1-star Dly | T13: 2-star Dly | U13: 3-star Dly | V13: 4-star Dly | W13: 5-star Dly | X13: 6-star Dly
A14: 1 | B14: 1st | C14: 5 | D14: 5 | E14: 30 | F14: 0 | G14: 0 | H14: 0 | I14: 0 | J14: 0 | K14: 0 | L14: 0 | M14: 0 | N14: 0 | O14: 0 | P14: 0 | Q14: 0 | R14: 0 | S14: 0 | T14: 0 | U14: 0 | V14: 0 | W14: 0 | X14: 0
A15: 1 | B15: 2nd | C15: 5 | D15: 5 | E15: 0 | F15: 0 | G15: 0 | H15: 0 | I15: 0 | J15: 0 | K15: 0 | L15: 0 | M15: 0 | N15: 15 | O15: 0 | P15: 0 | Q15: 0 | R15: 0 | S15: 0 | T15: 0 | U15: 0 | V15: 0 | W15: 0 | X15: 0
A16: 1 | B16: 3rd | C16: 5 | D16: 5 | E16: 0 | F16: 0 | G16: 0 | H16: 0 | I16: 0 | J16: 1 | K16: 0 | L16: 0 | M16: 0 | N16: 0 | O16: 0 | P16: 0 | Q16: 0 | R16: 0 | S16: 0 | T16: 0 | U16: 0 | V16: 0 | W16: 0 | X16: 0
A17: 1 | B17: 4th | C17: 5 | D17: 5 | E17: 0 | F17: 0 | G17: 0 | H17: 0 | I17: 0 | J17: 0 | K17: 0 | L17: 1 | M17: 0 | N17: 0 | O17: 0 | P17: 0 | Q17: 0 | R17: 0 | S17: 0 | T17: 0 | U17: 0 | V17: 0 | W17: 0 | X17: 0
A18: 1 | B18: 5th | C18: 5 | D18: 5 | E18: 0 | F18: 0 | G18: 0 | H18: 0 | I18: 0 | J18: 0 | K18: 0 | L18: 0 | M18: 0 | N18: 0 | O18: 0 | P18: 10 | Q18: 0 | R18: 0 | S18: 0 | T18: 0 | U18: 0 | V18: 0 | W18: 0 | X18: 0
A19: 2 | B19: 1st | C19: 6 | D19: 11 | E19: 0 | F19: 0 | G19: 0 | H19: 0 | I19: 0 | J19: 0 | K19: 0 | L19: 0 | M19: 0 | N19: 15 | O19: 0 | P19: 0 | Q19: 0 | R19: 0 | S19: 0 | T19: 0 | U19: 0 | V19: 0 | W19: 0 | X19: 0
A20: 2 | B20: 2nd | C20: 6 | D20: 11 | E20: 0 | F20: 0 | G20: 0 | H20: 0 | I20: 0 | J20: 0 | K20: 0 | L20: 0 | M20: 1 | N20: 0 | O20: 0 | P20: 0 | Q20: 0 | R20: 0 | S20: 0 | T20: 0 | U20: 0 | V20: 0 | W20: 0 | X20: 0
A21: 2 | B21: 3rd | C21: 6 | D21: 11 | E21: 0 | F21: 0 | G21: 0 | H21: 0 | I21: 1 | J21: 0 | K21: 0 | L21: 0 | M21: 0 | N21: 0 | O21: 0 | P21: 0 | Q21: 0 | R21: 0 | S21: 0 | T21: 0 | U21: 0 | V21: 0 | W21: 0 | X21: 0
A22: 2 | B22: 4th | C22: 6 | D22: 11 | E22: 0 | F22: 0 | G22: 0 | H22: 0 | I22: 0 | J22: 0 | K22: 0 | L22: 0 | M22: 0 | N22: 0 | O22: 10 | P22: 0 | Q22: 0 | R22: 0 | S22: 0 | T22: 0 | U22: 0 | V22: 0 | W22: 0 | X22: 0
A23: 2 | B23: 5th | C23: 6 | D23: 11 | E23: 0 | F23: 0 | G23: 10 | H23: 0 | I23: 0 | J23: 0 | K23: 0 | L23: 0 | M23: 0 | N23: 0 | O23: 0 | P23: 0 | Q23: 0 | R23: 0 | S23: 0 | T23: 0 | U23: 0 | V23: 0 | W23: 0 | X23: 0
A24: 3 | B24: 1st | C24: 10 | D24: 21 | E24: 0 | F24: 0 | G24: 0 | H24: 0 | I24: 0 | J24: 0 | K24: 0 | L24: 0 | M24: 0 | N24: 0 | O24: 0 | P24: 0 | Q24: 20 | R24: 0 | S24: 0 | T24: 0 | U24: 0 | V24: 0 | W24: 0 | X24: 0
A25: 3 | B25: 2nd | C25: 10 | D25: 21 | E25: 0 | F25: 0 | G25: 0 | H25: 0 | I25: 0 | J25: 0 | K25: 0 | L25: 1 | M25: 0 | N25: 0 | O25: 0 | P25: 0 | Q25: 0 | R25: 0 | S25: 0 | T25: 0 | U25: 0 | V25: 0 | W25: 0 | X25: 0
... A88: 15 | B88: 5th | C88: 25 | D88: 185 | E88: 0 | F88: 0 | G88: 30 | H88: 0 | I88: 0 | J88: 0 | K88: 0 | L88: 0 | M88: 0 | N88: 0 | O88: 0 | P88: 0 | Q88: 0 | R88: 0 | S88: 0 | T88: 0 | U88: 0 | V88: 0 | W88: 0 | X88: 0

Sheet RR_v2
A1: River Rush
A2: Config Panel
A3: numberOfRounds | B3: 15
A4: groupSize | B4: 5
A5: cycleRounds | B5: =TRUE() -> TRUE
A6: loopbackPoint | B6: 10
A7: firstPeakLastRound | B7: 4
A8: Total levels | B8: =SUMIFS($C$14:$C$88,$B$14:$B$88,"1st") -> 185
A9: Levels during loop | B9: =SUMIFS($C$14:$C$88,$B$14:$B$88,"1st",$A$14:$A$88,">="&$B$6) -> 87
A10: Levels until 1st peak | B10: =SUMIFS($C$14:$C$88,$B$14:$B$88,"1st",$A$14:$A$88,"<="&$B$7) -> 36
A12: Goals and Rewards
A13: Round | B13: Place | C13: Level Req | D13: Level Req Cum | E13: Coins | F13: SPT | G13: SPT x2 | H13: Red | I13: Chuck | J13: Bomb | K13: Slingshot | L13: Shuffle | M13: Comet | N13: Unlimited Lives | O13: Unlimited Red | P13: Unlimited Chuck | Q13: Unlimited Bomb | R13: Avatar | S13: 1-star Dly | T13: 2-star Dly | U13: 3-star Dly | V13: 4-star Dly | W13: 5-star Dly | X13: 6-star Dly
A14: 1 | B14: 1st | C14: 5 | D14: 5 | E14: 30 | F14: 0 | G14: 0 | H14: 0 | I14: 0 | J14: 0 | K14: 0 | L14: 0 | M14: 0 | N14: 0 | O14: 0 | P14: 0 | Q14: 0 | R14: 0 | S14: 0 | T14: 0 | U14: 0 | V14: 0 | W14: 0 | X14: 0
A15: 1 | B15: 2nd | C15: 5 | D15: 5 | E15: 0 | F15: 0 | G15: 0 | H15: 0 | I15: 0 | J15: 0 | K15: 0 | L15: 0 | M15: 0 | N15: 15 | O15: 0 | P15: 0 | Q15: 0 | R15: 0 | S15: 0 | T15: 0 | U15: 0 | V15: 0 | W15: 0 | X15: 0
A16: 1 | B16: 3rd | C16: 5 | D16: 5 | E16: 0 | F16: 0 | G16: 0 | H16: 0 | I16: 0 | J16: 1 | K16: 0 | L16: 0 | M16: 0 | N16: 0 | O16: 0 | P16: 0 | Q16: 0 | R16: 0 | S16: 0 | T16: 0 | U16: 0 | V16: 0 | W16: 0 | X16: 0
A17: 1 | B17: 4th | C17: 5 | D17: 5 | E17: 0 | F17: 0 | G17: 0 | H17: 0 | I17: 0 | J17: 0 | K17: 0 | L17: 1 | M17: 0 | N17: 0 | O17: 0 | P17: 0 | Q17: 0 | R17: 0 | S17: 0 | T17: 0 | U17: 0 | V17: 0 | W17: 0 | X17: 0
A18: 1 | B18: 5th | C18: 5 | D18: 5 | E18: 0 | F18: 0 | G18: 0 | H18: 0 | I18: 0 | J18: 0 | K18: 0 | L18: 0 | M18: 0 | N18: 0 | O18: 0 | P18: 10 | Q18: 0 | R18: 0 | S18: 0 | T18: 0 | U18: 0 | V18: 0 | W18: 0 | X18: 0
A19: 2 | B19: 1st | C19: 6 | D19: 11 | E19: 0 | F19: 0 | G19: 0 | H19: 0 | I19: 0 | J19: 0 | K19: 0 | L19: 0 | M19: 0 | N19: 15 | O19: 0 | P19: 0 | Q19: 0 | R19: 0 | S19: 0 | T19: 0 | U19: 0 | V19: 0 | W19: 0 | X19: 0
A20: 2 | B20: 2nd | C20: 6 | D20: 11 | E20: 0 | F20: 0 | G20: 0 | H20: 0 | I20: 0 | J20: 0 | K20: 0 | L20: 0 | M20: 1 | N20: 0 | O20: 0 | P20: 0 | Q20: 0 | R20: 0 | S20: 0 | T20: 0 | U20: 0 | V20: 0 | W20: 0 | X20: 0
A21: 2 | B21: 3rd | C21: 6 | D21: 11 | E21: 0 | F21: 0 | G21: 0 | H21: 0 | I21: 1 | J21: 0 | K21: 0 | L21: 0 | M21: 0 | N21: 0 | O21: 0 | P21: 0 | Q21: 0 | R21: 0 | S21: 0 | T21: 0 | U21: 0 | V21: 0 | W21: 0 | X21: 0
A22: 2 | B22: 4th | C22: 6 | D22: 11 | E22: 0 | F22: 0 | G22: 0 | H22: 0 | I22: 0 | J22: 0 | K22: 0 | L22: 0 | M22: 0 | N22: 0 | O22: 10 | P22: 0 | Q22: 0 | R22: 0 | S22: 0 | T22: 0 | U22: 0 | V22: 0 | W22: 0 | X22: 0
A23: 2 | B23: 5th | C23: 6 | D23: 11 | E23: 0 | F23: 0 | G23: 10 | H23: 0 | I23: 0 | J23: 0 | K23: 0 | L23: 0 | M23: 0 | N23: 0 | O23: 0 | P23: 0 | Q23: 0 | R23: 0 | S23: 0 | T23: 0 | U23: 0 | V23: 0 | W23: 0 | X23: 0
A24: 3 | B24: 1st | C24: 10 | D24: 21 | E24: 0 | F24: 0 | G24: 0 | H24: 0 | I24: 0 | J24: 0 | K24: 0 | L24: 0 | M24: 0 | N24: 0 | O24: 0 | P24: 0 | Q24: 20 | R24: 0 | S24: 0 | T24: 0 | U24: 0 | V24: 0 | W24: 0 | X24: 0
A25: 3 | B25: 2nd | C25: 10 | D25: 21 | E25: 0 | F25: 0 | G25: 0 | H25: 0 | I25: 0 | J25: 0 | K25: 0 | L25: 1 | M25: 0 | N25: 0 | O25: 0 | P25: 0 | Q25: 0 | R25: 0 | S25: 0 | T25: 0 | U25: 0 | V25: 0 | W25: 0 | X25: 0
... A88: 15 | B88: 5th | C88: 25 | D88: 185 | E88: 0 | F88: 0 | G88: 30 | H88: 0 | I88: 0 | J88: 0 | K88: 0 | L88: 0 | M88: 0 | N88: 0 | O88: 0 | P88: 0 | Q88: 0 | R88: 0 | S88: 0 | T88: 0 | U88: 0 | V88: 0 | W88: 0 | X88: 0

Sheet J
A1: Jigsaw Puzzle
A2: Config Panel
A3: EventDuration | B3: 4
A4: requiredPlayerLevel | B4: 1
A5: requiredSagaLevel | B5: 15
A6: tokenMultiplier | B6: 2
A7: scoreDoubler | B7: =TRUE() -> TRUE
A9: Goals and Rewards
A10: Milestone | B10: Cumul token req | C10: Coins | D10: SPT | E10: SPT x2 | F10: Red | G10: Chuck | H10: Bomb | I10: Slingshot | J10: Shuffle | K10: Comet | L10: Unlimited Lives | M10: Unlimited Red | N10: Unlimited Chuck | O10: Unlimited Bomb | P10: COOP Token | Q10: Avatar | R10: 1-star Dly | S10: 2-star Dly | T10: 3-star Dly | U10: 4-star Dly | V10: 5-star Dly | W10: 6-star Dly
A11: 1 | B11: 30 | C11: 0 | D11: 0 | E11: 0 | F11: 0 | G11: 1 | H11: 0 | I11: 0 | J11: 0 | K11: 0 | L11: 0 | M11: 0 | N11: 0 | O11: 0 | P11: 0 | Q11: 0 | R11: 0 | S11: 0 | T11: 0 | U11: 0 | V11: 0 | W11: 0
A12: 2 | B12: 80 | C12: 0 | D12: 0 | E12: 0 | F12: 0 | G12: 0 | H12: 0 | I12: 0 | J12: 0 | K12: 0 | L12: 0 | M12: 10 | N12: 0 | O12: 0 | P12: 0 | Q12: 0 | R12: 0 | S12: 0 | T12: 0 | U12: 0 | V12: 0 | W12: 0
A13: 3 | B13: 150 | C13: 0 | D13: 0 | E13: 0 | F13: 0 | G13: 0 | H13: 0 | I13: 0 | J13: 0 | K13: 0 | L13: 0 | M13: 0 | N13: 10 | O13: 0 | P13: 0 | Q13: 0 | R13: 0 | S13: 0 | T13: 0 | U13: 0 | V13: 0 | W13: 0
A14: 4 | B14: 250 | C14: 0 | D14: 0 | E14: 0 | F14: 0 | G14: 0 | H14: 0 | I14: 0 | J14: 0 | K14: 0 | L14: 30 | M14: 0 | N14: 0 | O14: 0 | P14: 0 | Q14: 0 | R14: 0 | S14: 0 | T14: 0 | U14: 0 | V14: 0 | W14: 0
A15: 5 | B15: 370 | C15: 25 | D15: 0 | E15: 0 | F15: 0 | G15: 0 | H15: 0 | I15: 0 | J15: 0 | K15: 0 | L15: 0 | M15: 0 | N15: 0 | O15: 0 | P15: 0 | Q15: 0 | R15: 0 | S15: 0 | T15: 0 | U15: 0 | V15: 0 | W15: 0
A16: 6 | B16: 520 | C16: 0 | D16: 0 | E16: 0 | F16: 1 | G16: 0 | H16: 0 | I16: 0 | J16: 0 | K16: 0 | L16: 0 | M16: 0 | N16: 0 | O16: 10 | P16: 0 | Q16: 0 | R16: 0 | S16: 0 | T16: 0 | U16: 0 | V16: 0 | W16: 0
A17: 7 | B17: 690 | C17: 0 | D17: 0 | E17: 0 | F17: 0 | G17: 0 | H17: 0 | I17: 0 | J17: 0 | K17: 0 | L17: 60 | M17: 0 | N17: 0 | O17: 0 | P17: 0 | Q17: 0 | R17: 0 | S17: 0 | T17: 0 | U17: 0 | V17: 0 | W17: 0
A18: 8 | B18: 890 | C18: 0 | D18: 0 | E18: 0 | F18: 0 | G18: 0 | H18: 0 | I18: 0 | J18: 0 | K18: 0 | L18: 0 | M18: 15 | N18: 0 | O18: 0 | P18: 0 | Q18: 0 | R18: 0 | S18: 0 | T18: 0 | U18: 0 | V18: 0 | W18: 0
A19: 9 | B19: 1110 | C19: 25 | D19: 0 | E19: 0 | F19: 0 | G19: 0 | H19: 0 | I19: 0 | J19: 0 | K19: 0 | L19: 0 | M19: 0 | N19: 0 | O19: 0 | P19: 0 | Q19: 0 | R19: 0 | S19: 0 | T19: 0 | U19: 0 | V19: 0 | W19: 0
A20: 10 | B20: 1360 | C20: 0 | D20: 0 | E20: 0 | F20: 0 | G20: 0 | H20: 0 | I20: 0 | J20: 0 | K20: 0 | L20: 0 | M20: 0 | N20: 15 | O20: 0 | P20: 0 | Q20: 0 | R20: 0 | S20: 0 | T20: 0 | U20: 0 | V20: 0 | W20: 0
A21: 11 | B21: 1630 | C21: 0 | D21: 0 | E21: 0 | F21: 0 | G21: 0 | H21: 0 | I21: 1 | J21: 0 | K21: 0 | L21: 0 | M21: 0 | N21: 0 | O21: 0 | P21: 0 | Q21: 0 | R21: 0 | S21: 0 | T21: 0 | U21: 0 | V21: 0 | W21: 0
A22: 12 | B22: 1930 | C22: 0 | D22: 0 | E22: 0 | F22: 0 | G22: 0 | H22: 0 | I22: 0 | J22: 0 | K22: 0 | L22: 60 | M22: 0 | N22: 0 | O22: 15 | P22: 0 | Q22: 0 | R22: 0 | S22: 0 | T22: 0 | U22: 0 | V22: 0 | W22: 0

Sheet J_v2
A1: Jigsaw Puzzle | AH1: Player Reach Simulation (per event day) - SIMULATED
A2: Config Panel | AH2: Percentile | AI2: p50
A3: EventDuration | B3: 3 | AH3: Payer | AI3: NONPAYER
A4: requiredPlayerLevel | B4: 1
A5: requiredSagaLevel | B5: 15 | AH5: Day_of_event | AI5: 0-9_ms | AJ5: 0-9_reward | AK5: 10-19_ms | AL5: 10-19_reward | AM5: 20-39_ms | AN5: 20-39_reward | AO5: 40-99_ms | AP5: 40-99_reward | AQ5: 100_ms | AR5: 100_reward
A6: tokenMultiplier | B6: 2 | AH6: =IF(1<=$B$3,1,"") -> 1 | AI6: {=IF($AH6="","",LET(bal,SUMIFS(data_event_inst!$N:$N,data_event_inst!$A:$A,"Jigsaw",data_event_inst!$B:$B,$AI$3,data_event_inst!$C:$C,"0-9"),shr,MIN(1,IFERROR(CHOOSE(MATCH($AI$2,{"Avg","p25","p50","p75"},0),AVERAGEIFS(data_event_accrual!$I:$I,data_event_accrual!$A:$A,"Jigsaw",data_event_accrual!$B:$B,$AI$3,data_event_accrual!$C:$C,"0-9",data_event_accrual!$E:$E,$AH6),AVERAGEIFS(data_event_accrual!$K:$K,data_event_accrual!$A:$A,"Jigsaw",data_event_accrual!$B:$B,$AI$3,data_event_accrual!$C:$C,"0-9",data_event_accrual!$E:$E,$AH6),AVERAGEIFS(data_event_accrual!$J:$J,data_event_accrual!$A:$A,"Jigsaw",data_event_accrual!$B:$B,$AI$3,data_event_accrual!$C:$C,"0-9",data_event_accrual!$E:$E,$AH6),AVERAGEIFS(data_event_accrual!$L:$L,data_event_accrual!$A:$A,"Jigsaw",data_event_accrual!$B:$B,$AI$3,data_event_accrual!$C:$C,"0-9",data_event_accrual!$E:$E,$AH6)),1)),COUNTIF($B$11:$B$22,"<="&bal*shr)))} -> 0 | AJ6: {=IF($AH6="","",IF(AI6=0,"{}",LET(m,AI6,s,MMULT(SEQUENCE(1,m,1,0),$C$11:$W$22),"{"&TEXTJOIN(", ",TRUE,IF(s>0,$C$10:$W$10&": "&ROUND(s,2),""))&"}")))} -> {} | AK6: {=IF($AH6="","",LET(bal,SUMIFS(data_event_inst!$N:$N,data_event_inst!$A:$A,"Jigsaw",data_event_inst!$B:$B,$AI$3,data_event_inst!$C:$C,"10-19"),shr,MIN(1,IFERROR(CHOOSE(MATCH($AI$2,{"Avg","p25","p50","p75"},0),AVERAGEIFS(data_event_accrual!$I:$I,data_event_accrual!$A:$A,"Jigsaw",data_event_accrual!$B:$B,$AI$3,data_event_accrual!$C:$C,"10-19",data_event_accrual!$E:$E,$AH6),AVERAGEIFS(data_event_accrual!$K:$K,data_event_accrual!$A:$A,"Jigsaw",data_event_accrual!$B:$B,$AI$3,data_event_accrual!$C:$C,"10-19",data_event_accrual!$E:$E,$AH6),AVERAGEIFS(data_event_accrual!$J:$J,data_event_accrual!$A:$A,"Jigsaw",data_event_accrual!$B:$B,$AI$3,data_event_accrual!$C:$C,"10-19",data_event_accrual!$E:$E,$AH6),AVERAGEIFS(data_event_accrual!$L:$L,data_event_accrual!$A:$A,"Jigsaw",data_event_accrual!$B:$B,$AI$3,data_event_accrual!$C:$C,"10-19",data_event_accrual!$E:$E,$AH6)),1)),COUNTIF($B$11:$B$22,"<="&bal*shr)))} -> 1 | AL6: {=IF($AH6="","",IF(AK6=0,"{}",LET(m,AK6,s,MMULT(SEQUENCE(1,m,1,0),$C$11:$W$22),"{"&TEXTJOIN(", ",TRUE,IF(s>0,$C$10:$W$10&": "&ROUND(s,2),""))&"}")))} -> {Chuck: 1} | AM6: {=IF($AH6="","",LET(bal,SUMIFS(data_event_inst!$N:$N,data_event_inst!$A:$A,"Jigsaw",data_event_inst!$B:$B,$AI$3,data_event_inst!$C:$C,"20-39"),shr,MIN(1,IFERROR(CHOOSE(MATCH($AI$2,{"Avg","p25","p50","p75"},0),AVERAGEIFS(data_event_accrual!$I:$I,data_event_accrual!$A:$A,"Jigsaw",data_event_accrual!$B:$B,$AI$3,data_event_accrual!$C:$C,"20-39",data_event_accrual!$E:$E,$AH6),AVERAGEIFS(data_event_accrual!$K:$K,data_event_accrual!$A:$A,"Jigsaw",data_event_accrual!$B:$B,$AI$3,data_event_accrual!$C:$C,"20-39",data_event_accrual!$E:$E,$AH6),AVERAGEIFS(data_event_accrual!$J:$J,data_event_accrual!$A:$A,"Jigsaw",data_event_accrual!$B:$B,$AI$3,data_event_accrual!$C:$C,"20-39",data_event_accrual!$E:$E,$AH6),AVERAGEIFS(data_event_accrual!$L:$L,data_event_accrual!$A:$A,"Jigsaw",data_event_accrual!$B:$B,$AI$3,data_event_accrual!$C:$C,"20-39",data_event_accrual!$E:$E,$AH6)),1)),COUNTIF($B$11:$B$22,"<="&bal*shr)))} -> 2 | AN6: {=IF($AH6="","",IF(AM6=0,"{}",LET(m,AM6,s,MMULT(SEQUENCE(1,m,1,0),$C$11:$W$22),"{"&TEXTJOIN(", ",TRUE,IF(s>0,$C$10:$W$10&": "&ROUND(s,2),""))&"}")))} -> {Chuck: 1, Unlimited Red: 10} | AO6: {=IF($AH6="","",LET(bal,SUMIFS(data_event_inst!$N:$N,data_event_inst!$A:$A,"Jigsaw",data_event_inst!$B:$B,$AI$3,data_event_inst!$C:$C,"40-99"),shr,MIN(1,IFERROR(CHOOSE(MATCH($AI$2,{"Avg","p25","p50","p75"},0),AVERAGEIFS(data_event_accrual!$I:$I,data_event_accrual!$A:$A,"Jigsaw",data_event_accrual!$B:$B,$AI$3,data_event_accrual!$C:$C,"40-99",data_event_accrual!$E:$E,$AH6),AVERAGEIFS(data_event_accrual!$K:$K,data_event_accrual!$A:$A,"Jigsaw",data_event_accrual!$B:$B,$AI$3,data_event_accrual!$C:$C,"40-99",data_event_accrual!$E:$E,$AH6),AVERAGEIFS(data_event_accrual!$J:$J,data_event_accrual!$A:$A,"Jigsaw",data_event_accrual!$B:$B,$AI$3,data_event_accrual!$C:$C,"40-99",data_event_accrual!$E:$E,$AH6),AVERAGEIFS(data_event_accrual!$L:$L,data_event_accrual!$A:$A,"Jigsaw",data_event_accrual!$B:$B,$AI$3,data_event_accrual!$C:$C,"40-99",data_event_accrual!$E:$E,$AH6)),1)),COUNTIF($B$11:$B$22,"<="&bal*shr)))} -> 4 | AP6: {=IF($AH6="","",IF(AO6=0,"{}",LET(m,AO6,s,MMULT(SEQUENCE(1,m,1,0),$C$11:$W$22),"{"&TEXTJOIN(", ",TRUE,IF(s>0,$C$10:$W$10&": "&ROUND(s,2),""))&"}")))} -> {Chuck: 1, Unlimited Lives: 30, Unlimited Red: 10, Unlimited Chuck: 10} | AQ6: {=IF($AH6="","",LET(bal,SUMIFS(data_event_inst!$N:$N,data_event_inst!$A:$A,"Jigsaw",data_event_inst!$B:$B,$AI$3,data_event_inst!$C:$C,"100+"),shr,MIN(1,IFERROR(CHOOSE(MATCH($AI$2,{"Avg","p25","p50","p75"},0),AVERAGEIFS(data_event_accrual!$I:$I,data_event_accrual!$A:$A,"Jigsaw",data_event_accrual!$B:$B,$AI$3,data_event_accrual!$C:$C,"100+",data_event_accrual!$E:$E,$AH6),AVERAGEIFS(data_event_accrual!$K:$K,data_event_accrual!$A:$A,"Jigsaw",data_event_accrual!$B:$B,$AI$3,data_event_accrual!$C:$C,"100+",data_event_accrual!$E:$E,$AH6),AVERAGEIFS(data_event_accrual!$J:$J,data_event_accrual!$A:$A,"Jigsaw",data_event_accrual!$B:$B,$AI$3,data_event_accrual!$C:$C,"100+",data_event_accrual!$E:$E,$AH6),AVERAGEIFS(data_event_accrual!$L:$L,data_event_accrual!$A:$A,"Jigsaw",data_event_accrual!$B:$B,$AI$3,data_event_accrual!$C:$C,"100+",data_event_accrual!$E:$E,$AH6)),1)),COUNTIF($B$11:$B$22,"<="&bal*shr)))} -> 6 | AR6: {=IF($AH6="","",IF(AQ6=0,"{}",LET(m,AQ6,s,MMULT(SEQUENCE(1,m,1,0),$C$11:$W$22),"{"&TEXTJOIN(", ",TRUE,IF(s>0,$C$10:$W$10&": "&ROUND(s,2),""))&"}")))} -> {Coins: 25, Red: 1, Chuck: 1, Unlimited Lives: 30, Unlimited Red: 10, Unlimited Chuck: 10, Unlimited Bomb: 10}
A7: scoreDoubler | B7: =TRUE() -> TRUE | AH7: =IF(2<=$B$3,2,"") -> 2 | AI7: {=IF($AH7="","",LET(bal,SUMIFS(data_event_inst!$N:$N,data_event_inst!$A:$A,"Jigsaw",data_event_inst!$B:$B,$AI$3,data_event_inst!$C:$C,"0-9"),shr,MIN(1,IFERROR(CHOOSE(MATCH($AI$2,{"Avg","p25","p50","p75"},0),AVERAGEIFS(data_event_accrual!$I:$I,data_event_accrual!$A:$A,"Jigsaw",data_event_accrual!$B:$B,$AI$3,data_event_accrual!$C:$C,"0-9",data_event_accrual!$E:$E,$AH7),AVERAGEIFS(data_event_accrual!$K:$K,data_event_accrual!$A:$A,"Jigsaw",data_event_accrual!$B:$B,$AI$3,data_event_accrual!$C:$C,"0-9",data_event_accrual!$E:$E,$AH7),AVERAGEIFS(data_event_accrual!$J:$J,data_event_accrual!$A:$A,"Jigsaw",data_event_accrual!$B:$B,$AI$3,data_event_accrual!$C:$C,"0-9",data_event_accrual!$E:$E,$AH7),AVERAGEIFS(data_event_accrual!$L:$L,data_event_accrual!$A:$A,"Jigsaw",data_event_accrual!$B:$B,$AI$3,data_event_accrual!$C:$C,"0-9",data_event_accrual!$E:$E,$AH7)),1)),COUNTIF($B$11:$B$22,"<="&bal*shr)))} -> 1 | AJ7: {=IF($AH7="","",IF(AI7=0,"{}",LET(m,AI7,s,MMULT(SEQUENCE(1,m,1,0),$C$11:$W$22),"{"&TEXTJOIN(", ",TRUE,IF(s>0,$C$10:$W$10&": "&ROUND(s,2),""))&"}")))} -> {Chuck: 1} | AK7: {=IF($AH7="","",LET(bal,SUMIFS(data_event_inst!$N:$N,data_event_inst!$A:$A,"Jigsaw",data_event_inst!$B:$B,$AI$3,data_event_inst!$C:$C,"10-19"),shr,MIN(1,IFERROR(CHOOSE(MATCH($AI$2,{"Avg","p25","p50","p75"},0),AVERAGEIFS(data_event_accrual!$I:$I,data_event_accrual!$A:$A,"Jigsaw",data_event_accrual!$B:$B,$AI$3,data_event_accrual!$C:$C,"10-19",data_event_accrual!$E:$E,$AH7),AVERAGEIFS(data_event_accrual!$K:$K,data_event_accrual!$A:$A,"Jigsaw",data_event_accrual!$B:$B,$AI$3,data_event_accrual!$C:$C,"10-19",data_event_accrual!$E:$E,$AH7),AVERAGEIFS(data_event_accrual!$J:$J,data_event_accrual!$A:$A,"Jigsaw",data_event_accrual!$B:$B,$AI$3,data_event_accrual!$C:$C,"10-19",data_event_accrual!$E:$E,$AH7),AVERAGEIFS(data_event_accrual!$L:$L,data_event_accrual!$A:$A,"Jigsaw",data_event_accrual!$B:$B,$AI$3,data_event_accrual!$C:$C,"10-19",data_event_accrual!$E:$E,$AH7)),1)),COUNTIF($B$11:$B$22,"<="&bal*shr)))} -> 3 | AL7: {=IF($AH7="","",IF(AK7=0,"{}",LET(m,AK7,s,MMULT(SEQUENCE(1,m,1,0),$C$11:$W$22),"{"&TEXTJOIN(", ",TRUE,IF(s>0,$C$10:$W$10&": "&ROUND(s,2),""))&"}")))} -> {Chuck: 1, Unlimited Red: 10, Unlimited Chuck: 10} | AM7: {=IF($AH7="","",LET(bal,SUMIFS(data_event_inst!$N:$N,data_event_inst!$A:$A,"Jigsaw",data_event_inst!$B:$B,$AI$3,data_event_inst!$C:$C,"20-39"),shr,MIN(1,IFERROR(CHOOSE(MATCH($AI$2,{"Avg","p25","p50","p75"},0),AVERAGEIFS(data_event_accrual!$I:$I,data_event_accrual!$A:$A,"Jigsaw",data_event_accrual!$B:$B,$AI$3,data_event_accrual!$C:$C,"20-39",data_event_accrual!$E:$E,$AH7),AVERAGEIFS(data_event_accrual!$K:$K,data_event_accrual!$A:$A,"Jigsaw",data_event_accrual!$B:$B,$AI$3,data_event_accrual!$C:$C,"20-39",data_event_accrual!$E:$E,$AH7),AVERAGEIFS(data_event_accrual!$J:$J,data_event_accrual!$A:$A,"Jigsaw",data_event_accrual!$B:$B,$AI$3,data_event_accrual!$C:$C,"20-39",data_event_accrual!$E:$E,$AH7),AVERAGEIFS(data_event_accrual!$L:$L,data_event_accrual!$A:$A,"Jigsaw",data_event_accrual!$B:$B,$AI$3,data_event_accrual!$C:$C,"20-39",data_event_accrual!$E:$E,$AH7)),1)),COUNTIF($B$11:$B$22,"<="&bal*shr)))} -> 5 | AN7: {=IF($AH7="","",IF(AM7=0,"{}",LET(m,AM7,s,MMULT(SEQUENCE(1,m,1,0),$C$11:$W$22),"{"&TEXTJOIN(", ",TRUE,IF(s>0,$C$10:$W$10&": "&ROUND(s,2),""))&"}")))} -> {Coins: 25, Chuck: 1, Unlimited Lives: 30, Unlimited Red: 10, Unlimited Chuck: 10} | AO7: {=IF($AH7="","",LET(bal,SUMIFS(data_event_inst!$N:$N,data_event_inst!$A:$A,"Jigsaw",data_event_inst!$B:$B,$AI$3,data_event_inst!$C:$C,"40-99"),shr,MIN(1,IFERROR(CHOOSE(MATCH($AI$2,{"Avg","p25","p50","p75"},0),AVERAGEIFS(data_event_accrual!$I:$I,data_event_accrual!$A:$A,"Jigsaw",data_event_accrual!$B:$B,$AI$3,data_event_accrual!$C:$C,"40-99",data_event_accrual!$E:$E,$AH7),AVERAGEIFS(data_event_accrual!$K:$K,data_event_accrual!$A:$A,"Jigsaw",data_event_accrual!$B:$B,$AI$3,data_event_accrual!$C:$C,"40-99",data_event_accrual!$E:$E,$AH7),AVERAGEIFS(data_event_accrual!$J:$J,data_event_accrual!$A:$A,"Jigsaw",data_event_accrual!$B:$B,$AI$3,data_event_accrual!$C:$C,"40-99",data_event_accrual!$E:$E,$AH7),AVERAGEIFS(data_event_accrual!$L:$L,data_event_accrual!$A:$A,"Jigsaw",data_event_accrual!$B:$B,$AI$3,data_event_accrual!$C:$C,"40-99",data_event_accrual!$E:$E,$AH7)),1)),COUNTIF($B$11:$B$22,"<="&bal*shr)))} -> 7 | AP7: {=IF($AH7="","",IF(AO7=0,"{}",LET(m,AO7,s,MMULT(SEQUENCE(1,m,1,0),$C$11:$W$22),"{"&TEXTJOIN(", ",TRUE,IF(s>0,$C$10:$W$10&": "&ROUND(s,2),""))&"}")))} -> {Coins: 25, Red: 1, Chuck: 1, Unlimited Lives: 90, Unlimited Red: 10, Unlimited Chuck: 10, Unlimited Bomb: 10} | AQ7: {=IF($AH7="","",LET(bal,SUMIFS(data_event_inst!$N:$N,data_event_inst!$A:$A,"Jigsaw",data_event_inst!$B:$B,$AI$3,data_event_inst!$C:$C,"100+"),shr,MIN(1,IFERROR(CHOOSE(MATCH($AI$2,{"Avg","p25","p50","p75"},0),AVERAGEIFS(data_event_accrual!$I:$I,data_event_accrual!$A:$A,"Jigsaw",data_event_accrual!$B:$B,$AI$3,data_event_accrual!$C:$C,"100+",data_event_accrual!$E:$E,$AH7),AVERAGEIFS(data_event_accrual!$K:$K,data_event_accrual!$A:$A,"Jigsaw",data_event_accrual!$B:$B,$AI$3,data_event_accrual!$C:$C,"100+",data_event_accrual!$E:$E,$AH7),AVERAGEIFS(data_event_accrual!$J:$J,data_event_accrual!$A:$A,"Jigsaw",data_event_accrual!$B:$B,$AI$3,data_event_accrual!$C:$C,"100+",data_event_accrual!$E:$E,$AH7),AVERAGEIFS(data_event_accrual!$L:$L,data_event_accrual!$A:$A,"Jigsaw",data_event_accrual!$B:$B,$AI$3,data_event_accrual!$C:$C,"100+",data_event_accrual!$E:$E,$AH7)),1)),COUNTIF($B$11:$B$22,"<="&bal*shr)))} -> 10 | AR7: {=IF($AH7="","",IF(AQ7=0,"{}",LET(m,AQ7,s,MMULT(SEQUENCE(1,m,1,0),$C$11:$W$22),"{"&TEXTJOIN(", ",TRUE,IF(s>0,$C$10:$W$10&": "&ROUND(s,2),""))&"}")))} -> {Coins: 50, Red: 1, Chuck: 1, Unlimited Lives: 90, Unlimited Red: 25, Unlimited Chuck: 25, Unlimited Bomb: 10}
AH8: =IF(3<=$B$3,3,"") -> 3 | AI8: {=IF($AH8="","",LET(bal,SUMIFS(data_event_inst!$N:$N,data_event_inst!$A:$A,"Jigsaw",data_event_inst!$B:$B,$AI$3,data_event_inst!$C:$C,"0-9"),shr,MIN(1,IFERROR(CHOOSE(MATCH($AI$2,{"Avg","p25","p50","p75"},0),AVERAGEIFS(data_event_accrual!$I:$I,data_event_accrual!$A:$A,"Jigsaw",data_event_accrual!$B:$B,$AI$3,data_event_accrual!$C:$C,"0-9",data_event_accrual!$E:$E,$AH8),AVERAGEIFS(data_event_accrual!$K:$K,data_event_accrual!$A:$A,"Jigsaw",data_event_accrual!$B:$B,$AI$3,data_event_accrual!$C:$C,"0-9",data_event_accrual!$E:$E,$AH8),AVERAGEIFS(data_event_accrual!$J:$J,data_event_accrual!$A:$A,"Jigsaw",data_event_accrual!$B:$B,$AI$3,data_event_accrual!$C:$C,"0-9",data_event_accrual!$E:$E,$AH8),AVERAGEIFS(data_event_accrual!$L:$L,data_event_accrual!$A:$A,"Jigsaw",data_event_accrual!$B:$B,$AI$3,data_event_accrual!$C:$C,"0-9",data_event_accrual!$E:$E,$AH8)),1)),COUNTIF($B$11:$B$22,"<="&bal*shr)))} -> 2 | AJ8: {=IF($AH8="","",IF(AI8=0,"{}",LET(m,AI8,s,MMULT(SEQUENCE(1,m,1,0),$C$11:$W$22),"{"&TEXTJOIN(", ",TRUE,IF(s>0,$C$10:$W$10&": "&ROUND(s,2),""))&"}")))} -> {Chuck: 1, Unlimited Red: 10} | AK8: {=IF($AH8="","",LET(bal,SUMIFS(data_event_inst!$N:$N,data_event_inst!$A:$A,"Jigsaw",data_event_inst!$B:$B,$AI$3,data_event_inst!$C:$C,"10-19"),shr,MIN(1,IFERROR(CHOOSE(MATCH($AI$2,{"Avg","p25","p50","p75"},0),AVERAGEIFS(data_event_accrual!$I:$I,data_event_accrual!$A:$A,"Jigsaw",data_event_accrual!$B:$B,$AI$3,data_event_accrual!$C:$C,"10-19",data_event_accrual!$E:$E,$AH8),AVERAGEIFS(data_event_accrual!$K:$K,data_event_accrual!$A:$A,"Jigsaw",data_event_accrual!$B:$B,$AI$3,data_event_accrual!$C:$C,"10-19",data_event_accrual!$E:$E,$AH8),AVERAGEIFS(data_event_accrual!$J:$J,data_event_accrual!$A:$A,"Jigsaw",data_event_accrual!$B:$B,$AI$3,data_event_accrual!$C:$C,"10-19",data_event_accrual!$E:$E,$AH8),AVERAGEIFS(data_event_accrual!$L:$L,data_event_accrual!$A:$A,"Jigsaw",data_event_accrual!$B:$B,$AI$3,data_event_accrual!$C:$C,"10-19",data_event_accrual!$E:$E,$AH8)),1)),COUNTIF($B$11:$B$22,"<="&bal*shr)))} -> 4 | AL8: {=IF($AH8="","",IF(AK8=0,"{}",LET(m,AK8,s,MMULT(SEQUENCE(1,m,1,0),$C$11:$W$22),"{"&TEXTJOIN(", ",TRUE,IF(s>0,$C$10:$W$10&": "&ROUND(s,2),""))&"}")))} -> {Chuck: 1, Unlimited Lives: 30, Unlimited Red: 10, Unlimited Chuck: 10} | AM8: {=IF($AH8="","",LET(bal,SUMIFS(data_event_inst!$N:$N,data_event_inst!$A:$A,"Jigsaw",data_event_inst!$B:$B,$AI$3,data_event_inst!$C:$C,"20-39"),shr,MIN(1,IFERROR(CHOOSE(MATCH($AI$2,{"Avg","p25","p50","p75"},0),AVERAGEIFS(data_event_accrual!$I:$I,data_event_accrual!$A:$A,"Jigsaw",data_event_accrual!$B:$B,$AI$3,data_event_accrual!$C:$C,"20-39",data_event_accrual!$E:$E,$AH8),AVERAGEIFS(data_event_accrual!$K:$K,data_event_accrual!$A:$A,"Jigsaw",data_event_accrual!$B:$B,$AI$3,data_event_accrual!$C:$C,"20-39",data_event_accrual!$E:$E,$AH8),AVERAGEIFS(data_event_accrual!$J:$J,data_event_accrual!$A:$A,"Jigsaw",data_event_accrual!$B:$B,$AI$3,data_event_accrual!$C:$C,"20-39",data_event_accrual!$E:$E,$AH8),AVERAGEIFS(data_event_accrual!$L:$L,data_event_accrual!$A:$A,"Jigsaw",data_event_accrual!$B:$B,$AI$3,data_event_accrual!$C:$C,"20-39",data_event_accrual!$E:$E,$AH8)),1)),COUNTIF($B$11:$B$22,"<="&bal*shr)))} -> 6 | AN8: {=IF($AH8="","",IF(AM8=0,"{}",LET(m,AM8,s,MMULT(SEQUENCE(1,m,1,0),$C$11:$W$22),"{"&TEXTJOIN(", ",TRUE,IF(s>0,$C$10:$W$10&": "&ROUND(s,2),""))&"}")))} -> {Coins: 25, Red: 1, Chuck: 1, Unlimited Lives: 30, Unlimited Red: 10, Unlimited Chuck: 10, Unlimited Bomb: 10} | AO8: {=IF($AH8="","",LET(bal,SUMIFS(data_event_inst!$N:$N,data_event_inst!$A:$A,"Jigsaw",data_event_inst!$B:$B,$AI$3,data_event_inst!$C:$C,"40-99"),shr,MIN(1,IFERROR(CHOOSE(MATCH($AI$2,{"Avg","p25","p50","p75"},0),AVERAGEIFS(data_event_accrual!$I:$I,data_event_accrual!$A:$A,"Jigsaw",data_event_accrual!$B:$B,$AI$3,data_event_accrual!$C:$C,"40-99",data_event_accrual!$E:$E,$AH8),AVERAGEIFS(data_event_accrual!$K:$K,data_event_accrual!$A:$A,"Jigsaw",data_event_accrual!$B:$B,$AI$3,data_event_accrual!$C:$C,"40-99",data_event_accrual!$E:$E,$AH8),AVERAGEIFS(data_event_accrual!$J:$J,data_event_accrual!$A:$A,"Jigsaw",data_event_accrual!$B:$B,$AI$3,data_event_accrual!$C:$C,"40-99",data_event_accrual!$E:$E,$AH8),AVERAGEIFS(data_event_accrual!$L:$L,data_event_accrual!$A:$A,"Jigsaw",data_event_accrual!$B:$B,$AI$3,data_event_accrual!$C:$C,"40-99",data_event_accrual!$E:$E,$AH8)),1)),COUNTIF($B$11:$B$22,"<="&bal*shr)))} -> 9 | AP8: {=IF($AH8="","",IF(AO8=0,"{}",LET(m,AO8,s,MMULT(SEQUENCE(1,m,1,0),$C$11:$W$22),"{"&TEXTJOIN(", ",TRUE,IF(s>0,$C$10:$W$10&": "&ROUND(s,2),""))&"}")))} -> {Coins: 50, Red: 1, Chuck: 1, Unlimited Lives: 90, Unlimited Red: 25, Unlimited Chuck: 10, Unlimited Bomb: 10} | AQ8: {=IF($AH8="","",LET(bal,SUMIFS(data_event_inst!$N:$N,data_event_inst!$A:$A,"Jigsaw",data_event_inst!$B:$B,$AI$3,data_event_inst!$C:$C,"100+"),shr,MIN(1,IFERROR(CHOOSE(MATCH($AI$2,{"Avg","p25","p50","p75"},0),AVERAGEIFS(data_event_accrual!$I:$I,data_event_accrual!$A:$A,"Jigsaw",data_event_accrual!$B:$B,$AI$3,data_event_accrual!$C:$C,"100+",data_event_accrual!$E:$E,$AH8),AVERAGEIFS(data_event_accrual!$K:$K,data_event_accrual!$A:$A,"Jigsaw",data_event_accrual!$B:$B,$AI$3,data_event_accrual!$C:$C,"100+",data_event_accrual!$E:$E,$AH8),AVERAGEIFS(data_event_accrual!$J:$J,data_event_accrual!$A:$A,"Jigsaw",data_event_accrual!$B:$B,$AI$3,data_event_accrual!$C:$C,"100+",data_event_accrual!$E:$E,$AH8),AVERAGEIFS(data_event_accrual!$L:$L,data_event_accrual!$A:$A,"Jigsaw",data_event_accrual!$B:$B,$AI$3,data_event_accrual!$C:$C,"100+",data_event_accrual!$E:$E,$AH8)),1)),COUNTIF($B$11:$B$22,"<="&bal*shr)))} -> 11 | AR8: {=IF($AH8="","",IF(AQ8=0,"{}",LET(m,AQ8,s,MMULT(SEQUENCE(1,m,1,0),$C$11:$W$22),"{"&TEXTJOIN(", ",TRUE,IF(s>0,$C$10:$W$10&": "&ROUND(s,2),""))&"}")))} -> {Coins: 50, Red: 1, Chuck: 1, Slingshot: 1, Unlimited Lives: 90, Unlimited Red: 25, Unlimited Chuck: 25, Unlimited Bomb: 10}
A9: Goals and Rewards | AH9: =IF(4<=$B$3,4,"") | AI9: {=IF($AH9="","",LET(bal,SUMIFS(data_event_inst!$N:$N,data_event_inst!$A:$A,"Jigsaw",data_event_inst!$B:$B,$AI$3,data_event_inst!$C:$C,"0-9"),shr,MIN(1,IFERROR(CHOOSE(MATCH($AI$2,{"Avg","p25","p50","p75"},0),AVERAGEIFS(data_event_accrual!$I:$I,data_event_accrual!$A:$A,"Jigsaw",data_event_accrual!$B:$B,$AI$3,data_event_accrual!$C:$C,"0-9",data_event_accrual!$E:$E,$AH9),AVERAGEIFS(data_event_accrual!$K:$K,data_event_accrual!$A:$A,"Jigsaw",data_event_accrual!$B:$B,$AI$3,data_event_accrual!$C:$C,"0-9",data_event_accrual!$E:$E,$AH9),AVERAGEIFS(data_event_accrual!$J:$J,data_event_accrual!$A:$A,"Jigsaw",data_event_accrual!$B:$B,$AI$3,data_event_accrual!$C:$C,"0-9",data_event_accrual!$E:$E,$AH9),AVERAGEIFS(data_event_accrual!$L:$L,data_event_accrual!$A:$A,"Jigsaw",data_event_accrual!$B:$B,$AI$3,data_event_accrual!$C:$C,"0-9",data_event_accrual!$E:$E,$AH9)),1)),COUNTIF($B$11:$B$22,"<="&bal*shr)))} | AJ9: {=IF($AH9="","",IF(AI9=0,"{}",LET(m,AI9,s,MMULT(SEQUENCE(1,m,1,0),$C$11:$W$22),"{"&TEXTJOIN(", ",TRUE,IF(s>0,$C$10:$W$10&": "&ROUND(s,2),""))&"}")))} | AK9: {=IF($AH9="","",LET(bal,SUMIFS(data_event_inst!$N:$N,data_event_inst!$A:$A,"Jigsaw",data_event_inst!$B:$B,$AI$3,data_event_inst!$C:$C,"10-19"),shr,MIN(1,IFERROR(CHOOSE(MATCH($AI$2,{"Avg","p25","p50","p75"},0),AVERAGEIFS(data_event_accrual!$I:$I,data_event_accrual!$A:$A,"Jigsaw",data_event_accrual!$B:$B,$AI$3,data_event_accrual!$C:$C,"10-19",data_event_accrual!$E:$E,$AH9),AVERAGEIFS(data_event_accrual!$K:$K,data_event_accrual!$A:$A,"Jigsaw",data_event_accrual!$B:$B,$AI$3,data_event_accrual!$C:$C,"10-19",data_event_accrual!$E:$E,$AH9),AVERAGEIFS(data_event_accrual!$J:$J,data_event_accrual!$A:$A,"Jigsaw",data_event_accrual!$B:$B,$AI$3,data_event_accrual!$C:$C,"10-19",data_event_accrual!$E:$E,$AH9),AVERAGEIFS(data_event_accrual!$L:$L,data_event_accrual!$A:$A,"Jigsaw",data_event_accrual!$B:$B,$AI$3,data_event_accrual!$C:$C,"10-19",data_event_accrual!$E:$E,$AH9)),1)),COUNTIF($B$11:$B$22,"<="&bal*shr)))} | AL9: {=IF($AH9="","",IF(AK9=0,"{}",LET(m,AK9,s,MMULT(SEQUENCE(1,m,1,0),$C$11:$W$22),"{"&TEXTJOIN(", ",TRUE,IF(s>0,$C$10:$W$10&": "&ROUND(s,2),""))&"}")))} | AM9: {=IF($AH9="","",LET(bal,SUMIFS(data_event_inst!$N:$N,data_event_inst!$A:$A,"Jigsaw",data_event_inst!$B:$B,$AI$3,data_event_inst!$C:$C,"20-39"),shr,MIN(1,IFERROR(CHOOSE(MATCH($AI$2,{"Avg","p25","p50","p75"},0),AVERAGEIFS(data_event_accrual!$I:$I,data_event_accrual!$A:$A,"Jigsaw",data_event_accrual!$B:$B,$AI$3,data_event_accrual!$C:$C,"20-39",data_event_accrual!$E:$E,$AH9),AVERAGEIFS(data_event_accrual!$K:$K,data_event_accrual!$A:$A,"Jigsaw",data_event_accrual!$B:$B,$AI$3,data_event_accrual!$C:$C,"20-39",data_event_accrual!$E:$E,$AH9),AVERAGEIFS(data_event_accrual!$J:$J,data_event_accrual!$A:$A,"Jigsaw",data_event_accrual!$B:$B,$AI$3,data_event_accrual!$C:$C,"20-39",data_event_accrual!$E:$E,$AH9),AVERAGEIFS(data_event_accrual!$L:$L,data_event_accrual!$A:$A,"Jigsaw",data_event_accrual!$B:$B,$AI$3,data_event_accrual!$C:$C,"20-39",data_event_accrual!$E:$E,$AH9)),1)),COUNTIF($B$11:$B$22,"<="&bal*shr)))} | AN9: {=IF($AH9="","",IF(AM9=0,"{}",LET(m,AM9,s,MMULT(SEQUENCE(1,m,1,0),$C$11:$W$22),"{"&TEXTJOIN(", ",TRUE,IF(s>0,$C$10:$W$10&": "&ROUND(s,2),""))&"}")))} | AO9: {=IF($AH9="","",LET(bal,SUMIFS(data_event_inst!$N:$N,data_event_inst!$A:$A,"Jigsaw",data_event_inst!$B:$B,$AI$3,data_event_inst!$C:$C,"40-99"),shr,MIN(1,IFERROR(CHOOSE(MATCH($AI$2,{"Avg","p25","p50","p75"},0),AVERAGEIFS(data_event_accrual!$I:$I,data_event_accrual!$A:$A,"Jigsaw",data_event_accrual!$B:$B,$AI$3,data_event_accrual!$C:$C,"40-99",data_event_accrual!$E:$E,$AH9),AVERAGEIFS(data_event_accrual!$K:$K,data_event_accrual!$A:$A,"Jigsaw",data_event_accrual!$B:$B,$AI$3,data_event_accrual!$C:$C,"40-99",data_event_accrual!$E:$E,$AH9),AVERAGEIFS(data_event_accrual!$J:$J,data_event_accrual!$A:$A,"Jigsaw",data_event_accrual!$B:$B,$AI$3,data_event_accrual!$C:$C,"40-99",data_event_accrual!$E:$E,$AH9),AVERAGEIFS(data_event_accrual!$L:$L,data_event_accrual!$A:$A,"Jigsaw",data_event_accrual!$B:$B,$AI$3,data_event_accrual!$C:$C,"40-99",data_event_accrual!$E:$E,$AH9)),1)),COUNTIF($B$11:$B$22,"<="&bal*shr)))} | AP9: {=IF($AH9="","",IF(AO9=0,"{}",LET(m,AO9,s,MMULT(SEQUENCE(1,m,1,0),$C$11:$W$22),"{"&TEXTJOIN(", ",TRUE,IF(s>0,$C$10:$W$10&": "&ROUND(s,2),""))&"}")))} | AQ9: {=IF($AH9="","",LET(bal,SUMIFS(data_event_inst!$N:$N,data_event_inst!$A:$A,"Jigsaw",data_event_inst!$B:$B,$AI$3,data_event_inst!$C:$C,"100+"),shr,MIN(1,IFERROR(CHOOSE(MATCH($AI$2,{"Avg","p25","p50","p75"},0),AVERAGEIFS(data_event_accrual!$I:$I,data_event_accrual!$A:$A,"Jigsaw",data_event_accrual!$B:$B,$AI$3,data_event_accrual!$C:$C,"100+",data_event_accrual!$E:$E,$AH9),AVERAGEIFS(data_event_accrual!$K:$K,data_event_accrual!$A:$A,"Jigsaw",data_event_accrual!$B:$B,$AI$3,data_event_accrual!$C:$C,"100+",data_event_accrual!$E:$E,$AH9),AVERAGEIFS(data_event_accrual!$J:$J,data_event_accrual!$A:$A,"Jigsaw",data_event_accrual!$B:$B,$AI$3,data_event_accrual!$C:$C,"100+",data_event_accrual!$E:$E,$AH9),AVERAGEIFS(data_event_accrual!$L:$L,data_event_accrual!$A:$A,"Jigsaw",data_event_accrual!$B:$B,$AI$3,data_event_accrual!$C:$C,"100+",data_event_accrual!$E:$E,$AH9)),1)),COUNTIF($B$11:$B$22,"<="&bal*shr)))} | AR9: {=IF($AH9="","",IF(AQ9=0,"{}",LET(m,AQ9,s,MMULT(SEQUENCE(1,m,1,0),$C$11:$W$22),"{"&TEXTJOIN(", ",TRUE,IF(s>0,$C$10:$W$10&": "&ROUND(s,2),""))&"}")))}
A10: Milestone | B10: Cumul token req | C10: Coins | D10: SPT | E10: SPT x2 | F10: Red | G10: Chuck | H10: Bomb | I10: Slingshot | J10: Shuffle | K10: Comet | L10: Unlimited Lives | M10: Unlimited Red | N10: Unlimited Chuck | O10: Unlimited Bomb | P10: COOP Token | Q10: Avatar | R10: 1-star Dly | S10: 2-star Dly | T10: 3-star Dly | U10: 4-star Dly | V10: 5-star Dly | W10: 6-star Dly | AH10: =IF(5<=$B$3,5,"") | AI10: {=IF($AH10="","",LET(bal,SUMIFS(data_event_inst!$N:$N,data_event_inst!$A:$A,"Jigsaw",data_event_inst!$B:$B,$AI$3,data_event_inst!$C:$C,"0-9"),shr,MIN(1,IFERROR(CHOOSE(MATCH($AI$2,{"Avg","p25","p50","p75"},0),AVERAGEIFS(data_event_accrual!$I:$I,data_event_accrual!$A:$A,"Jigsaw",data_event_accrual!$B:$B,$AI$3,data_event_accrual!$C:$C,"0-9",data_event_accrual!$E:$E,$AH10),AVERAGEIFS(data_event_accrual!$K:$K,data_event_accrual!$A:$A,"Jigsaw",data_event_accrual!$B:$B,$AI$3,data_event_accrual!$C:$C,"0-9",data_event_accrual!$E:$E,$AH10),AVERAGEIFS(data_event_accrual!$J:$J,data_event_accrual!$A:$A,"Jigsaw",data_event_accrual!$B:$B,$AI$3,data_event_accrual!$C:$C,"0-9",data_event_accrual!$E:$E,$AH10),AVERAGEIFS(data_event_accrual!$L:$L,data_event_accrual!$A:$A,"Jigsaw",data_event_accrual!$B:$B,$AI$3,data_event_accrual!$C:$C,"0-9",data_event_accrual!$E:$E,$AH10)),1)),COUNTIF($B$11:$B$22,"<="&bal*shr)))} | AJ10: {=IF($AH10="","",IF(AI10=0,"{}",LET(m,AI10,s,MMULT(SEQUENCE(1,m,1,0),$C$11:$W$22),"{"&TEXTJOIN(", ",TRUE,IF(s>0,$C$10:$W$10&": "&ROUND(s,2),""))&"}")))} | AK10: {=IF($AH10="","",LET(bal,SUMIFS(data_event_inst!$N:$N,data_event_inst!$A:$A,"Jigsaw",data_event_inst!$B:$B,$AI$3,data_event_inst!$C:$C,"10-19"),shr,MIN(1,IFERROR(CHOOSE(MATCH($AI$2,{"Avg","p25","p50","p75"},0),AVERAGEIFS(data_event_accrual!$I:$I,data_event_accrual!$A:$A,"Jigsaw",data_event_accrual!$B:$B,$AI$3,data_event_accrual!$C:$C,"10-19",data_event_accrual!$E:$E,$AH10),AVERAGEIFS(data_event_accrual!$K:$K,data_event_accrual!$A:$A,"Jigsaw",data_event_accrual!$B:$B,$AI$3,data_event_accrual!$C:$C,"10-19",data_event_accrual!$E:$E,$AH10),AVERAGEIFS(data_event_accrual!$J:$J,data_event_accrual!$A:$A,"Jigsaw",data_event_accrual!$B:$B,$AI$3,data_event_accrual!$C:$C,"10-19",data_event_accrual!$E:$E,$AH10),AVERAGEIFS(data_event_accrual!$L:$L,data_event_accrual!$A:$A,"Jigsaw",data_event_accrual!$B:$B,$AI$3,data_event_accrual!$C:$C,"10-19",data_event_accrual!$E:$E,$AH10)),1)),COUNTIF($B$11:$B$22,"<="&bal*shr)))} | AL10: {=IF($AH10="","",IF(AK10=0,"{}",LET(m,AK10,s,MMULT(SEQUENCE(1,m,1,0),$C$11:$W$22),"{"&TEXTJOIN(", ",TRUE,IF(s>0,$C$10:$W$10&": "&ROUND(s,2),""))&"}")))} | AM10: {=IF($AH10="","",LET(bal,SUMIFS(data_event_inst!$N:$N,data_event_inst!$A:$A,"Jigsaw",data_event_inst!$B:$B,$AI$3,data_event_inst!$C:$C,"20-39"),shr,MIN(1,IFERROR(CHOOSE(MATCH($AI$2,{"Avg","p25","p50","p75"},0),AVERAGEIFS(data_event_accrual!$I:$I,data_event_accrual!$A:$A,"Jigsaw",data_event_accrual!$B:$B,$AI$3,data_event_accrual!$C:$C,"20-39",data_event_accrual!$E:$E,$AH10),AVERAGEIFS(data_event_accrual!$K:$K,data_event_accrual!$A:$A,"Jigsaw",data_event_accrual!$B:$B,$AI$3,data_event_accrual!$C:$C,"20-39",data_event_accrual!$E:$E,$AH10),AVERAGEIFS(data_event_accrual!$J:$J,data_event_accrual!$A:$A,"Jigsaw",data_event_accrual!$B:$B,$AI$3,data_event_accrual!$C:$C,"20-39",data_event_accrual!$E:$E,$AH10),AVERAGEIFS(data_event_accrual!$L:$L,data_event_accrual!$A:$A,"Jigsaw",data_event_accrual!$B:$B,$AI$3,data_event_accrual!$C:$C,"20-39",data_event_accrual!$E:$E,$AH10)),1)),COUNTIF($B$11:$B$22,"<="&bal*shr)))} | AN10: {=IF($AH10="","",IF(AM10=0,"{}",LET(m,AM10,s,MMULT(SEQUENCE(1,m,1,0),$C$11:$W$22),"{"&TEXTJOIN(", ",TRUE,IF(s>0,$C$10:$W$10&": "&ROUND(s,2),""))&"}")))} | AO10: {=IF($AH10="","",LET(bal,SUMIFS(data_event_inst!$N:$N,data_event_inst!$A:$A,"Jigsaw",data_event_inst!$B:$B,$AI$3,data_event_inst!$C:$C,"40-99"),shr,MIN(1,IFERROR(CHOOSE(MATCH($AI$2,{"Avg","p25","p50","p75"},0),AVERAGEIFS(data_event_accrual!$I:$I,data_event_accrual!$A:$A,"Jigsaw",data_event_accrual!$B:$B,$AI$3,data_event_accrual!$C:$C,"40-99",data_event_accrual!$E:$E,$AH10),AVERAGEIFS(data_event_accrual!$K:$K,data_event_accrual!$A:$A,"Jigsaw",data_event_accrual!$B:$B,$AI$3,data_event_accrual!$C:$C,"40-99",data_event_accrual!$E:$E,$AH10),AVERAGEIFS(data_event_accrual!$J:$J,data_event_accrual!$A:$A,"Jigsaw",data_event_accrual!$B:$B,$AI$3,data_event_accrual!$C:$C,"40-99",data_event_accrual!$E:$E,$AH10),AVERAGEIFS(data_event_accrual!$L:$L,data_event_accrual!$A:$A,"Jigsaw",data_event_accrual!$B:$B,$AI$3,data_event_accrual!$C:$C,"40-99",data_event_accrual!$E:$E,$AH10)),1)),COUNTIF($B$11:$B$22,"<="&bal*shr)))} | AP10: {=IF($AH10="","",IF(AO10=0,"{}",LET(m,AO10,s,MMULT(SEQUENCE(1,m,1,0),$C$11:$W$22),"{"&TEXTJOIN(", ",TRUE,IF(s>0,$C$10:$W$10&": "&ROUND(s,2),""))&"}")))} | AQ10: {=IF($AH10="","",LET(bal,SUMIFS(data_event_inst!$N:$N,data_event_inst!$A:$A,"Jigsaw",data_event_inst!$B:$B,$AI$3,data_event_inst!$C:$C,"100+"),shr,MIN(1,IFERROR(CHOOSE(MATCH($AI$2,{"Avg","p25","p50","p75"},0),AVERAGEIFS(data_event_accrual!$I:$I,data_event_accrual!$A:$A,"Jigsaw",data_event_accrual!$B:$B,$AI$3,data_event_accrual!$C:$C,"100+",data_event_accrual!$E:$E,$AH10),AVERAGEIFS(data_event_accrual!$K:$K,data_event_accrual!$A:$A,"Jigsaw",data_event_accrual!$B:$B,$AI$3,data_event_accrual!$C:$C,"100+",data_event_accrual!$E:$E,$AH10),AVERAGEIFS(data_event_accrual!$J:$J,data_event_accrual!$A:$A,"Jigsaw",data_event_accrual!$B:$B,$AI$3,data_event_accrual!$C:$C,"100+",data_event_accrual!$E:$E,$AH10),AVERAGEIFS(data_event_accrual!$L:$L,data_event_accrual!$A:$A,"Jigsaw",data_event_accrual!$B:$B,$AI$3,data_event_accrual!$C:$C,"100+",data_event_accrual!$E:$E,$AH10)),1)),COUNTIF($B$11:$B$22,"<="&bal*shr)))} | AR10: {=IF($AH10="","",IF(AQ10=0,"{}",LET(m,AQ10,s,MMULT(SEQUENCE(1,m,1,0),$C$11:$W$22),"{"&TEXTJOIN(", ",TRUE,IF(s>0,$C$10:$W$10&": "&ROUND(s,2),""))&"}")))}
A11: 1 | B11: 30 | C11: 0 | D11: 0 | E11: 0 | F11: 0 | G11: 1 | H11: 0 | I11: 0 | J11: 0 | K11: 0 | L11: 0 | M11: 0 | N11: 0 | O11: 0 | P11: 0 | Q11: 0 | R11: 0 | S11: 0 | T11: 0 | U11: 0 | V11: 0 | W11: 0 | AH11: =IF(6<=$B$3,6,"") | AI11: {=IF($AH11="","",LET(bal,SUMIFS(data_event_inst!$N:$N,data_event_inst!$A:$A,"Jigsaw",data_event_inst!$B:$B,$AI$3,data_event_inst!$C:$C,"0-9"),shr,MIN(1,IFERROR(CHOOSE(MATCH($AI$2,{"Avg","p25","p50","p75"},0),AVERAGEIFS(data_event_accrual!$I:$I,data_event_accrual!$A:$A,"Jigsaw",data_event_accrual!$B:$B,$AI$3,data_event_accrual!$C:$C,"0-9",data_event_accrual!$E:$E,$AH11),AVERAGEIFS(data_event_accrual!$K:$K,data_event_accrual!$A:$A,"Jigsaw",data_event_accrual!$B:$B,$AI$3,data_event_accrual!$C:$C,"0-9",data_event_accrual!$E:$E,$AH11),AVERAGEIFS(data_event_accrual!$J:$J,data_event_accrual!$A:$A,"Jigsaw",data_event_accrual!$B:$B,$AI$3,data_event_accrual!$C:$C,"0-9",data_event_accrual!$E:$E,$AH11),AVERAGEIFS(data_event_accrual!$L:$L,data_event_accrual!$A:$A,"Jigsaw",data_event_accrual!$B:$B,$AI$3,data_event_accrual!$C:$C,"0-9",data_event_accrual!$E:$E,$AH11)),1)),COUNTIF($B$11:$B$22,"<="&bal*shr)))} | AJ11: {=IF($AH11="","",IF(AI11=0,"{}",LET(m,AI11,s,MMULT(SEQUENCE(1,m,1,0),$C$11:$W$22),"{"&TEXTJOIN(", ",TRUE,IF(s>0,$C$10:$W$10&": "&ROUND(s,2),""))&"}")))} | AK11: {=IF($AH11="","",LET(bal,SUMIFS(data_event_inst!$N:$N,data_event_inst!$A:$A,"Jigsaw",data_event_inst!$B:$B,$AI$3,data_event_inst!$C:$C,"10-19"),shr,MIN(1,IFERROR(CHOOSE(MATCH($AI$2,{"Avg","p25","p50","p75"},0),AVERAGEIFS(data_event_accrual!$I:$I,data_event_accrual!$A:$A,"Jigsaw",data_event_accrual!$B:$B,$AI$3,data_event_accrual!$C:$C,"10-19",data_event_accrual!$E:$E,$AH11),AVERAGEIFS(data_event_accrual!$K:$K,data_event_accrual!$A:$A,"Jigsaw",data_event_accrual!$B:$B,$AI$3,data_event_accrual!$C:$C,"10-19",data_event_accrual!$E:$E,$AH11),AVERAGEIFS(data_event_accrual!$J:$J,data_event_accrual!$A:$A,"Jigsaw",data_event_accrual!$B:$B,$AI$3,data_event_accrual!$C:$C,"10-19",data_event_accrual!$E:$E,$AH11),AVERAGEIFS(data_event_accrual!$L:$L,data_event_accrual!$A:$A,"Jigsaw",data_event_accrual!$B:$B,$AI$3,data_event_accrual!$C:$C,"10-19",data_event_accrual!$E:$E,$AH11)),1)),COUNTIF($B$11:$B$22,"<="&bal*shr)))} | AL11: {=IF($AH11="","",IF(AK11=0,"{}",LET(m,AK11,s,MMULT(SEQUENCE(1,m,1,0),$C$11:$W$22),"{"&TEXTJOIN(", ",TRUE,IF(s>0,$C$10:$W$10&": "&ROUND(s,2),""))&"}")))} | AM11: {=IF($AH11="","",LET(bal,SUMIFS(data_event_inst!$N:$N,data_event_inst!$A:$A,"Jigsaw",data_event_inst!$B:$B,$AI$3,data_event_inst!$C:$C,"20-39"),shr,MIN(1,IFERROR(CHOOSE(MATCH($AI$2,{"Avg","p25","p50","p75"},0),AVERAGEIFS(data_event_accrual!$I:$I,data_event_accrual!$A:$A,"Jigsaw",data_event_accrual!$B:$B,$AI$3,data_event_accrual!$C:$C,"20-39",data_event_accrual!$E:$E,$AH11),AVERAGEIFS(data_event_accrual!$K:$K,data_event_accrual!$A:$A,"Jigsaw",data_event_accrual!$B:$B,$AI$3,data_event_accrual!$C:$C,"20-39",data_event_accrual!$E:$E,$AH11),AVERAGEIFS(data_event_accrual!$J:$J,data_event_accrual!$A:$A,"Jigsaw",data_event_accrual!$B:$B,$AI$3,data_event_accrual!$C:$C,"20-39",data_event_accrual!$E:$E,$AH11),AVERAGEIFS(data_event_accrual!$L:$L,data_event_accrual!$A:$A,"Jigsaw",data_event_accrual!$B:$B,$AI$3,data_event_accrual!$C:$C,"20-39",data_event_accrual!$E:$E,$AH11)),1)),COUNTIF($B$11:$B$22,"<="&bal*shr)))} | AN11: {=IF($AH11="","",IF(AM11=0,"{}",LET(m,AM11,s,MMULT(SEQUENCE(1,m,1,0),$C$11:$W$22),"{"&TEXTJOIN(", ",TRUE,IF(s>0,$C$10:$W$10&": "&ROUND(s,2),""))&"}")))} | AO11: {=IF($AH11="","",LET(bal,SUMIFS(data_event_inst!$N:$N,data_event_inst!$A:$A,"Jigsaw",data_event_inst!$B:$B,$AI$3,data_event_inst!$C:$C,"40-99"),shr,MIN(1,IFERROR(CHOOSE(MATCH($AI$2,{"Avg","p25","p50","p75"},0),AVERAGEIFS(data_event_accrual!$I:$I,data_event_accrual!$A:$A,"Jigsaw",data_event_accrual!$B:$B,$AI$3,data_event_accrual!$C:$C,"40-99",data_event_accrual!$E:$E,$AH11),AVERAGEIFS(data_event_accrual!$K:$K,data_event_accrual!$A:$A,"Jigsaw",data_event_accrual!$B:$B,$AI$3,data_event_accrual!$C:$C,"40-99",data_event_accrual!$E:$E,$AH11),AVERAGEIFS(data_event_accrual!$J:$J,data_event_accrual!$A:$A,"Jigsaw",data_event_accrual!$B:$B,$AI$3,data_event_accrual!$C:$C,"40-99",data_event_accrual!$E:$E,$AH11),AVERAGEIFS(data_event_accrual!$L:$L,data_event_accrual!$A:$A,"Jigsaw",data_event_accrual!$B:$B,$AI$3,data_event_accrual!$C:$C,"40-99",data_event_accrual!$E:$E,$AH11)),1)),COUNTIF($B$11:$B$22,"<="&bal*shr)))} | AP11: {=IF($AH11="","",IF(AO11=0,"{}",LET(m,AO11,s,MMULT(SEQUENCE(1,m,1,0),$C$11:$W$22),"{"&TEXTJOIN(", ",TRUE,IF(s>0,$C$10:$W$10&": "&ROUND(s,2),""))&"}")))} | AQ11: {=IF($AH11="","",LET(bal,SUMIFS(data_event_inst!$N:$N,data_event_inst!$A:$A,"Jigsaw",data_event_inst!$B:$B,$AI$3,data_event_inst!$C:$C,"100+"),shr,MIN(1,IFERROR(CHOOSE(MATCH($AI$2,{"Avg","p25","p50","p75"},0),AVERAGEIFS(data_event_accrual!$I:$I,data_event_accrual!$A:$A,"Jigsaw",data_event_accrual!$B:$B,$AI$3,data_event_accrual!$C:$C,"100+",data_event_accrual!$E:$E,$AH11),AVERAGEIFS(data_event_accrual!$K:$K,data_event_accrual!$A:$A,"Jigsaw",data_event_accrual!$B:$B,$AI$3,data_event_accrual!$C:$C,"100+",data_event_accrual!$E:$E,$AH11),AVERAGEIFS(data_event_accrual!$J:$J,data_event_accrual!$A:$A,"Jigsaw",data_event_accrual!$B:$B,$AI$3,data_event_accrual!$C:$C,"100+",data_event_accrual!$E:$E,$AH11),AVERAGEIFS(data_event_accrual!$L:$L,data_event_accrual!$A:$A,"Jigsaw",data_event_accrual!$B:$B,$AI$3,data_event_accrual!$C:$C,"100+",data_event_accrual!$E:$E,$AH11)),1)),COUNTIF($B$11:$B$22,"<="&bal*shr)))} | AR11: {=IF($AH11="","",IF(AQ11=0,"{}",LET(m,AQ11,s,MMULT(SEQUENCE(1,m,1,0),$C$11:$W$22),"{"&TEXTJOIN(", ",TRUE,IF(s>0,$C$10:$W$10&": "&ROUND(s,2),""))&"}")))}
A12: 2 | B12: 80 | C12: 0 | D12: 0 | E12: 0 | F12: 0 | G12: 0 | H12: 0 | I12: 0 | J12: 0 | K12: 0 | L12: 0 | M12: 10 | N12: 0 | O12: 0 | P12: 0 | Q12: 0 | R12: 0 | S12: 0 | T12: 0 | U12: 0 | V12: 0 | W12: 0 | AH12: =IF(7<=$B$3,7,"") | AI12: {=IF($AH12="","",LET(bal,SUMIFS(data_event_inst!$N:$N,data_event_inst!$A:$A,"Jigsaw",data_event_inst!$B:$B,$AI$3,data_event_inst!$C:$C,"0-9"),shr,MIN(1,IFERROR(CHOOSE(MATCH($AI$2,{"Avg","p25","p50","p75"},0),AVERAGEIFS(data_event_accrual!$I:$I,data_event_accrual!$A:$A,"Jigsaw",data_event_accrual!$B:$B,$AI$3,data_event_accrual!$C:$C,"0-9",data_event_accrual!$E:$E,$AH12),AVERAGEIFS(data_event_accrual!$K:$K,data_event_accrual!$A:$A,"Jigsaw",data_event_accrual!$B:$B,$AI$3,data_event_accrual!$C:$C,"0-9",data_event_accrual!$E:$E,$AH12),AVERAGEIFS(data_event_accrual!$J:$J,data_event_accrual!$A:$A,"Jigsaw",data_event_accrual!$B:$B,$AI$3,data_event_accrual!$C:$C,"0-9",data_event_accrual!$E:$E,$AH12),AVERAGEIFS(data_event_accrual!$L:$L,data_event_accrual!$A:$A,"Jigsaw",data_event_accrual!$B:$B,$AI$3,data_event_accrual!$C:$C,"0-9",data_event_accrual!$E:$E,$AH12)),1)),COUNTIF($B$11:$B$22,"<="&bal*shr)))} | AJ12: {=IF($AH12="","",IF(AI12=0,"{}",LET(m,AI12,s,MMULT(SEQUENCE(1,m,1,0),$C$11:$W$22),"{"&TEXTJOIN(", ",TRUE,IF(s>0,$C$10:$W$10&": "&ROUND(s,2),""))&"}")))} | AK12: {=IF($AH12="","",LET(bal,SUMIFS(data_event_inst!$N:$N,data_event_inst!$A:$A,"Jigsaw",data_event_inst!$B:$B,$AI$3,data_event_inst!$C:$C,"10-19"),shr,MIN(1,IFERROR(CHOOSE(MATCH($AI$2,{"Avg","p25","p50","p75"},0),AVERAGEIFS(data_event_accrual!$I:$I,data_event_accrual!$A:$A,"Jigsaw",data_event_accrual!$B:$B,$AI$3,data_event_accrual!$C:$C,"10-19",data_event_accrual!$E:$E,$AH12),AVERAGEIFS(data_event_accrual!$K:$K,data_event_accrual!$A:$A,"Jigsaw",data_event_accrual!$B:$B,$AI$3,data_event_accrual!$C:$C,"10-19",data_event_accrual!$E:$E,$AH12),AVERAGEIFS(data_event_accrual!$J:$J,data_event_accrual!$A:$A,"Jigsaw",data_event_accrual!$B:$B,$AI$3,data_event_accrual!$C:$C,"10-19",data_event_accrual!$E:$E,$AH12),AVERAGEIFS(data_event_accrual!$L:$L,data_event_accrual!$A:$A,"Jigsaw",data_event_accrual!$B:$B,$AI$3,data_event_accrual!$C:$C,"10-19",data_event_accrual!$E:$E,$AH12)),1)),COUNTIF($B$11:$B$22,"<="&bal*shr)))} | AL12: {=IF($AH12="","",IF(AK12=0,"{}",LET(m,AK12,s,MMULT(SEQUENCE(1,m,1,0),$C$11:$W$22),"{"&TEXTJOIN(", ",TRUE,IF(s>0,$C$10:$W$10&": "&ROUND(s,2),""))&"}")))} | AM12: {=IF($AH12="","",LET(bal,SUMIFS(data_event_inst!$N:$N,data_event_inst!$A:$A,"Jigsaw",data_event_inst!$B:$B,$AI$3,data_event_inst!$C:$C,"20-39"),shr,MIN(1,IFERROR(CHOOSE(MATCH($AI$2,{"Avg","p25","p50","p75"},0),AVERAGEIFS(data_event_accrual!$I:$I,data_event_accrual!$A:$A,"Jigsaw",data_event_accrual!$B:$B,$AI$3,data_event_accrual!$C:$C,"20-39",data_event_accrual!$E:$E,$AH12),AVERAGEIFS(data_event_accrual!$K:$K,data_event_accrual!$A:$A,"Jigsaw",data_event_accrual!$B:$B,$AI$3,data_event_accrual!$C:$C,"20-39",data_event_accrual!$E:$E,$AH12),AVERAGEIFS(data_event_accrual!$J:$J,data_event_accrual!$A:$A,"Jigsaw",data_event_accrual!$B:$B,$AI$3,data_event_accrual!$C:$C,"20-39",data_event_accrual!$E:$E,$AH12),AVERAGEIFS(data_event_accrual!$L:$L,data_event_accrual!$A:$A,"Jigsaw",data_event_accrual!$B:$B,$AI$3,data_event_accrual!$C:$C,"20-39",data_event_accrual!$E:$E,$AH12)),1)),COUNTIF($B$11:$B$22,"<="&bal*shr)))} | AN12: {=IF($AH12="","",IF(AM12=0,"{}",LET(m,AM12,s,MMULT(SEQUENCE(1,m,1,0),$C$11:$W$22),"{"&TEXTJOIN(", ",TRUE,IF(s>0,$C$10:$W$10&": "&ROUND(s,2),""))&"}")))} | AO12: {=IF($AH12="","",LET(bal,SUMIFS(data_event_inst!$N:$N,data_event_inst!$A:$A,"Jigsaw",data_event_inst!$B:$B,$AI$3,data_event_inst!$C:$C,"40-99"),shr,MIN(1,IFERROR(CHOOSE(MATCH($AI$2,{"Avg","p25","p50","p75"},0),AVERAGEIFS(data_event_accrual!$I:$I,data_event_accrual!$A:$A,"Jigsaw",data_event_accrual!$B:$B,$AI$3,data_event_accrual!$C:$C,"40-99",data_event_accrual!$E:$E,$AH12),AVERAGEIFS(data_event_accrual!$K:$K,data_event_accrual!$A:$A,"Jigsaw",data_event_accrual!$B:$B,$AI$3,data_event_accrual!$C:$C,"40-99",data_event_accrual!$E:$E,$AH12),AVERAGEIFS(data_event_accrual!$J:$J,data_event_accrual!$A:$A,"Jigsaw",data_event_accrual!$B:$B,$AI$3,data_event_accrual!$C:$C,"40-99",data_event_accrual!$E:$E,$AH12),AVERAGEIFS(data_event_accrual!$L:$L,data_event_accrual!$A:$A,"Jigsaw",data_event_accrual!$B:$B,$AI$3,data_event_accrual!$C:$C,"40-99",data_event_accrual!$E:$E,$AH12)),1)),COUNTIF($B$11:$B$22,"<="&bal*shr)))} | AP12: {=IF($AH12="","",IF(AO12=0,"{}",LET(m,AO12,s,MMULT(SEQUENCE(1,m,1,0),$C$11:$W$22),"{"&TEXTJOIN(", ",TRUE,IF(s>0,$C$10:$W$10&": "&ROUND(s,2),""))&"}")))} | AQ12: {=IF($AH12="","",LET(bal,SUMIFS(data_event_inst!$N:$N,data_event_inst!$A:$A,"Jigsaw",data_event_inst!$B:$B,$AI$3,data_event_inst!$C:$C,"100+"),shr,MIN(1,IFERROR(CHOOSE(MATCH($AI$2,{"Avg","p25","p50","p75"},0),AVERAGEIFS(data_event_accrual!$I:$I,data_event_accrual!$A:$A,"Jigsaw",data_event_accrual!$B:$B,$AI$3,data_event_accrual!$C:$C,"100+",data_event_accrual!$E:$E,$AH12),AVERAGEIFS(data_event_accrual!$K:$K,data_event_accrual!$A:$A,"Jigsaw",data_event_accrual!$B:$B,$AI$3,data_event_accrual!$C:$C,"100+",data_event_accrual!$E:$E,$AH12),AVERAGEIFS(data_event_accrual!$J:$J,data_event_accrual!$A:$A,"Jigsaw",data_event_accrual!$B:$B,$AI$3,data_event_accrual!$C:$C,"100+",data_event_accrual!$E:$E,$AH12),AVERAGEIFS(data_event_accrual!$L:$L,data_event_accrual!$A:$A,"Jigsaw",data_event_accrual!$B:$B,$AI$3,data_event_accrual!$C:$C,"100+",data_event_accrual!$E:$E,$AH12)),1)),COUNTIF($B$11:$B$22,"<="&bal*shr)))} | AR12: {=IF($AH12="","",IF(AQ12=0,"{}",LET(m,AQ12,s,MMULT(SEQUENCE(1,m,1,0),$C$11:$W$22),"{"&TEXTJOIN(", ",TRUE,IF(s>0,$C$10:$W$10&": "&ROUND(s,2),""))&"}")))}
A13: 3 | B13: 150 | C13: 0 | D13: 0 | E13: 0 | F13: 0 | G13: 0 | H13: 0 | I13: 0 | J13: 0 | K13: 0 | L13: 0 | M13: 0 | N13: 10 | O13: 0 | P13: 0 | Q13: 0 | R13: 0 | S13: 0 | T13: 0 | U13: 0 | V13: 0 | W13: 0
A14: 4 | B14: 250 | C14: 0 | D14: 0 | E14: 0 | F14: 0 | G14: 0 | H14: 0 | I14: 0 | J14: 0 | K14: 0 | L14: 30 | M14: 0 | N14: 0 | O14: 0 | P14: 0 | Q14: 0 | R14: 0 | S14: 0 | T14: 0 | U14: 0 | V14: 0 | W14: 0
A15: 5 | B15: 370 | C15: 25 | D15: 0 | E15: 0 | F15: 0 | G15: 0 | H15: 0 | I15: 0 | J15: 0 | K15: 0 | L15: 0 | M15: 0 | N15: 0 | O15: 0 | P15: 0 | Q15: 0 | R15: 0 | S15: 0 | T15: 0 | U15: 0 | V15: 0 | W15: 0
A16: 6 | B16: 520 | C16: 0 | D16: 0 | E16: 0 | F16: 1 | G16: 0 | H16: 0 | I16: 0 | J16: 0 | K16: 0 | L16: 0 | M16: 0 | N16: 0 | O16: 10 | P16: 0 | Q16: 0 | R16: 0 | S16: 0 | T16: 0 | U16: 0 | V16: 0 | W16: 0
A17: 7 | B17: 690 | C17: 0 | D17: 0 | E17: 0 | F17: 0 | G17: 0 | H17: 0 | I17: 0 | J17: 0 | K17: 0 | L17: 60 | M17: 0 | N17: 0 | O17: 0 | P17: 0 | Q17: 0 | R17: 0 | S17: 0 | T17: 0 | U17: 0 | V17: 0 | W17: 0
A18: 8 | B18: 890 | C18: 0 | D18: 0 | E18: 0 | F18: 0 | G18: 0 | H18: 0 | I18: 0 | J18: 0 | K18: 0 | L18: 0 | M18: 15 | N18: 0 | O18: 0 | P18: 0 | Q18: 0 | R18: 0 | S18: 0 | T18: 0 | U18: 0 | V18: 0 | W18: 0
A19: 9 | B19: 1110 | C19: 25 | D19: 0 | E19: 0 | F19: 0 | G19: 0 | H19: 0 | I19: 0 | J19: 0 | K19: 0 | L19: 0 | M19: 0 | N19: 0 | O19: 0 | P19: 0 | Q19: 0 | R19: 0 | S19: 0 | T19: 0 | U19: 0 | V19: 0 | W19: 0
A20: 10 | B20: 1360 | C20: 0 | D20: 0 | E20: 0 | F20: 0 | G20: 0 | H20: 0 | I20: 0 | J20: 0 | K20: 0 | L20: 0 | M20: 0 | N20: 15 | O20: 0 | P20: 0 | Q20: 0 | R20: 0 | S20: 0 | T20: 0 | U20: 0 | V20: 0 | W20: 0
A21: 11 | B21: 1630 | C21: 0 | D21: 0 | E21: 0 | F21: 0 | G21: 0 | H21: 0 | I21: 1 | J21: 0 | K21: 0 | L21: 0 | M21: 0 | N21: 0 | O21: 0 | P21: 0 | Q21: 0 | R21: 0 | S21: 0 | T21: 0 | U21: 0 | V21: 0 | W21: 0
A22: 12 | B22: 1930 | C22: 0 | D22: 0 | E22: 0 | F22: 0 | G22: 0 | H22: 0 | I22: 0 | J22: 0 | K22: 0 | L22: 60 | M22: 0 | N22: 0 | O22: 15 | P22: 0 | Q22: 0 | R22: 0 | S22: 0 | T22: 0 | U22: 0 | V22: 0 | W22: 0

Sheet HH
A1: Hatchling Hideaway
A2: Config Panel
A3: EventDuration | B3: 3
A4: requiredPlayerLevel | B4: 1
A5: requiredSagaLevel | B5: 15
A6: NormalLevelTokenReward | B6: 1
A7: HardLevelTokenReward | B7: 2
A8: ExtremeLevelTokenReward | B8: 3
A10: Goals and Rewards
A11: Gate number | B11: Coins | C11: SPT | D11: SPT x2 | E11: Red | F11: Chuck | G11: Bomb | H11: Slingshot | I11: Shuffle | J11: Comet | K11: Unlimited Lives | L11: Unlimited Red | M11: Unlimited Chuck | N11: Unlimited Bomb | O11: COOP Token | P11: Avatar | Q11: 1-star Dly | R11: 2-star Dly | S11: 3-star Dly | T11: 4-star Dly | U11: 5-star Dly | V11: 6-star Dly
A12: Gate 1 | B12: 0 | C12: 0 | D12: 0 | E12: 1 | F12: 0 | G12: 0 | H12: 0 | I12: 0 | J12: 0 | K12: 60 | L12: 0 | M12: 0 | N12: 0 | O12: 5 | P12: 0 | Q12: 0 | R12: 0 | S12: 0 | T12: 0 | U12: 0 | V12: 0
A13: Gate 2 | B13: 10 | C13: 0 | D13: 0 | E13: 0 | F13: 1 | G13: 0 | H13: 0 | I13: 0 | J13: 0 | K13: 0 | L13: 0 | M13: 0 | N13: 0 | O13: 10 | P13: 0 | Q13: 0 | R13: 0 | S13: 0 | T13: 0 | U13: 0 | V13: 0
A14: Gate 3 | B14: 0 | C14: 0 | D14: 0 | E14: 0 | F14: 0 | G14: 1 | H14: 0 | I14: 0 | J14: 1 | K14: 30 | L14: 0 | M14: 0 | N14: 0 | O14: 20 | P14: 0 | Q14: 0 | R14: 0 | S14: 0 | T14: 0 | U14: 0 | V14: 0
A15: Gate 4 | B15: 15 | C15: 0 | D15: 0 | E15: 0 | F15: 0 | G15: 0 | H15: 0 | I15: 1 | J15: 0 | K15: 0 | L15: 10 | M15: 0 | N15: 0 | O15: 50 | P15: 0 | Q15: 0 | R15: 0 | S15: 0 | T15: 0 | U15: 0 | V15: 0
A16: Gate 5 | B16: 40 | C16: 0 | D16: 0 | E16: 0 | F16: 0 | G16: 0 | H16: 1 | I16: 0 | J16: 0 | K16: 0 | L16: 0 | M16: 10 | N16: 0 | O16: 70 | P16: 0 | Q16: 0 | R16: 0 | S16: 0 | T16: 0 | U16: 0 | V16: 0

Sheet HH_v2
A1: Hatchling Hideaway | AH1: Player Reach Simulation (per event day) - SIMULATED
A2: Config Panel | AH2: Percentile | AI2: Avg | AT2: accuracy | AU2: 0.8
A3: EventDuration | B3: 4 | AH3: Payer | AI3: NONPAYER
A4: requiredPlayerLevel | B4: 1 | AT4: Gate | AU4: Tiles | AV4: Cum tokens req
A5: requiredSagaLevel | B5: 15 | AH5: Day_of_event | AI5: 0-9_ms | AJ5: 0-9_reward | AK5: 10-19_ms | AL5: 10-19_reward | AM5: 20-39_ms | AN5: 20-39_reward | AO5: 40-99_ms | AP5: 40-99_reward | AQ5: 100_ms | AR5: 100_reward | AT5: 1 | AU5: 16 | AV5: =SUM($AU$5:$AU5)/$AU$2 -> 20
A6: NormalLevelTokenReward | B6: 1 | AH6: =IF(1<=$B$3,1,"") -> 1 | AI6: {=IF($AH6="","",LET(bal,SUMIFS(data_event_inst!$N:$N,data_event_inst!$A:$A,"Hatchling Hideaway",data_event_inst!$B:$B,$AI$3,data_event_inst!$C:$C,"0-9"),shr,MIN(1,IFERROR(CHOOSE(MATCH($AI$2,{"Avg","p25","p50","p75"},0),AVERAGEIFS(data_event_accrual!$I:$I,data_event_accrual!$A:$A,"Hatchling Hideaway",data_event_accrual!$B:$B,$AI$3,data_event_accrual!$C:$C,"0-9",data_event_accrual!$E:$E,$AH6),AVERAGEIFS(data_event_accrual!$K:$K,data_event_accrual!$A:$A,"Hatchling Hideaway",data_event_accrual!$B:$B,$AI$3,data_event_accrual!$C:$C,"0-9",data_event_accrual!$E:$E,$AH6),AVERAGEIFS(data_event_accrual!$J:$J,data_event_accrual!$A:$A,"Hatchling Hideaway",data_event_accrual!$B:$B,$AI$3,data_event_accrual!$C:$C,"0-9",data_event_accrual!$E:$E,$AH6),AVERAGEIFS(data_event_accrual!$L:$L,data_event_accrual!$A:$A,"Hatchling Hideaway",data_event_accrual!$B:$B,$AI$3,data_event_accrual!$C:$C,"0-9",data_event_accrual!$E:$E,$AH6)),1)),COUNTIF($AV$5:$AV$9,"<="&bal*shr)))} -> 0 | AJ6: {=IF($AH6="","",IF(AI6=0,"{}",LET(m,AI6,s,MMULT(SEQUENCE(1,m,1,0),$B$12:$V$16),"{"&TEXTJOIN(", ",TRUE,IF(s>0,$B$11:$V$11&": "&ROUND(s,2),""))&"}")))} -> {} | AK6: {=IF($AH6="","",LET(bal,SUMIFS(data_event_inst!$N:$N,data_event_inst!$A:$A,"Hatchling Hideaway",data_event_inst!$B:$B,$AI$3,data_event_inst!$C:$C,"10-19"),shr,MIN(1,IFERROR(CHOOSE(MATCH($AI$2,{"Avg","p25","p50","p75"},0),AVERAGEIFS(data_event_accrual!$I:$I,data_event_accrual!$A:$A,"Hatchling Hideaway",data_event_accrual!$B:$B,$AI$3,data_event_accrual!$C:$C,"10-19",data_event_accrual!$E:$E,$AH6),AVERAGEIFS(data_event_accrual!$K:$K,data_event_accrual!$A:$A,"Hatchling Hideaway",data_event_accrual!$B:$B,$AI$3,data_event_accrual!$C:$C,"10-19",data_event_accrual!$E:$E,$AH6),AVERAGEIFS(data_event_accrual!$J:$J,data_event_accrual!$A:$A,"Hatchling Hideaway",data_event_accrual!$B:$B,$AI$3,data_event_accrual!$C:$C,"10-19",data_event_accrual!$E:$E,$AH6),AVERAGEIFS(data_event_accrual!$L:$L,data_event_accrual!$A:$A,"Hatchling Hideaway",data_event_accrual!$B:$B,$AI$3,data_event_accrual!$C:$C,"10-19",data_event_accrual!$E:$E,$AH6)),1)),COUNTIF($AV$5:$AV$9,"<="&bal*shr)))} -> 0 | AL6: {=IF($AH6="","",IF(AK6=0,"{}",LET(m,AK6,s,MMULT(SEQUENCE(1,m,1,0),$B$12:$V$16),"{"&TEXTJOIN(", ",TRUE,IF(s>0,$B$11:$V$11&": "&ROUND(s,2),""))&"}")))} -> {} | AM6: {=IF($AH6="","",LET(bal,SUMIFS(data_event_inst!$N:$N,data_event_inst!$A:$A,"Hatchling Hideaway",data_event_inst!$B:$B,$AI$3,data_event_inst!$C:$C,"20-39"),shr,MIN(1,IFERROR(CHOOSE(MATCH($AI$2,{"Avg","p25","p50","p75"},0),AVERAGEIFS(data_event_accrual!$I:$I,data_event_accrual!$A:$A,"Hatchling Hideaway",data_event_accrual!$B:$B,$AI$3,data_event_accrual!$C:$C,"20-39",data_event_accrual!$E:$E,$AH6),AVERAGEIFS(data_event_accrual!$K:$K,data_event_accrual!$A:$A,"Hatchling Hideaway",data_event_accrual!$B:$B,$AI$3,data_event_accrual!$C:$C,"20-39",data_event_accrual!$E:$E,$AH6),AVERAGEIFS(data_event_accrual!$J:$J,data_event_accrual!$A:$A,"Hatchling Hideaway",data_event_accrual!$B:$B,$AI$3,data_event_accrual!$C:$C,"20-39",data_event_accrual!$E:$E,$AH6),AVERAGEIFS(data_event_accrual!$L:$L,data_event_accrual!$A:$A,"Hatchling Hideaway",data_event_accrual!$B:$B,$AI$3,data_event_accrual!$C:$C,"20-39",data_event_accrual!$E:$E,$AH6)),1)),COUNTIF($AV$5:$AV$9,"<="&bal*shr)))} -> 1 | AN6: {=IF($AH6="","",IF(AM6=0,"{}",LET(m,AM6,s,MMULT(SEQUENCE(1,m,1,0),$B$12:$V$16),"{"&TEXTJOIN(", ",TRUE,IF(s>0,$B$11:$V$11&": "&ROUND(s,2),""))&"}")))} -> {Red: 1, Unlimited Lives: 60, COOP Token: 5} | AO6: {=IF($AH6="","",LET(bal,SUMIFS(data_event_inst!$N:$N,data_event_inst!$A:$A,"Hatchling Hideaway",data_event_inst!$B:$B,$AI$3,data_event_inst!$C:$C,"40-99"),shr,MIN(1,IFERROR(CHOOSE(MATCH($AI$2,{"Avg","p25","p50","p75"},0),AVERAGEIFS(data_event_accrual!$I:$I,data_event_accrual!$A:$A,"Hatchling Hideaway",data_event_accrual!$B:$B,$AI$3,data_event_accrual!$C:$C,"40-99",data_event_accrual!$E:$E,$AH6),AVERAGEIFS(data_event_accrual!$K:$K,data_event_accrual!$A:$A,"Hatchling Hideaway",data_event_accrual!$B:$B,$AI$3,data_event_accrual!$C:$C,"40-99",data_event_accrual!$E:$E,$AH6),AVERAGEIFS(data_event_accrual!$J:$J,data_event_accrual!$A:$A,"Hatchling Hideaway",data_event_accrual!$B:$B,$AI$3,data_event_accrual!$C:$C,"40-99",data_event_accrual!$E:$E,$AH6),AVERAGEIFS(data_event_accrual!$L:$L,data_event_accrual!$A:$A,"Hatchling Hideaway",data_event_accrual!$B:$B,$AI$3,data_event_accrual!$C:$C,"40-99",data_event_accrual!$E:$E,$AH6)),1)),COUNTIF($AV$5:$AV$9,"<="&bal*shr)))} -> 2 | AP6: {=IF($AH6="","",IF(AO6=0,"{}",LET(m,AO6,s,MMULT(SEQUENCE(1,m,1,0),$B$12:$V$16),"{"&TEXTJOIN(", ",TRUE,IF(s>0,$B$11:$V$11&": "&ROUND(s,2),""))&"}")))} -> {Coins: 10, Red: 1, Chuck: 1, Unlimited Lives: 60, COOP Token: 15} | AQ6: {=IF($AH6="","",LET(bal,SUMIFS(data_event_inst!$N:$N,data_event_inst!$A:$A,"Hatchling Hideaway",data_event_inst!$B:$B,$AI$3,data_event_inst!$C:$C,"100+"),shr,MIN(1,IFERROR(CHOOSE(MATCH($AI$2,{"Avg","p25","p50","p75"},0),AVERAGEIFS(data_event_accrual!$I:$I,data_event_accrual!$A:$A,"Hatchling Hideaway",data_event_accrual!$B:$B,$AI$3,data_event_accrual!$C:$C,"100+",data_event_accrual!$E:$E,$AH6),AVERAGEIFS(data_event_accrual!$K:$K,data_event_accrual!$A:$A,"Hatchling Hideaway",data_event_accrual!$B:$B,$AI$3,data_event_accrual!$C:$C,"100+",data_event_accrual!$E:$E,$AH6),AVERAGEIFS(data_event_accrual!$J:$J,data_event_accrual!$A:$A,"Hatchling Hideaway",data_event_accrual!$B:$B,$AI$3,data_event_accrual!$C:$C,"100+",data_event_accrual!$E:$E,$AH6),AVERAGEIFS(data_event_accrual!$L:$L,data_event_accrual!$A:$A,"Hatchling Hideaway",data_event_accrual!$B:$B,$AI$3,data_event_accrual!$C:$C,"100+",data_event_accrual!$E:$E,$AH6)),1)),COUNTIF($AV$5:$AV$9,"<="&bal*shr)))} -> 3 | AR6: {=IF($AH6="","",IF(AQ6=0,"{}",LET(m,AQ6,s,MMULT(SEQUENCE(1,m,1,0),$B$12:$V$16),"{"&TEXTJOIN(", ",TRUE,IF(s>0,$B$11:$V$11&": "&ROUND(s,2),""))&"}")))} -> {Coins: 10, Red: 1, Chuck: 1, Bomb: 1, Comet: 1, Unlimited Lives: 90, COOP Token: 35} | AT6: 2 | AU6: 25 | AV6: =SUM($AU$5:$AU6)/$AU$2 -> 51.25
A7: HardLevelTokenReward | B7: 2 | AH7: =IF(2<=$B$3,2,"") -> 2 | AI7: {=IF($AH7="","",LET(bal,SUMIFS(data_event_inst!$N:$N,data_event_inst!$A:$A,"Hatchling Hideaway",data_event_inst!$B:$B,$AI$3,data_event_inst!$C:$C,"0-9"),shr,MIN(1,IFERROR(CHOOSE(MATCH($AI$2,{"Avg","p25","p50","p75"},0),AVERAGEIFS(data_event_accrual!$I:$I,data_event_accrual!$A:$A,"Hatchling Hideaway",data_event_accrual!$B:$B,$AI$3,data_event_accrual!$C:$C,"0-9",data_event_accrual!$E:$E,$AH7),AVERAGEIFS(data_event_accrual!$K:$K,data_event_accrual!$A:$A,"Hatchling Hideaway",data_event_accrual!$B:$B,$AI$3,data_event_accrual!$C:$C,"0-9",data_event_accrual!$E:$E,$AH7),AVERAGEIFS(data_event_accrual!$J:$J,data_event_accrual!$A:$A,"Hatchling Hideaway",data_event_accrual!$B:$B,$AI$3,data_event_accrual!$C:$C,"0-9",data_event_accrual!$E:$E,$AH7),AVERAGEIFS(data_event_accrual!$L:$L,data_event_accrual!$A:$A,"Hatchling Hideaway",data_event_accrual!$B:$B,$AI$3,data_event_accrual!$C:$C,"0-9",data_event_accrual!$E:$E,$AH7)),1)),COUNTIF($AV$5:$AV$9,"<="&bal*shr)))} -> 0 | AJ7: {=IF($AH7="","",IF(AI7=0,"{}",LET(m,AI7,s,MMULT(SEQUENCE(1,m,1,0),$B$12:$V$16),"{"&TEXTJOIN(", ",TRUE,IF(s>0,$B$11:$V$11&": "&ROUND(s,2),""))&"}")))} -> {} | AK7: {=IF($AH7="","",LET(bal,SUMIFS(data_event_inst!$N:$N,data_event_inst!$A:$A,"Hatchling Hideaway",data_event_inst!$B:$B,$AI$3,data_event_inst!$C:$C,"10-19"),shr,MIN(1,IFERROR(CHOOSE(MATCH($AI$2,{"Avg","p25","p50","p75"},0),AVERAGEIFS(data_event_accrual!$I:$I,data_event_accrual!$A:$A,"Hatchling Hideaway",data_event_accrual!$B:$B,$AI$3,data_event_accrual!$C:$C,"10-19",data_event_accrual!$E:$E,$AH7),AVERAGEIFS(data_event_accrual!$K:$K,data_event_accrual!$A:$A,"Hatchling Hideaway",data_event_accrual!$B:$B,$AI$3,data_event_accrual!$C:$C,"10-19",data_event_accrual!$E:$E,$AH7),AVERAGEIFS(data_event_accrual!$J:$J,data_event_accrual!$A:$A,"Hatchling Hideaway",data_event_accrual!$B:$B,$AI$3,data_event_accrual!$C:$C,"10-19",data_event_accrual!$E:$E,$AH7),AVERAGEIFS(data_event_accrual!$L:$L,data_event_accrual!$A:$A,"Hatchling Hideaway",data_event_accrual!$B:$B,$AI$3,data_event_accrual!$C:$C,"10-19",data_event_accrual!$E:$E,$AH7)),1)),COUNTIF($AV$5:$AV$9,"<="&bal*shr)))} -> 1 | AL7: {=IF($AH7="","",IF(AK7=0,"{}",LET(m,AK7,s,MMULT(SEQUENCE(1,m,1,0),$B$12:$V$16),"{"&TEXTJOIN(", ",TRUE,IF(s>0,$B$11:$V$11&": "&ROUND(s,2),""))&"}")))} -> {Red: 1, Unlimited Lives: 60, COOP Token: 5} | AM7: {=IF($AH7="","",LET(bal,SUMIFS(data_event_inst!$N:$N,data_event_inst!$A:$A,"Hatchling Hideaway",data_event_inst!$B:$B,$AI$3,data_event_inst!$C:$C,"20-39"),shr,MIN(1,IFERROR(CHOOSE(MATCH($AI$2,{"Avg","p25","p50","p75"},0),AVERAGEIFS(data_event_accrual!$I:$I,data_event_accrual!$A:$A,"Hatchling Hideaway",data_event_accrual!$B:$B,$AI$3,data_event_accrual!$C:$C,"20-39",data_event_accrual!$E:$E,$AH7),AVERAGEIFS(data_event_accrual!$K:$K,data_event_accrual!$A:$A,"Hatchling Hideaway",data_event_accrual!$B:$B,$AI$3,data_event_accrual!$C:$C,"20-39",data_event_accrual!$E:$E,$AH7),AVERAGEIFS(data_event_accrual!$J:$J,data_event_accrual!$A:$A,"Hatchling Hideaway",data_event_accrual!$B:$B,$AI$3,data_event_accrual!$C:$C,"20-39",data_event_accrual!$E:$E,$AH7),AVERAGEIFS(data_event_accrual!$L:$L,data_event_accrual!$A:$A,"Hatchling Hideaway",data_event_accrual!$B:$B,$AI$3,data_event_accrual!$C:$C,"20-39",data_event_accrual!$E:$E,$AH7)),1)),COUNTIF($AV$5:$AV$9,"<="&bal*shr)))} -> 2 | AN7: {=IF($AH7="","",IF(AM7=0,"{}",LET(m,AM7,s,MMULT(SEQUENCE(1,m,1,0),$B$12:$V$16),"{"&TEXTJOIN(", ",TRUE,IF(s>0,$B$11:$V$11&": "&ROUND(s,2),""))&"}")))} -> {Coins: 10, Red: 1, Chuck: 1, Unlimited Lives: 60, COOP Token: 15} | AO7: {=IF($AH7="","",LET(bal,SUMIFS(data_event_inst!$N:$N,data_event_inst!$A:$A,"Hatchling Hideaway",data_event_inst!$B:$B,$AI$3,data_event_inst!$C:$C,"40-99"),shr,MIN(1,IFERROR(CHOOSE(MATCH($AI$2,{"Avg","p25","p50","p75"},0),AVERAGEIFS(data_event_accrual!$I:$I,data_event_accrual!$A:$A,"Hatchling Hideaway",data_event_accrual!$B:$B,$AI$3,data_event_accrual!$C:$C,"40-99",data_event_accrual!$E:$E,$AH7),AVERAGEIFS(data_event_accrual!$K:$K,data_event_accrual!$A:$A,"Hatchling Hideaway",data_event_accrual!$B:$B,$AI$3,data_event_accrual!$C:$C,"40-99",data_event_accrual!$E:$E,$AH7),AVERAGEIFS(data_event_accrual!$J:$J,data_event_accrual!$A:$A,"Hatchling Hideaway",data_event_accrual!$B:$B,$AI$3,data_event_accrual!$C:$C,"40-99",data_event_accrual!$E:$E,$AH7),AVERAGEIFS(data_event_accrual!$L:$L,data_event_accrual!$A:$A,"Hatchling Hideaway",data_event_accrual!$B:$B,$AI$3,data_event_accrual!$C:$C,"40-99",data_event_accrual!$E:$E,$AH7)),1)),COUNTIF($AV$5:$AV$9,"<="&bal*shr)))} -> 3 | AP7: {=IF($AH7="","",IF(AO7=0,"{}",LET(m,AO7,s,MMULT(SEQUENCE(1,m,1,0),$B$12:$V$16),"{"&TEXTJOIN(", ",TRUE,IF(s>0,$B$11:$V$11&": "&ROUND(s,2),""))&"}")))} -> {Coins: 10, Red: 1, Chuck: 1, Bomb: 1, Comet: 1, Unlimited Lives: 90, COOP Token: 35} | AQ7: {=IF($AH7="","",LET(bal,SUMIFS(data_event_inst!$N:$N,data_event_inst!$A:$A,"Hatchling Hideaway",data_event_inst!$B:$B,$AI$3,data_event_inst!$C:$C,"100+"),shr,MIN(1,IFERROR(CHOOSE(MATCH($AI$2,{"Avg","p25","p50","p75"},0),AVERAGEIFS(data_event_accrual!$I:$I,data_event_accrual!$A:$A,"Hatchling Hideaway",data_event_accrual!$B:$B,$AI$3,data_event_accrual!$C:$C,"100+",data_event_accrual!$E:$E,$AH7),AVERAGEIFS(data_event_accrual!$K:$K,data_event_accrual!$A:$A,"Hatchling Hideaway",data_event_accrual!$B:$B,$AI$3,data_event_accrual!$C:$C,"100+",data_event_accrual!$E:$E,$AH7),AVERAGEIFS(data_event_accrual!$J:$J,data_event_accrual!$A:$A,"Hatchling Hideaway",data_event_accrual!$B:$B,$AI$3,data_event_accrual!$C:$C,"100+",data_event_accrual!$E:$E,$AH7),AVERAGEIFS(data_event_accrual!$L:$L,data_event_accrual!$A:$A,"Hatchling Hideaway",data_event_accrual!$B:$B,$AI$3,data_event_accrual!$C:$C,"100+",data_event_accrual!$E:$E,$AH7)),1)),COUNTIF($AV$5:$AV$9,"<="&bal*shr)))} -> 3 | AR7: {=IF($AH7="","",IF(AQ7=0,"{}",LET(m,AQ7,s,MMULT(SEQUENCE(1,m,1,0),$B$12:$V$16),"{"&TEXTJOIN(", ",TRUE,IF(s>0,$B$11:$V$11&": "&ROUND(s,2),""))&"}")))} -> {Coins: 10, Red: 1, Chuck: 1, Bomb: 1, Comet: 1, Unlimited Lives: 90, COOP Token: 35} | AT7: 3 | AU7: 36 | AV7: =SUM($AU$5:$AU7)/$AU$2 -> 96.25
A8: ExtremeLevelTokenReward | B8: 3 | AH8: =IF(3<=$B$3,3,"") -> 3 | AI8: {=IF($AH8="","",LET(bal,SUMIFS(data_event_inst!$N:$N,data_event_inst!$A:$A,"Hatchling Hideaway",data_event_inst!$B:$B,$AI$3,data_event_inst!$C:$C,"0-9"),shr,MIN(1,IFERROR(CHOOSE(MATCH($AI$2,{"Avg","p25","p50","p75"},0),AVERAGEIFS(data_event_accrual!$I:$I,data_event_accrual!$A:$A,"Hatchling Hideaway",data_event_accrual!$B:$B,$AI$3,data_event_accrual!$C:$C,"0-9",data_event_accrual!$E:$E,$AH8),AVERAGEIFS(data_event_accrual!$K:$K,data_event_accrual!$A:$A,"Hatchling Hideaway",data_event_accrual!$B:$B,$AI$3,data_event_accrual!$C:$C,"0-9",data_event_accrual!$E:$E,$AH8),AVERAGEIFS(data_event_accrual!$J:$J,data_event_accrual!$A:$A,"Hatchling Hideaway",data_event_accrual!$B:$B,$AI$3,data_event_accrual!$C:$C,"0-9",data_event_accrual!$E:$E,$AH8),AVERAGEIFS(data_event_accrual!$L:$L,data_event_accrual!$A:$A,"Hatchling Hideaway",data_event_accrual!$B:$B,$AI$3,data_event_accrual!$C:$C,"0-9",data_event_accrual!$E:$E,$AH8)),1)),COUNTIF($AV$5:$AV$9,"<="&bal*shr)))} -> 0 | AJ8: {=IF($AH8="","",IF(AI8=0,"{}",LET(m,AI8,s,MMULT(SEQUENCE(1,m,1,0),$B$12:$V$16),"{"&TEXTJOIN(", ",TRUE,IF(s>0,$B$11:$V$11&": "&ROUND(s,2),""))&"}")))} -> {} | AK8: {=IF($AH8="","",LET(bal,SUMIFS(data_event_inst!$N:$N,data_event_inst!$A:$A,"Hatchling Hideaway",data_event_inst!$B:$B,$AI$3,data_event_inst!$C:$C,"10-19"),shr,MIN(1,IFERROR(CHOOSE(MATCH($AI$2,{"Avg","p25","p50","p75"},0),AVERAGEIFS(data_event_accrual!$I:$I,data_event_accrual!$A:$A,"Hatchling Hideaway",data_event_accrual!$B:$B,$AI$3,data_event_accrual!$C:$C,"10-19",data_event_accrual!$E:$E,$AH8),AVERAGEIFS(data_event_accrual!$K:$K,data_event_accrual!$A:$A,"Hatchling Hideaway",data_event_accrual!$B:$B,$AI$3,data_event_accrual!$C:$C,"10-19",data_event_accrual!$E:$E,$AH8),AVERAGEIFS(data_event_accrual!$J:$J,data_event_accrual!$A:$A,"Hatchling Hideaway",data_event_accrual!$B:$B,$AI$3,data_event_accrual!$C:$C,"10-19",data_event_accrual!$E:$E,$AH8),AVERAGEIFS(data_event_accrual!$L:$L,data_event_accrual!$A:$A,"Hatchling Hideaway",data_event_accrual!$B:$B,$AI$3,data_event_accrual!$C:$C,"10-19",data_event_accrual!$E:$E,$AH8)),1)),COUNTIF($AV$5:$AV$9,"<="&bal*shr)))} -> 1 | AL8: {=IF($AH8="","",IF(AK8=0,"{}",LET(m,AK8,s,MMULT(SEQUENCE(1,m,1,0),$B$12:$V$16),"{"&TEXTJOIN(", ",TRUE,IF(s>0,$B$11:$V$11&": "&ROUND(s,2),""))&"}")))} -> {Red: 1, Unlimited Lives: 60, COOP Token: 5} | AM8: {=IF($AH8="","",LET(bal,SUMIFS(data_event_inst!$N:$N,data_event_inst!$A:$A,"Hatchling Hideaway",data_event_inst!$B:$B,$AI$3,data_event_inst!$C:$C,"20-39"),shr,MIN(1,IFERROR(CHOOSE(MATCH($AI$2,{"Avg","p25","p50","p75"},0),AVERAGEIFS(data_event_accrual!$I:$I,data_event_accrual!$A:$A,"Hatchling Hideaway",data_event_accrual!$B:$B,$AI$3,data_event_accrual!$C:$C,"20-39",data_event_accrual!$E:$E,$AH8),AVERAGEIFS(data_event_accrual!$K:$K,data_event_accrual!$A:$A,"Hatchling Hideaway",data_event_accrual!$B:$B,$AI$3,data_event_accrual!$C:$C,"20-39",data_event_accrual!$E:$E,$AH8),AVERAGEIFS(data_event_accrual!$J:$J,data_event_accrual!$A:$A,"Hatchling Hideaway",data_event_accrual!$B:$B,$AI$3,data_event_accrual!$C:$C,"20-39",data_event_accrual!$E:$E,$AH8),AVERAGEIFS(data_event_accrual!$L:$L,data_event_accrual!$A:$A,"Hatchling Hideaway",data_event_accrual!$B:$B,$AI$3,data_event_accrual!$C:$C,"20-39",data_event_accrual!$E:$E,$AH8)),1)),COUNTIF($AV$5:$AV$9,"<="&bal*shr)))} -> 2 | AN8: {=IF($AH8="","",IF(AM8=0,"{}",LET(m,AM8,s,MMULT(SEQUENCE(1,m,1,0),$B$12:$V$16),"{"&TEXTJOIN(", ",TRUE,IF(s>0,$B$11:$V$11&": "&ROUND(s,2),""))&"}")))} -> {Coins: 10, Red: 1, Chuck: 1, Unlimited Lives: 60, COOP Token: 15} | AO8: {=IF($AH8="","",LET(bal,SUMIFS(data_event_inst!$N:$N,data_event_inst!$A:$A,"Hatchling Hideaway",data_event_inst!$B:$B,$AI$3,data_event_inst!$C:$C,"40-99"),shr,MIN(1,IFERROR(CHOOSE(MATCH($AI$2,{"Avg","p25","p50","p75"},0),AVERAGEIFS(data_event_accrual!$I:$I,data_event_accrual!$A:$A,"Hatchling Hideaway",data_event_accrual!$B:$B,$AI$3,data_event_accrual!$C:$C,"40-99",data_event_accrual!$E:$E,$AH8),AVERAGEIFS(data_event_accrual!$K:$K,data_event_accrual!$A:$A,"Hatchling Hideaway",data_event_accrual!$B:$B,$AI$3,data_event_accrual!$C:$C,"40-99",data_event_accrual!$E:$E,$AH8),AVERAGEIFS(data_event_accrual!$J:$J,data_event_accrual!$A:$A,"Hatchling Hideaway",data_event_accrual!$B:$B,$AI$3,data_event_accrual!$C:$C,"40-99",data_event_accrual!$E:$E,$AH8),AVERAGEIFS(data_event_accrual!$L:$L,data_event_accrual!$A:$A,"Hatchling Hideaway",data_event_accrual!$B:$B,$AI$3,data_event_accrual!$C:$C,"40-99",data_event_accrual!$E:$E,$AH8)),1)),COUNTIF($AV$5:$AV$9,"<="&bal*shr)))} -> 3 | AP8: {=IF($AH8="","",IF(AO8=0,"{}",LET(m,AO8,s,MMULT(SEQUENCE(1,m,1,0),$B$12:$V$16),"{"&TEXTJOIN(", ",TRUE,IF(s>0,$B$11:$V$11&": "&ROUND(s,2),""))&"}")))} -> {Coins: 10, Red: 1, Chuck: 1, Bomb: 1, Comet: 1, Unlimited Lives: 90, COOP Token: 35} | AQ8: {=IF($AH8="","",LET(bal,SUMIFS(data_event_inst!$N:$N,data_event_inst!$A:$A,"Hatchling Hideaway",data_event_inst!$B:$B,$AI$3,data_event_inst!$C:$C,"100+"),shr,MIN(1,IFERROR(CHOOSE(MATCH($AI$2,{"Avg","p25","p50","p75"},0),AVERAGEIFS(data_event_accrual!$I:$I,data_event_accrual!$A:$A,"Hatchling Hideaway",data_event_accrual!$B:$B,$AI$3,data_event_accrual!$C:$C,"100+",data_event_accrual!$E:$E,$AH8),AVERAGEIFS(data_event_accrual!$K:$K,data_event_accrual!$A:$A,"Hatchling Hideaway",data_event_accrual!$B:$B,$AI$3,data_event_accrual!$C:$C,"100+",data_event_accrual!$E:$E,$AH8),AVERAGEIFS(data_event_accrual!$J:$J,data_event_accrual!$A:$A,"Hatchling Hideaway",data_event_accrual!$B:$B,$AI$3,data_event_accrual!$C:$C,"100+",data_event_accrual!$E:$E,$AH8),AVERAGEIFS(data_event_accrual!$L:$L,data_event_accrual!$A:$A,"Hatchling Hideaway",data_event_accrual!$B:$B,$AI$3,data_event_accrual!$C:$C,"100+",data_event_accrual!$E:$E,$AH8)),1)),COUNTIF($AV$5:$AV$9,"<="&bal*shr)))} -> 4 | AR8: {=IF($AH8="","",IF(AQ8=0,"{}",LET(m,AQ8,s,MMULT(SEQUENCE(1,m,1,0),$B$12:$V$16),"{"&TEXTJOIN(", ",TRUE,IF(s>0,$B$11:$V$11&": "&ROUND(s,2),""))&"}")))} -> {Coins: 25, Red: 1, Chuck: 1, Bomb: 1, Shuffle: 1, Comet: 1, Unlimited Lives: 90, Unlimited Red: 10, COOP Token: 85} | AT8: 4 | AU8: 49 | AV8: =SUM($AU$5:$AU8)/$AU$2 -> 157.5
AH9: =IF(4<=$B$3,4,"") -> 4 | AI9: {=IF($AH9="","",LET(bal,SUMIFS(data_event_inst!$N:$N,data_event_inst!$A:$A,"Hatchling Hideaway",data_event_inst!$B:$B,$AI$3,data_event_inst!$C:$C,"0-9"),shr,MIN(1,IFERROR(CHOOSE(MATCH($AI$2,{"Avg","p25","p50","p75"},0),AVERAGEIFS(data_event_accrual!$I:$I,data_event_accrual!$A:$A,"Hatchling Hideaway",data_event_accrual!$B:$B,$AI$3,data_event_accrual!$C:$C,"0-9",data_event_accrual!$E:$E,$AH9),AVERAGEIFS(data_event_accrual!$K:$K,data_event_accrual!$A:$A,"Hatchling Hideaway",data_event_accrual!$B:$B,$AI$3,data_event_accrual!$C:$C,"0-9",data_event_accrual!$E:$E,$AH9),AVERAGEIFS(data_event_accrual!$J:$J,data_event_accrual!$A:$A,"Hatchling Hideaway",data_event_accrual!$B:$B,$AI$3,data_event_accrual!$C:$C,"0-9",data_event_accrual!$E:$E,$AH9),AVERAGEIFS(data_event_accrual!$L:$L,data_event_accrual!$A:$A,"Hatchling Hideaway",data_event_accrual!$B:$B,$AI$3,data_event_accrual!$C:$C,"0-9",data_event_accrual!$E:$E,$AH9)),1)),COUNTIF($AV$5:$AV$9,"<="&bal*shr)))} -> 1 | AJ9: {=IF($AH9="","",IF(AI9=0,"{}",LET(m,AI9,s,MMULT(SEQUENCE(1,m,1,0),$B$12:$V$16),"{"&TEXTJOIN(", ",TRUE,IF(s>0,$B$11:$V$11&": "&ROUND(s,2),""))&"}")))} -> {Red: 1, Unlimited Lives: 60, COOP Token: 5} | AK9: {=IF($AH9="","",LET(bal,SUMIFS(data_event_inst!$N:$N,data_event_inst!$A:$A,"Hatchling Hideaway",data_event_inst!$B:$B,$AI$3,data_event_inst!$C:$C,"10-19"),shr,MIN(1,IFERROR(CHOOSE(MATCH($AI$2,{"Avg","p25","p50","p75"},0),AVERAGEIFS(data_event_accrual!$I:$I,data_event_accrual!$A:$A,"Hatchling Hideaway",data_event_accrual!$B:$B,$AI$3,data_event_accrual!$C:$C,"10-19",data_event_accrual!$E:$E,$AH9),AVERAGEIFS(data_event_accrual!$K:$K,data_event_accrual!$A:$A,"Hatchling Hideaway",data_event_accrual!$B:$B,$AI$3,data_event_accrual!$C:$C,"10-19",data_event_accrual!$E:$E,$AH9),AVERAGEIFS(data_event_accrual!$J:$J,data_event_accrual!$A:$A,"Hatchling Hideaway",data_event_accrual!$B:$B,$AI$3,data_event_accrual!$C:$C,"10-19",data_event_accrual!$E:$E,$AH9),AVERAGEIFS(data_event_accrual!$L:$L,data_event_accrual!$A:$A,"Hatchling Hideaway",data_event_accrual!$B:$B,$AI$3,data_event_accrual!$C:$C,"10-19",data_event_accrual!$E:$E,$AH9)),1)),COUNTIF($AV$5:$AV$9,"<="&bal*shr)))} -> 1 | AL9: {=IF($AH9="","",IF(AK9=0,"{}",LET(m,AK9,s,MMULT(SEQUENCE(1,m,1,0),$B$12:$V$16),"{"&TEXTJOIN(", ",TRUE,IF(s>0,$B$11:$V$11&": "&ROUND(s,2),""))&"}")))} -> {Red: 1, Unlimited Lives: 60, COOP Token: 5} | AM9: {=IF($AH9="","",LET(bal,SUMIFS(data_event_inst!$N:$N,data_event_inst!$A:$A,"Hatchling Hideaway",data_event_inst!$B:$B,$AI$3,data_event_inst!$C:$C,"20-39"),shr,MIN(1,IFERROR(CHOOSE(MATCH($AI$2,{"Avg","p25","p50","p75"},0),AVERAGEIFS(data_event_accrual!$I:$I,data_event_accrual!$A:$A,"Hatchling Hideaway",data_event_accrual!$B:$B,$AI$3,data_event_accrual!$C:$C,"20-39",data_event_accrual!$E:$E,$AH9),AVERAGEIFS(data_event_accrual!$K:$K,data_event_accrual!$A:$A,"Hatchling Hideaway",data_event_accrual!$B:$B,$AI$3,data_event_accrual!$C:$C,"20-39",data_event_accrual!$E:$E,$AH9),AVERAGEIFS(data_event_accrual!$J:$J,data_event_accrual!$A:$A,"Hatchling Hideaway",data_event_accrual!$B:$B,$AI$3,data_event_accrual!$C:$C,"20-39",data_event_accrual!$E:$E,$AH9),AVERAGEIFS(data_event_accrual!$L:$L,data_event_accrual!$A:$A,"Hatchling Hideaway",data_event_accrual!$B:$B,$AI$3,data_event_accrual!$C:$C,"20-39",data_event_accrual!$E:$E,$AH9)),1)),COUNTIF($AV$5:$AV$9,"<="&bal*shr)))} -> 2 | AN9: {=IF($AH9="","",IF(AM9=0,"{}",LET(m,AM9,s,MMULT(SEQUENCE(1,m,1,0),$B$12:$V$16),"{"&TEXTJOIN(", ",TRUE,IF(s>0,$B$11:$V$11&": "&ROUND(s,2),""))&"}")))} -> {Coins: 10, Red: 1, Chuck: 1, Unlimited Lives: 60, COOP Token: 15} | AO9: {=IF($AH9="","",LET(bal,SUMIFS(data_event_inst!$N:$N,data_event_inst!$A:$A,"Hatchling Hideaway",data_event_inst!$B:$B,$AI$3,data_event_inst!$C:$C,"40-99"),shr,MIN(1,IFERROR(CHOOSE(MATCH($AI$2,{"Avg","p25","p50","p75"},0),AVERAGEIFS(data_event_accrual!$I:$I,data_event_accrual!$A:$A,"Hatchling Hideaway",data_event_accrual!$B:$B,$AI$3,data_event_accrual!$C:$C,"40-99",data_event_accrual!$E:$E,$AH9),AVERAGEIFS(data_event_accrual!$K:$K,data_event_accrual!$A:$A,"Hatchling Hideaway",data_event_accrual!$B:$B,$AI$3,data_event_accrual!$C:$C,"40-99",data_event_accrual!$E:$E,$AH9),AVERAGEIFS(data_event_accrual!$J:$J,data_event_accrual!$A:$A,"Hatchling Hideaway",data_event_accrual!$B:$B,$AI$3,data_event_accrual!$C:$C,"40-99",data_event_accrual!$E:$E,$AH9),AVERAGEIFS(data_event_accrual!$L:$L,data_event_accrual!$A:$A,"Hatchling Hideaway",data_event_accrual!$B:$B,$AI$3,data_event_accrual!$C:$C,"40-99",data_event_accrual!$E:$E,$AH9)),1)),COUNTIF($AV$5:$AV$9,"<="&bal*shr)))} -> 3 | AP9: {=IF($AH9="","",IF(AO9=0,"{}",LET(m,AO9,s,MMULT(SEQUENCE(1,m,1,0),$B$12:$V$16),"{"&TEXTJOIN(", ",TRUE,IF(s>0,$B$11:$V$11&": "&ROUND(s,2),""))&"}")))} -> {Coins: 10, Red: 1, Chuck: 1, Bomb: 1, Comet: 1, Unlimited Lives: 90, COOP Token: 35} | AQ9: {=IF($AH9="","",LET(bal,SUMIFS(data_event_inst!$N:$N,data_event_inst!$A:$A,"Hatchling Hideaway",data_event_inst!$B:$B,$AI$3,data_event_inst!$C:$C,"100+"),shr,MIN(1,IFERROR(CHOOSE(MATCH($AI$2,{"Avg","p25","p50","p75"},0),AVERAGEIFS(data_event_accrual!$I:$I,data_event_accrual!$A:$A,"Hatchling Hideaway",data_event_accrual!$B:$B,$AI$3,data_event_accrual!$C:$C,"100+",data_event_accrual!$E:$E,$AH9),AVERAGEIFS(data_event_accrual!$K:$K,data_event_accrual!$A:$A,"Hatchling Hideaway",data_event_accrual!$B:$B,$AI$3,data_event_accrual!$C:$C,"100+",data_event_accrual!$E:$E,$AH9),AVERAGEIFS(data_event_accrual!$J:$J,data_event_accrual!$A:$A,"Hatchling Hideaway",data_event_accrual!$B:$B,$AI$3,data_event_accrual!$C:$C,"100+",data_event_accrual!$E:$E,$AH9),AVERAGEIFS(data_event_accrual!$L:$L,data_event_accrual!$A:$A,"Hatchling Hideaway",data_event_accrual!$B:$B,$AI$3,data_event_accrual!$C:$C,"100+",data_event_accrual!$E:$E,$AH9)),1)),COUNTIF($AV$5:$AV$9,"<="&bal*shr)))} -> 4 | AR9: {=IF($AH9="","",IF(AQ9=0,"{}",LET(m,AQ9,s,MMULT(SEQUENCE(1,m,1,0),$B$12:$V$16),"{"&TEXTJOIN(", ",TRUE,IF(s>0,$B$11:$V$11&": "&ROUND(s,2),""))&"}")))} -> {Coins: 25, Red: 1, Chuck: 1, Bomb: 1, Shuffle: 1, Comet: 1, Unlimited Lives: 90, Unlimited Red: 10, COOP Token: 85} | AT9: 5 | AU9: 64 | AV9: =SUM($AU$5:$AU9)/$AU$2 -> 237.5
A10: Goals and Rewards | AH10: =IF(5<=$B$3,5,"") | AI10: {=IF($AH10="","",LET(bal,SUMIFS(data_event_inst!$N:$N,data_event_inst!$A:$A,"Hatchling Hideaway",data_event_inst!$B:$B,$AI$3,data_event_inst!$C:$C,"0-9"),shr,MIN(1,IFERROR(CHOOSE(MATCH($AI$2,{"Avg","p25","p50","p75"},0),AVERAGEIFS(data_event_accrual!$I:$I,data_event_accrual!$A:$A,"Hatchling Hideaway",data_event_accrual!$B:$B,$AI$3,data_event_accrual!$C:$C,"0-9",data_event_accrual!$E:$E,$AH10),AVERAGEIFS(data_event_accrual!$K:$K,data_event_accrual!$A:$A,"Hatchling Hideaway",data_event_accrual!$B:$B,$AI$3,data_event_accrual!$C:$C,"0-9",data_event_accrual!$E:$E,$AH10),AVERAGEIFS(data_event_accrual!$J:$J,data_event_accrual!$A:$A,"Hatchling Hideaway",data_event_accrual!$B:$B,$AI$3,data_event_accrual!$C:$C,"0-9",data_event_accrual!$E:$E,$AH10),AVERAGEIFS(data_event_accrual!$L:$L,data_event_accrual!$A:$A,"Hatchling Hideaway",data_event_accrual!$B:$B,$AI$3,data_event_accrual!$C:$C,"0-9",data_event_accrual!$E:$E,$AH10)),1)),COUNTIF($AV$5:$AV$9,"<="&bal*shr)))} | AJ10: {=IF($AH10="","",IF(AI10=0,"{}",LET(m,AI10,s,MMULT(SEQUENCE(1,m,1,0),$B$12:$V$16),"{"&TEXTJOIN(", ",TRUE,IF(s>0,$B$11:$V$11&": "&ROUND(s,2),""))&"}")))} | AK10: {=IF($AH10="","",LET(bal,SUMIFS(data_event_inst!$N:$N,data_event_inst!$A:$A,"Hatchling Hideaway",data_event_inst!$B:$B,$AI$3,data_event_inst!$C:$C,"10-19"),shr,MIN(1,IFERROR(CHOOSE(MATCH($AI$2,{"Avg","p25","p50","p75"},0),AVERAGEIFS(data_event_accrual!$I:$I,data_event_accrual!$A:$A,"Hatchling Hideaway",data_event_accrual!$B:$B,$AI$3,data_event_accrual!$C:$C,"10-19",data_event_accrual!$E:$E,$AH10),AVERAGEIFS(data_event_accrual!$K:$K,data_event_accrual!$A:$A,"Hatchling Hideaway",data_event_accrual!$B:$B,$AI$3,data_event_accrual!$C:$C,"10-19",data_event_accrual!$E:$E,$AH10),AVERAGEIFS(data_event_accrual!$J:$J,data_event_accrual!$A:$A,"Hatchling Hideaway",data_event_accrual!$B:$B,$AI$3,data_event_accrual!$C:$C,"10-19",data_event_accrual!$E:$E,$AH10),AVERAGEIFS(data_event_accrual!$L:$L,data_event_accrual!$A:$A,"Hatchling Hideaway",data_event_accrual!$B:$B,$AI$3,data_event_accrual!$C:$C,"10-19",data_event_accrual!$E:$E,$AH10)),1)),COUNTIF($AV$5:$AV$9,"<="&bal*shr)))} | AL10: {=IF($AH10="","",IF(AK10=0,"{}",LET(m,AK10,s,MMULT(SEQUENCE(1,m,1,0),$B$12:$V$16),"{"&TEXTJOIN(", ",TRUE,IF(s>0,$B$11:$V$11&": "&ROUND(s,2),""))&"}")))} | AM10: {=IF($AH10="","",LET(bal,SUMIFS(data_event_inst!$N:$N,data_event_inst!$A:$A,"Hatchling Hideaway",data_event_inst!$B:$B,$AI$3,data_event_inst!$C:$C,"20-39"),shr,MIN(1,IFERROR(CHOOSE(MATCH($AI$2,{"Avg","p25","p50","p75"},0),AVERAGEIFS(data_event_accrual!$I:$I,data_event_accrual!$A:$A,"Hatchling Hideaway",data_event_accrual!$B:$B,$AI$3,data_event_accrual!$C:$C,"20-39",data_event_accrual!$E:$E,$AH10),AVERAGEIFS(data_event_accrual!$K:$K,data_event_accrual!$A:$A,"Hatchling Hideaway",data_event_accrual!$B:$B,$AI$3,data_event_accrual!$C:$C,"20-39",data_event_accrual!$E:$E,$AH10),AVERAGEIFS(data_event_accrual!$J:$J,data_event_accrual!$A:$A,"Hatchling Hideaway",data_event_accrual!$B:$B,$AI$3,data_event_accrual!$C:$C,"20-39",data_event_accrual!$E:$E,$AH10),AVERAGEIFS(data_event_accrual!$L:$L,data_event_accrual!$A:$A,"Hatchling Hideaway",data_event_accrual!$B:$B,$AI$3,data_event_accrual!$C:$C,"20-39",data_event_accrual!$E:$E,$AH10)),1)),COUNTIF($AV$5:$AV$9,"<="&bal*shr)))} | AN10: {=IF($AH10="","",IF(AM10=0,"{}",LET(m,AM10,s,MMULT(SEQUENCE(1,m,1,0),$B$12:$V$16),"{"&TEXTJOIN(", ",TRUE,IF(s>0,$B$11:$V$11&": "&ROUND(s,2),""))&"}")))} | AO10: {=IF($AH10="","",LET(bal,SUMIFS(data_event_inst!$N:$N,data_event_inst!$A:$A,"Hatchling Hideaway",data_event_inst!$B:$B,$AI$3,data_event_inst!$C:$C,"40-99"),shr,MIN(1,IFERROR(CHOOSE(MATCH($AI$2,{"Avg","p25","p50","p75"},0),AVERAGEIFS(data_event_accrual!$I:$I,data_event_accrual!$A:$A,"Hatchling Hideaway",data_event_accrual!$B:$B,$AI$3,data_event_accrual!$C:$C,"40-99",data_event_accrual!$E:$E,$AH10),AVERAGEIFS(data_event_accrual!$K:$K,data_event_accrual!$A:$A,"Hatchling Hideaway",data_event_accrual!$B:$B,$AI$3,data_event_accrual!$C:$C,"40-99",data_event_accrual!$E:$E,$AH10),AVERAGEIFS(data_event_accrual!$J:$J,data_event_accrual!$A:$A,"Hatchling Hideaway",data_event_accrual!$B:$B,$AI$3,data_event_accrual!$C:$C,"40-99",data_event_accrual!$E:$E,$AH10),AVERAGEIFS(data_event_accrual!$L:$L,data_event_accrual!$A:$A,"Hatchling Hideaway",data_event_accrual!$B:$B,$AI$3,data_event_accrual!$C:$C,"40-99",data_event_accrual!$E:$E,$AH10)),1)),COUNTIF($AV$5:$AV$9,"<="&bal*shr)))} | AP10: {=IF($AH10="","",IF(AO10=0,"{}",LET(m,AO10,s,MMULT(SEQUENCE(1,m,1,0),$B$12:$V$16),"{"&TEXTJOIN(", ",TRUE,IF(s>0,$B$11:$V$11&": "&ROUND(s,2),""))&"}")))} | AQ10: {=IF($AH10="","",LET(bal,SUMIFS(data_event_inst!$N:$N,data_event_inst!$A:$A,"Hatchling Hideaway",data_event_inst!$B:$B,$AI$3,data_event_inst!$C:$C,"100+"),shr,MIN(1,IFERROR(CHOOSE(MATCH($AI$2,{"Avg","p25","p50","p75"},0),AVERAGEIFS(data_event_accrual!$I:$I,data_event_accrual!$A:$A,"Hatchling Hideaway",data_event_accrual!$B:$B,$AI$3,data_event_accrual!$C:$C,"100+",data_event_accrual!$E:$E,$AH10),AVERAGEIFS(data_event_accrual!$K:$K,data_event_accrual!$A:$A,"Hatchling Hideaway",data_event_accrual!$B:$B,$AI$3,data_event_accrual!$C:$C,"100+",data_event_accrual!$E:$E,$AH10),AVERAGEIFS(data_event_accrual!$J:$J,data_event_accrual!$A:$A,"Hatchling Hideaway",data_event_accrual!$B:$B,$AI$3,data_event_accrual!$C:$C,"100+",data_event_accrual!$E:$E,$AH10),AVERAGEIFS(data_event_accrual!$L:$L,data_event_accrual!$A:$A,"Hatchling Hideaway",data_event_accrual!$B:$B,$AI$3,data_event_accrual!$C:$C,"100+",data_event_accrual!$E:$E,$AH10)),1)),COUNTIF($AV$5:$AV$9,"<="&bal*shr)))} | AR10: {=IF($AH10="","",IF(AQ10=0,"{}",LET(m,AQ10,s,MMULT(SEQUENCE(1,m,1,0),$B$12:$V$16),"{"&TEXTJOIN(", ",TRUE,IF(s>0,$B$11:$V$11&": "&ROUND(s,2),""))&"}")))}
A11: Gate number | B11: Coins | C11: SPT | D11: SPT x2 | E11: Red | F11: Chuck | G11: Bomb | H11: Slingshot | I11: Shuffle | J11: Comet | K11: Unlimited Lives | L11: Unlimited Red | M11: Unlimited Chuck | N11: Unlimited Bomb | O11: COOP Token | P11: Avatar | Q11: 1-star Dly | R11: 2-star Dly | S11: 3-star Dly | T11: 4-star Dly | U11: 5-star Dly | V11: 6-star Dly | AH11: =IF(6<=$B$3,6,"") | AI11: {=IF($AH11="","",LET(bal,SUMIFS(data_event_inst!$N:$N,data_event_inst!$A:$A,"Hatchling Hideaway",data_event_inst!$B:$B,$AI$3,data_event_inst!$C:$C,"0-9"),shr,MIN(1,IFERROR(CHOOSE(MATCH($AI$2,{"Avg","p25","p50","p75"},0),AVERAGEIFS(data_event_accrual!$I:$I,data_event_accrual!$A:$A,"Hatchling Hideaway",data_event_accrual!$B:$B,$AI$3,data_event_accrual!$C:$C,"0-9",data_event_accrual!$E:$E,$AH11),AVERAGEIFS(data_event_accrual!$K:$K,data_event_accrual!$A:$A,"Hatchling Hideaway",data_event_accrual!$B:$B,$AI$3,data_event_accrual!$C:$C,"0-9",data_event_accrual!$E:$E,$AH11),AVERAGEIFS(data_event_accrual!$J:$J,data_event_accrual!$A:$A,"Hatchling Hideaway",data_event_accrual!$B:$B,$AI$3,data_event_accrual!$C:$C,"0-9",data_event_accrual!$E:$E,$AH11),AVERAGEIFS(data_event_accrual!$L:$L,data_event_accrual!$A:$A,"Hatchling Hideaway",data_event_accrual!$B:$B,$AI$3,data_event_accrual!$C:$C,"0-9",data_event_accrual!$E:$E,$AH11)),1)),COUNTIF($AV$5:$AV$9,"<="&bal*shr)))} | AJ11: {=IF($AH11="","",IF(AI11=0,"{}",LET(m,AI11,s,MMULT(SEQUENCE(1,m,1,0),$B$12:$V$16),"{"&TEXTJOIN(", ",TRUE,IF(s>0,$B$11:$V$11&": "&ROUND(s,2),""))&"}")))} | AK11: {=IF($AH11="","",LET(bal,SUMIFS(data_event_inst!$N:$N,data_event_inst!$A:$A,"Hatchling Hideaway",data_event_inst!$B:$B,$AI$3,data_event_inst!$C:$C,"10-19"),shr,MIN(1,IFERROR(CHOOSE(MATCH($AI$2,{"Avg","p25","p50","p75"},0),AVERAGEIFS(data_event_accrual!$I:$I,data_event_accrual!$A:$A,"Hatchling Hideaway",data_event_accrual!$B:$B,$AI$3,data_event_accrual!$C:$C,"10-19",data_event_accrual!$E:$E,$AH11),AVERAGEIFS(data_event_accrual!$K:$K,data_event_accrual!$A:$A,"Hatchling Hideaway",data_event_accrual!$B:$B,$AI$3,data_event_accrual!$C:$C,"10-19",data_event_accrual!$E:$E,$AH11),AVERAGEIFS(data_event_accrual!$J:$J,data_event_accrual!$A:$A,"Hatchling Hideaway",data_event_accrual!$B:$B,$AI$3,data_event_accrual!$C:$C,"10-19",data_event_accrual!$E:$E,$AH11),AVERAGEIFS(data_event_accrual!$L:$L,data_event_accrual!$A:$A,"Hatchling Hideaway",data_event_accrual!$B:$B,$AI$3,data_event_accrual!$C:$C,"10-19",data_event_accrual!$E:$E,$AH11)),1)),COUNTIF($AV$5:$AV$9,"<="&bal*shr)))} | AL11: {=IF($AH11="","",IF(AK11=0,"{}",LET(m,AK11,s,MMULT(SEQUENCE(1,m,1,0),$B$12:$V$16),"{"&TEXTJOIN(", ",TRUE,IF(s>0,$B$11:$V$11&": "&ROUND(s,2),""))&"}")))} | AM11: {=IF($AH11="","",LET(bal,SUMIFS(data_event_inst!$N:$N,data_event_inst!$A:$A,"Hatchling Hideaway",data_event_inst!$B:$B,$AI$3,data_event_inst!$C:$C,"20-39"),shr,MIN(1,IFERROR(CHOOSE(MATCH($AI$2,{"Avg","p25","p50","p75"},0),AVERAGEIFS(data_event_accrual!$I:$I,data_event_accrual!$A:$A,"Hatchling Hideaway",data_event_accrual!$B:$B,$AI$3,data_event_accrual!$C:$C,"20-39",data_event_accrual!$E:$E,$AH11),AVERAGEIFS(data_event_accrual!$K:$K,data_event_accrual!$A:$A,"Hatchling Hideaway",data_event_accrual!$B:$B,$AI$3,data_event_accrual!$C:$C,"20-39",data_event_accrual!$E:$E,$AH11),AVERAGEIFS(data_event_accrual!$J:$J,data_event_accrual!$A:$A,"Hatchling Hideaway",data_event_accrual!$B:$B,$AI$3,data_event_accrual!$C:$C,"20-39",data_event_accrual!$E:$E,$AH11),AVERAGEIFS(data_event_accrual!$L:$L,data_event_accrual!$A:$A,"Hatchling Hideaway",data_event_accrual!$B:$B,$AI$3,data_event_accrual!$C:$C,"20-39",data_event_accrual!$E:$E,$AH11)),1)),COUNTIF($AV$5:$AV$9,"<="&bal*shr)))} | AN11: {=IF($AH11="","",IF(AM11=0,"{}",LET(m,AM11,s,MMULT(SEQUENCE(1,m,1,0),$B$12:$V$16),"{"&TEXTJOIN(", ",TRUE,IF(s>0,$B$11:$V$11&": "&ROUND(s,2),""))&"}")))} | AO11: {=IF($AH11="","",LET(bal,SUMIFS(data_event_inst!$N:$N,data_event_inst!$A:$A,"Hatchling Hideaway",data_event_inst!$B:$B,$AI$3,data_event_inst!$C:$C,"40-99"),shr,MIN(1,IFERROR(CHOOSE(MATCH($AI$2,{"Avg","p25","p50","p75"},0),AVERAGEIFS(data_event_accrual!$I:$I,data_event_accrual!$A:$A,"Hatchling Hideaway",data_event_accrual!$B:$B,$AI$3,data_event_accrual!$C:$C,"40-99",data_event_accrual!$E:$E,$AH11),AVERAGEIFS(data_event_accrual!$K:$K,data_event_accrual!$A:$A,"Hatchling Hideaway",data_event_accrual!$B:$B,$AI$3,data_event_accrual!$C:$C,"40-99",data_event_accrual!$E:$E,$AH11),AVERAGEIFS(data_event_accrual!$J:$J,data_event_accrual!$A:$A,"Hatchling Hideaway",data_event_accrual!$B:$B,$AI$3,data_event_accrual!$C:$C,"40-99",data_event_accrual!$E:$E,$AH11),AVERAGEIFS(data_event_accrual!$L:$L,data_event_accrual!$A:$A,"Hatchling Hideaway",data_event_accrual!$B:$B,$AI$3,data_event_accrual!$C:$C,"40-99",data_event_accrual!$E:$E,$AH11)),1)),COUNTIF($AV$5:$AV$9,"<="&bal*shr)))} | AP11: {=IF($AH11="","",IF(AO11=0,"{}",LET(m,AO11,s,MMULT(SEQUENCE(1,m,1,0),$B$12:$V$16),"{"&TEXTJOIN(", ",TRUE,IF(s>0,$B$11:$V$11&": "&ROUND(s,2),""))&"}")))} | AQ11: {=IF($AH11="","",LET(bal,SUMIFS(data_event_inst!$N:$N,data_event_inst!$A:$A,"Hatchling Hideaway",data_event_inst!$B:$B,$AI$3,data_event_inst!$C:$C,"100+"),shr,MIN(1,IFERROR(CHOOSE(MATCH($AI$2,{"Avg","p25","p50","p75"},0),AVERAGEIFS(data_event_accrual!$I:$I,data_event_accrual!$A:$A,"Hatchling Hideaway",data_event_accrual!$B:$B,$AI$3,data_event_accrual!$C:$C,"100+",data_event_accrual!$E:$E,$AH11),AVERAGEIFS(data_event_accrual!$K:$K,data_event_accrual!$A:$A,"Hatchling Hideaway",data_event_accrual!$B:$B,$AI$3,data_event_accrual!$C:$C,"100+",data_event_accrual!$E:$E,$AH11),AVERAGEIFS(data_event_accrual!$J:$J,data_event_accrual!$A:$A,"Hatchling Hideaway",data_event_accrual!$B:$B,$AI$3,data_event_accrual!$C:$C,"100+",data_event_accrual!$E:$E,$AH11),AVERAGEIFS(data_event_accrual!$L:$L,data_event_accrual!$A:$A,"Hatchling Hideaway",data_event_accrual!$B:$B,$AI$3,data_event_accrual!$C:$C,"100+",data_event_accrual!$E:$E,$AH11)),1)),COUNTIF($AV$5:$AV$9,"<="&bal*shr)))} | AR11: {=IF($AH11="","",IF(AQ11=0,"{}",LET(m,AQ11,s,MMULT(SEQUENCE(1,m,1,0),$B$12:$V$16),"{"&TEXTJOIN(", ",TRUE,IF(s>0,$B$11:$V$11&": "&ROUND(s,2),""))&"}")))}
A12: Gate 1 | B12: 0 | C12: 0 | D12: 0 | E12: 1 | F12: 0 | G12: 0 | H12: 0 | I12: 0 | J12: 0 | K12: 60 | L12: 0 | M12: 0 | N12: 0 | O12: 5 | P12: 0 | Q12: 0 | R12: 0 | S12: 0 | T12: 0 | U12: 0 | V12: 0 | AH12: =IF(7<=$B$3,7,"") | AI12: {=IF($AH12="","",LET(bal,SUMIFS(data_event_inst!$N:$N,data_event_inst!$A:$A,"Hatchling Hideaway",data_event_inst!$B:$B,$AI$3,data_event_inst!$C:$C,"0-9"),shr,MIN(1,IFERROR(CHOOSE(MATCH($AI$2,{"Avg","p25","p50","p75"},0),AVERAGEIFS(data_event_accrual!$I:$I,data_event_accrual!$A:$A,"Hatchling Hideaway",data_event_accrual!$B:$B,$AI$3,data_event_accrual!$C:$C,"0-9",data_event_accrual!$E:$E,$AH12),AVERAGEIFS(data_event_accrual!$K:$K,data_event_accrual!$A:$A,"Hatchling Hideaway",data_event_accrual!$B:$B,$AI$3,data_event_accrual!$C:$C,"0-9",data_event_accrual!$E:$E,$AH12),AVERAGEIFS(data_event_accrual!$J:$J,data_event_accrual!$A:$A,"Hatchling Hideaway",data_event_accrual!$B:$B,$AI$3,data_event_accrual!$C:$C,"0-9",data_event_accrual!$E:$E,$AH12),AVERAGEIFS(data_event_accrual!$L:$L,data_event_accrual!$A:$A,"Hatchling Hideaway",data_event_accrual!$B:$B,$AI$3,data_event_accrual!$C:$C,"0-9",data_event_accrual!$E:$E,$AH12)),1)),COUNTIF($AV$5:$AV$9,"<="&bal*shr)))} | AJ12: {=IF($AH12="","",IF(AI12=0,"{}",LET(m,AI12,s,MMULT(SEQUENCE(1,m,1,0),$B$12:$V$16),"{"&TEXTJOIN(", ",TRUE,IF(s>0,$B$11:$V$11&": "&ROUND(s,2),""))&"}")))} | AK12: {=IF($AH12="","",LET(bal,SUMIFS(data_event_inst!$N:$N,data_event_inst!$A:$A,"Hatchling Hideaway",data_event_inst!$B:$B,$AI$3,data_event_inst!$C:$C,"10-19"),shr,MIN(1,IFERROR(CHOOSE(MATCH($AI$2,{"Avg","p25","p50","p75"},0),AVERAGEIFS(data_event_accrual!$I:$I,data_event_accrual!$A:$A,"Hatchling Hideaway",data_event_accrual!$B:$B,$AI$3,data_event_accrual!$C:$C,"10-19",data_event_accrual!$E:$E,$AH12),AVERAGEIFS(data_event_accrual!$K:$K,data_event_accrual!$A:$A,"Hatchling Hideaway",data_event_accrual!$B:$B,$AI$3,data_event_accrual!$C:$C,"10-19",data_event_accrual!$E:$E,$AH12),AVERAGEIFS(data_event_accrual!$J:$J,data_event_accrual!$A:$A,"Hatchling Hideaway",data_event_accrual!$B:$B,$AI$3,data_event_accrual!$C:$C,"10-19",data_event_accrual!$E:$E,$AH12),AVERAGEIFS(data_event_accrual!$L:$L,data_event_accrual!$A:$A,"Hatchling Hideaway",data_event_accrual!$B:$B,$AI$3,data_event_accrual!$C:$C,"10-19",data_event_accrual!$E:$E,$AH12)),1)),COUNTIF($AV$5:$AV$9,"<="&bal*shr)))} | AL12: {=IF($AH12="","",IF(AK12=0,"{}",LET(m,AK12,s,MMULT(SEQUENCE(1,m,1,0),$B$12:$V$16),"{"&TEXTJOIN(", ",TRUE,IF(s>0,$B$11:$V$11&": "&ROUND(s,2),""))&"}")))} | AM12: {=IF($AH12="","",LET(bal,SUMIFS(data_event_inst!$N:$N,data_event_inst!$A:$A,"Hatchling Hideaway",data_event_inst!$B:$B,$AI$3,data_event_inst!$C:$C,"20-39"),shr,MIN(1,IFERROR(CHOOSE(MATCH($AI$2,{"Avg","p25","p50","p75"},0),AVERAGEIFS(data_event_accrual!$I:$I,data_event_accrual!$A:$A,"Hatchling Hideaway",data_event_accrual!$B:$B,$AI$3,data_event_accrual!$C:$C,"20-39",data_event_accrual!$E:$E,$AH12),AVERAGEIFS(data_event_accrual!$K:$K,data_event_accrual!$A:$A,"Hatchling Hideaway",data_event_accrual!$B:$B,$AI$3,data_event_accrual!$C:$C,"20-39",data_event_accrual!$E:$E,$AH12),AVERAGEIFS(data_event_accrual!$J:$J,data_event_accrual!$A:$A,"Hatchling Hideaway",data_event_accrual!$B:$B,$AI$3,data_event_accrual!$C:$C,"20-39",data_event_accrual!$E:$E,$AH12),AVERAGEIFS(data_event_accrual!$L:$L,data_event_accrual!$A:$A,"Hatchling Hideaway",data_event_accrual!$B:$B,$AI$3,data_event_accrual!$C:$C,"20-39",data_event_accrual!$E:$E,$AH12)),1)),COUNTIF($AV$5:$AV$9,"<="&bal*shr)))} | AN12: {=IF($AH12="","",IF(AM12=0,"{}",LET(m,AM12,s,MMULT(SEQUENCE(1,m,1,0),$B$12:$V$16),"{"&TEXTJOIN(", ",TRUE,IF(s>0,$B$11:$V$11&": "&ROUND(s,2),""))&"}")))} | AO12: {=IF($AH12="","",LET(bal,SUMIFS(data_event_inst!$N:$N,data_event_inst!$A:$A,"Hatchling Hideaway",data_event_inst!$B:$B,$AI$3,data_event_inst!$C:$C,"40-99"),shr,MIN(1,IFERROR(CHOOSE(MATCH($AI$2,{"Avg","p25","p50","p75"},0),AVERAGEIFS(data_event_accrual!$I:$I,data_event_accrual!$A:$A,"Hatchling Hideaway",data_event_accrual!$B:$B,$AI$3,data_event_accrual!$C:$C,"40-99",data_event_accrual!$E:$E,$AH12),AVERAGEIFS(data_event_accrual!$K:$K,data_event_accrual!$A:$A,"Hatchling Hideaway",data_event_accrual!$B:$B,$AI$3,data_event_accrual!$C:$C,"40-99",data_event_accrual!$E:$E,$AH12),AVERAGEIFS(data_event_accrual!$J:$J,data_event_accrual!$A:$A,"Hatchling Hideaway",data_event_accrual!$B:$B,$AI$3,data_event_accrual!$C:$C,"40-99",data_event_accrual!$E:$E,$AH12),AVERAGEIFS(data_event_accrual!$L:$L,data_event_accrual!$A:$A,"Hatchling Hideaway",data_event_accrual!$B:$B,$AI$3,data_event_accrual!$C:$C,"40-99",data_event_accrual!$E:$E,$AH12)),1)),COUNTIF($AV$5:$AV$9,"<="&bal*shr)))} | AP12: {=IF($AH12="","",IF(AO12=0,"{}",LET(m,AO12,s,MMULT(SEQUENCE(1,m,1,0),$B$12:$V$16),"{"&TEXTJOIN(", ",TRUE,IF(s>0,$B$11:$V$11&": "&ROUND(s,2),""))&"}")))} | AQ12: {=IF($AH12="","",LET(bal,SUMIFS(data_event_inst!$N:$N,data_event_inst!$A:$A,"Hatchling Hideaway",data_event_inst!$B:$B,$AI$3,data_event_inst!$C:$C,"100+"),shr,MIN(1,IFERROR(CHOOSE(MATCH($AI$2,{"Avg","p25","p50","p75"},0),AVERAGEIFS(data_event_accrual!$I:$I,data_event_accrual!$A:$A,"Hatchling Hideaway",data_event_accrual!$B:$B,$AI$3,data_event_accrual!$C:$C,"100+",data_event_accrual!$E:$E,$AH12),AVERAGEIFS(data_event_accrual!$K:$K,data_event_accrual!$A:$A,"Hatchling Hideaway",data_event_accrual!$B:$B,$AI$3,data_event_accrual!$C:$C,"100+",data_event_accrual!$E:$E,$AH12),AVERAGEIFS(data_event_accrual!$J:$J,data_event_accrual!$A:$A,"Hatchling Hideaway",data_event_accrual!$B:$B,$AI$3,data_event_accrual!$C:$C,"100+",data_event_accrual!$E:$E,$AH12),AVERAGEIFS(data_event_accrual!$L:$L,data_event_accrual!$A:$A,"Hatchling Hideaway",data_event_accrual!$B:$B,$AI$3,data_event_accrual!$C:$C,"100+",data_event_accrual!$E:$E,$AH12)),1)),COUNTIF($AV$5:$AV$9,"<="&bal*shr)))} | AR12: {=IF($AH12="","",IF(AQ12=0,"{}",LET(m,AQ12,s,MMULT(SEQUENCE(1,m,1,0),$B$12:$V$16),"{"&TEXTJOIN(", ",TRUE,IF(s>0,$B$11:$V$11&": "&ROUND(s,2),""))&"}")))}
A13: Gate 2 | B13: 10 | C13: 0 | D13: 0 | E13: 0 | F13: 1 | G13: 0 | H13: 0 | I13: 0 | J13: 0 | K13: 0 | L13: 0 | M13: 0 | N13: 0 | O13: 10 | P13: 0 | Q13: 0 | R13: 0 | S13: 0 | T13: 0 | U13: 0 | V13: 0
A14: Gate 3 | B14: 0 | C14: 0 | D14: 0 | E14: 0 | F14: 0 | G14: 1 | H14: 0 | I14: 0 | J14: 1 | K14: 30 | L14: 0 | M14: 0 | N14: 0 | O14: 20 | P14: 0 | Q14: 0 | R14: 0 | S14: 0 | T14: 0 | U14: 0 | V14: 0
A15: Gate 4 | B15: 15 | C15: 0 | D15: 0 | E15: 0 | F15: 0 | G15: 0 | H15: 0 | I15: 1 | J15: 0 | K15: 0 | L15: 10 | M15: 0 | N15: 0 | O15: 50 | P15: 0 | Q15: 0 | R15: 0 | S15: 0 | T15: 0 | U15: 0 | V15: 0
A16: Gate 5 | B16: 40 | C16: 0 | D16: 0 | E16: 0 | F16: 0 | G16: 0 | H16: 1 | I16: 0 | J16: 0 | K16: 0 | L16: 0 | M16: 10 | N16: 0 | O16: 70 | P16: 0 | Q16: 0 | R16: 0 | S16: 0 | T16: 0 | U16: 0 | V16: 0

Sheet BB
A1: Bomb's Ballet
A2: Config Panel
A3: EventDuration (days) | B3: 4
A4: tokensPerLevel | B4: 5
A5: spawnTokensOnlyOnFirstTry | B5: =TRUE() -> TRUE
A7: Goals and Rewards
A8: Reward level | B8: price | C8: Coins | D8: SPT | E8: SPT x2 | F8: Red | G8: Chuck | H8: Bomb | I8: Slingshot | J8: Shuffle | K8: Comet | L8: Unlimited Lives | M8: Unlimited Red | N8: Unlimited Chuck | O8: Unlimited Bomb | P8: COOP Token | Q8: Avatar | R8: 1-star Dly | S8: 2-star Dly | T8: 3-star Dly | U8: 4-star Dly | V8: 5-star Dly | W8: 6-star Dly
A9: 1 | B9: 15 | C9: 0 | D9: 0 | E9: 0 | F9: 0 | G9: 1 | H9: 0 | I9: 0 | J9: 0 | K9: 0 | L9: 0 | M9: 0 | N9: 0 | O9: 0 | P9: 0 | Q9: 0 | R9: 0 | S9: 0 | T9: 0 | U9: 0 | V9: 0 | W9: 0
A10: 2 | B10: 40 | C10: 0 | D10: 0 | E10: 0 | F10: 0 | G10: 0 | H10: 0 | I10: 0 | J10: 0 | K10: 0 | L10: 0 | M10: 10 | N10: 0 | O10: 0 | P10: 0 | Q10: 0 | R10: 0 | S10: 0 | T10: 0 | U10: 0 | V10: 0 | W10: 0
A11: 3 | B11: 70 | C11: 0 | D11: 0 | E11: 0 | F11: 0 | G11: 0 | H11: 0 | I11: 0 | J11: 0 | K11: 0 | L11: 0 | M11: 0 | N11: 10 | O11: 0 | P11: 0 | Q11: 0 | R11: 0 | S11: 0 | T11: 0 | U11: 0 | V11: 0 | W11: 0
A12: 4 | B12: 110 | C12: 0 | D12: 0 | E12: 0 | F12: 0 | G12: 0 | H12: 0 | I12: 0 | J12: 0 | K12: 0 | L12: 30 | M12: 0 | N12: 0 | O12: 0 | P12: 0 | Q12: 0 | R12: 0 | S12: 0 | T12: 0 | U12: 0 | V12: 0 | W12: 0
A13: 5 | B13: 160 | C13: 25 | D13: 0 | E13: 0 | F13: 0 | G13: 0 | H13: 0 | I13: 0 | J13: 0 | K13: 0 | L13: 0 | M13: 0 | N13: 0 | O13: 0 | P13: 0 | Q13: 0 | R13: 0 | S13: 0 | T13: 0 | U13: 0 | V13: 0 | W13: 0
A14: 6 | B14: 220 | C14: 0 | D14: 0 | E14: 0 | F14: 0 | G14: 0 | H14: 0 | I14: 0 | J14: 0 | K14: 0 | L14: 0 | M14: 0 | N14: 0 | O14: 10 | P14: 0 | Q14: 0 | R14: 0 | S14: 0 | T14: 0 | U14: 0 | V14: 0 | W14: 0
A15: 7 | B15: 290 | C15: 0 | D15: 0 | E15: 0 | F15: 1 | G15: 0 | H15: 0 | I15: 0 | J15: 0 | K15: 0 | L15: 0 | M15: 0 | N15: 0 | O15: 0 | P15: 0 | Q15: 0 | R15: 0 | S15: 0 | T15: 0 | U15: 0 | V15: 0 | W15: 0
A16: 8 | B16: 370 | C16: 0 | D16: 0 | E16: 0 | F16: 0 | G16: 0 | H16: 0 | I16: 0 | J16: 0 | K16: 0 | L16: 60 | M16: 0 | N16: 0 | O16: 0 | P16: 0 | Q16: 0 | R16: 0 | S16: 0 | T16: 0 | U16: 0 | V16: 0 | W16: 0
A17: 9 | B17: 460 | C17: 0 | D17: 0 | E17: 0 | F17: 0 | G17: 0 | H17: 0 | I17: 0 | J17: 0 | K17: 0 | L17: 0 | M17: 15 | N17: 0 | O17: 0 | P17: 0 | Q17: 0 | R17: 0 | S17: 0 | T17: 0 | U17: 0 | V17: 0 | W17: 0
A18: 10 | B18: 560 | C18: 25 | D18: 0 | E18: 0 | F18: 0 | G18: 0 | H18: 0 | I18: 0 | J18: 0 | K18: 0 | L18: 0 | M18: 0 | N18: 0 | O18: 0 | P18: 0 | Q18: 0 | R18: 0 | S18: 0 | T18: 0 | U18: 0 | V18: 0 | W18: 0
A19: 11 | B19: 670 | C19: 0 | D19: 0 | E19: 0 | F19: 0 | G19: 0 | H19: 0 | I19: 0 | J19: 0 | K19: 0 | L19: 0 | M19: 0 | N19: 15 | O19: 0 | P19: 0 | Q19: 0 | R19: 0 | S19: 0 | T19: 0 | U19: 0 | V19: 0 | W19: 0
A20: 12 | B20: 790 | C20: 0 | D20: 0 | E20: 0 | F20: 0 | G20: 0 | H20: 0 | I20: 0 | J20: 0 | K20: 0 | L20: 0 | M20: 0 | N20: 0 | O20: 15 | P20: 0 | Q20: 0 | R20: 0 | S20: 0 | T20: 0 | U20: 0 | V20: 0 | W20: 0
... A23: 15 | B23: 1210 | C23: 0 | D23: 0 | E23: 0 | F23: 0 | G23: 0 | H23: 0 | I23: 0 | J23: 1 | K23: 0 | L23: 0 | M23: 0 | N23: 0 | O23: 0 | P23: 0 | Q23: 0 | R23: 0 | S23: 0 | T23: 0 | U23: 0 | V23: 0 | W23: 0
A24: Completion reward | C24: 50 | D24: 0 | E24: 0 | F24: 0 | G24: 0 | H24: 1 | I24: 0 | J24: 0 | K24: 1 | L24: 0 | M24: 0 | N24: 0 | O24: 0 | P24: 0 | Q24: 0 | R24: 0 | S24: 0 | T24: 0 | U24: 0 | V24: 0 | W24: 0

Sheet BB_v2
A1: Bomb's Ballet | AH1: Player Reach Simulation (per event day) - SIMULATED
A2: Config Panel | AH2: Percentile | AI2: p50
A3: EventDuration (days) | B3: 3 | AH3: Payer | AI3: NONPAYER
A4: tokensPerLevel | B4: 5
A5: spawnTokensOnlyOnFirstTry | B5: =TRUE() -> TRUE | AH5: Day_of_event | AI5: 0-9_ms | AJ5: 0-9_reward | AK5: 10-19_ms | AL5: 10-19_reward | AM5: 20-39_ms | AN5: 20-39_reward | AO5: 40-99_ms | AP5: 40-99_reward | AQ5: 100_ms | AR5: 100_reward
AH6: =IF(1<=$B$3,1,"") -> 1 | AI6: {=IF($AH6="","",LET(bal,SUMIFS(data_event_inst!$N:$N,data_event_inst!$A:$A,"Bombs Ballet",data_event_inst!$B:$B,$AI$3,data_event_inst!$C:$C,"0-9"),shr,MIN(1,IFERROR(CHOOSE(MATCH($AI$2,{"Avg","p25","p50","p75"},0),AVERAGEIFS(data_event_accrual!$I:$I,data_event_accrual!$A:$A,"Bombs Ballet",data_event_accrual!$B:$B,$AI$3,data_event_accrual!$C:$C,"0-9",data_event_accrual!$E:$E,$AH6),AVERAGEIFS(data_event_accrual!$K:$K,data_event_accrual!$A:$A,"Bombs Ballet",data_event_accrual!$B:$B,$AI$3,data_event_accrual!$C:$C,"0-9",data_event_accrual!$E:$E,$AH6),AVERAGEIFS(data_event_accrual!$J:$J,data_event_accrual!$A:$A,"Bombs Ballet",data_event_accrual!$B:$B,$AI$3,data_event_accrual!$C:$C,"0-9",data_event_accrual!$E:$E,$AH6),AVERAGEIFS(data_event_accrual!$L:$L,data_event_accrual!$A:$A,"Bombs Ballet",data_event_accrual!$B:$B,$AI$3,data_event_accrual!$C:$C,"0-9",data_event_accrual!$E:$E,$AH6)),1)),COUNTIF($B$9:$B$23,"<="&bal*shr)))} -> 0 | AJ6: {=IF($AH6="","",IF(AI6=0,"{}",LET(m,IF(AI6=15,16,AI6),s,MMULT(SEQUENCE(1,m,1,0),$C$9:$W$24),"{"&TEXTJOIN(", ",TRUE,IF(s>0,$C$8:$W$8&": "&ROUND(s,2),""))&"}")))} -> {} | AK6: {=IF($AH6="","",LET(bal,SUMIFS(data_event_inst!$N:$N,data_event_inst!$A:$A,"Bombs Ballet",data_event_inst!$B:$B,$AI$3,data_event_inst!$C:$C,"10-19"),shr,MIN(1,IFERROR(CHOOSE(MATCH($AI$2,{"Avg","p25","p50","p75"},0),AVERAGEIFS(data_event_accrual!$I:$I,data_event_accrual!$A:$A,"Bombs Ballet",data_event_accrual!$B:$B,$AI$3,data_event_accrual!$C:$C,"10-19",data_event_accrual!$E:$E,$AH6),AVERAGEIFS(data_event_accrual!$K:$K,data_event_accrual!$A:$A,"Bombs Ballet",data_event_accrual!$B:$B,$AI$3,data_event_accrual!$C:$C,"10-19",data_event_accrual!$E:$E,$AH6),AVERAGEIFS(data_event_accrual!$J:$J,data_event_accrual!$A:$A,"Bombs Ballet",data_event_accrual!$B:$B,$AI$3,data_event_accrual!$C:$C,"10-19",data_event_accrual!$E:$E,$AH6),AVERAGEIFS(data_event_accrual!$L:$L,data_event_accrual!$A:$A,"Bombs Ballet",data_event_accrual!$B:$B,$AI$3,data_event_accrual!$C:$C,"10-19",data_event_accrual!$E:$E,$AH6)),1)),COUNTIF($B$9:$B$23,"<="&bal*shr)))} -> 1 | AL6: {=IF($AH6="","",IF(AK6=0,"{}",LET(m,IF(AK6=15,16,AK6),s,MMULT(SEQUENCE(1,m,1,0),$C$9:$W$24),"{"&TEXTJOIN(", ",TRUE,IF(s>0,$C$8:$W$8&": "&ROUND(s,2),""))&"}")))} -> {Chuck: 1} | AM6: {=IF($AH6="","",LET(bal,SUMIFS(data_event_inst!$N:$N,data_event_inst!$A:$A,"Bombs Ballet",data_event_inst!$B:$B,$AI$3,data_event_inst!$C:$C,"20-39"),shr,MIN(1,IFERROR(CHOOSE(MATCH($AI$2,{"Avg","p25","p50","p75"},0),AVERAGEIFS(data_event_accrual!$I:$I,data_event_accrual!$A:$A,"Bombs Ballet",data_event_accrual!$B:$B,$AI$3,data_event_accrual!$C:$C,"20-39",data_event_accrual!$E:$E,$AH6),AVERAGEIFS(data_event_accrual!$K:$K,data_event_accrual!$A:$A,"Bombs Ballet",data_event_accrual!$B:$B,$AI$3,data_event_accrual!$C:$C,"20-39",data_event_accrual!$E:$E,$AH6),AVERAGEIFS(data_event_accrual!$J:$J,data_event_accrual!$A:$A,"Bombs Ballet",data_event_accrual!$B:$B,$AI$3,data_event_accrual!$C:$C,"20-39",data_event_accrual!$E:$E,$AH6),AVERAGEIFS(data_event_accrual!$L:$L,data_event_accrual!$A:$A,"Bombs Ballet",data_event_accrual!$B:$B,$AI$3,data_event_accrual!$C:$C,"20-39",data_event_accrual!$E:$E,$AH6)),1)),COUNTIF($B$9:$B$23,"<="&bal*shr)))} -> 2 | AN6: {=IF($AH6="","",IF(AM6=0,"{}",LET(m,IF(AM6=15,16,AM6),s,MMULT(SEQUENCE(1,m,1,0),$C$9:$W$24),"{"&TEXTJOIN(", ",TRUE,IF(s>0,$C$8:$W$8&": "&ROUND(s,2),""))&"}")))} -> {Chuck: 1, Unlimited Red: 10} | AO6: {=IF($AH6="","",LET(bal,SUMIFS(data_event_inst!$N:$N,data_event_inst!$A:$A,"Bombs Ballet",data_event_inst!$B:$B,$AI$3,data_event_inst!$C:$C,"40-99"),shr,MIN(1,IFERROR(CHOOSE(MATCH($AI$2,{"Avg","p25","p50","p75"},0),AVERAGEIFS(data_event_accrual!$I:$I,data_event_accrual!$A:$A,"Bombs Ballet",data_event_accrual!$B:$B,$AI$3,data_event_accrual!$C:$C,"40-99",data_event_accrual!$E:$E,$AH6),AVERAGEIFS(data_event_accrual!$K:$K,data_event_accrual!$A:$A,"Bombs Ballet",data_event_accrual!$B:$B,$AI$3,data_event_accrual!$C:$C,"40-99",data_event_accrual!$E:$E,$AH6),AVERAGEIFS(data_event_accrual!$J:$J,data_event_accrual!$A:$A,"Bombs Ballet",data_event_accrual!$B:$B,$AI$3,data_event_accrual!$C:$C,"40-99",data_event_accrual!$E:$E,$AH6),AVERAGEIFS(data_event_accrual!$L:$L,data_event_accrual!$A:$A,"Bombs Ballet",data_event_accrual!$B:$B,$AI$3,data_event_accrual!$C:$C,"40-99",data_event_accrual!$E:$E,$AH6)),1)),COUNTIF($B$9:$B$23,"<="&bal*shr)))} -> 5 | AP6: {=IF($AH6="","",IF(AO6=0,"{}",LET(m,IF(AO6=15,16,AO6),s,MMULT(SEQUENCE(1,m,1,0),$C$9:$W$24),"{"&TEXTJOIN(", ",TRUE,IF(s>0,$C$8:$W$8&": "&ROUND(s,2),""))&"}")))} -> {Coins: 25, Chuck: 1, Unlimited Lives: 30, Unlimited Red: 10, Unlimited Chuck: 10} | AQ6: {=IF($AH6="","",LET(bal,SUMIFS(data_event_inst!$N:$N,data_event_inst!$A:$A,"Bombs Ballet",data_event_inst!$B:$B,$AI$3,data_event_inst!$C:$C,"100+"),shr,MIN(1,IFERROR(CHOOSE(MATCH($AI$2,{"Avg","p25","p50","p75"},0),AVERAGEIFS(data_event_accrual!$I:$I,data_event_accrual!$A:$A,"Bombs Ballet",data_event_accrual!$B:$B,$AI$3,data_event_accrual!$C:$C,"100+",data_event_accrual!$E:$E,$AH6),AVERAGEIFS(data_event_accrual!$K:$K,data_event_accrual!$A:$A,"Bombs Ballet",data_event_accrual!$B:$B,$AI$3,data_event_accrual!$C:$C,"100+",data_event_accrual!$E:$E,$AH6),AVERAGEIFS(data_event_accrual!$J:$J,data_event_accrual!$A:$A,"Bombs Ballet",data_event_accrual!$B:$B,$AI$3,data_event_accrual!$C:$C,"100+",data_event_accrual!$E:$E,$AH6),AVERAGEIFS(data_event_accrual!$L:$L,data_event_accrual!$A:$A,"Bombs Ballet",data_event_accrual!$B:$B,$AI$3,data_event_accrual!$C:$C,"100+",data_event_accrual!$E:$E,$AH6)),1)),COUNTIF($B$9:$B$23,"<="&bal*shr)))} -> 6 | AR6: {=IF($AH6="","",IF(AQ6=0,"{}",LET(m,IF(AQ6=15,16,AQ6),s,MMULT(SEQUENCE(1,m,1,0),$C$9:$W$24),"{"&TEXTJOIN(", ",TRUE,IF(s>0,$C$8:$W$8&": "&ROUND(s,2),""))&"}")))} -> {Coins: 25, Chuck: 1, Unlimited Lives: 30, Unlimited Red: 10, Unlimited Chuck: 10, Unlimited Bomb: 10}
